{"index": {"_index": "set_eod", "_type": "eod", "_id": "19961101_ABICO"}}
{"symbol": "ABICO", "eodDate": "1996-11-01T00:00:00", "open": 4.8, "high": 4.9, "low": 4.8, "close": 4.9, "volume": 4000, "id": "19961101_ABICO" }
{"index": {"_index": "set_eod", "_type": "eod", "_id": "19961101_ADVANC"}}
{"symbol": "ADVANC", "eodDate": "1996-11-01T00:00:00", "open": 34.6, "high": 35, "low": 34.6, "close": 35, "volume": 362830, "id": "19961101_ADVANC" }
{"index": {"_index": "set_eod", "_type": "eod", "_id": "19961101_AFC"}}
{"symbol": "AFC", "eodDate": "1996-11-01T00:00:00", "open": 9.6, "high": 9.6, "low": 9.6, "close": 9.6, "volume": 4000, "id": "19961101_AFC" }
{"index": {"_index": "set_eod", "_type": "eod", "_id": "19961101_AHC"}}
{"symbol": "AHC", "eodDate": "1996-11-01T00:00:00", "open": 23, "high": 23, "low": 23, "close": 23, "volume": 1800, "id": "19961101_AHC" }
{"index": {"_index": "set_eod", "_type": "eod", "_id": "19961101_AJ"}}
{"symbol": "AJ", "eodDate": "1996-11-01T00:00:00", "open": 0.95, "high": 0.98, "low": 0.95, "close": 0.98, "volume": 26000, "id": "19961101_AJ" }
{"index": {"_index": "set_eod", "_type": "eod", "_id": "19961101_AMARIN"}}
{"symbol": "AMARIN", "eodDate": "1996-11-01T00:00:00", "open": 3.65, "high": 3.675, "low": 3.625, "close": 3.675, "volume": 770000, "id": "19961101_AMARIN" }
{"index": {"_index": "set_eod", "_type": "eod", "_id": "19961101_AP"}}
{"symbol": "AP", "eodDate": "1996-11-01T00:00:00", "open": 1.575, "high": 1.575, "low": 1.375, "close": 1.375, "volume": 18000, "id": "19961101_AP" }
{"index": {"_index": "set_eod", "_type": "eod", "_id": "19961101_ASIA"}}
{"symbol": "ASIA", "eodDate": "1996-11-01T00:00:00", "open": 15.25, "high": 16, "low": 15.25, "close": 16, "volume": 6200, "id": "19961101_ASIA" }
{"index": {"_index": "set_eod", "_type": "eod", "_id": "19961101_ASIMAR"}}
{"symbol": "ASIMAR", "eodDate": "1996-11-01T00:00:00", "open": 2.3608, "high": 2.7185, "low": 2.3608, "close": 2.7185, "volume": 21666, "id": "19961101_ASIMAR" }
{"index": {"_index": "set_eod", "_type": "eod", "_id": "19961101_ASP"}}
{"symbol": "ASP", "eodDate": "1996-11-01T00:00:00", "open": 4.15, "high": 4.175, "low": 4.05, "close": 4.175, "volume": 392000, "id": "19961101_ASP" }
{"index": {"_index": "set_eod", "_type": "eod", "_id": "19961101_BANPU"}}
{"symbol": "BANPU", "eodDate": "1996-11-01T00:00:00", "open": 152.79, "high": 154.1, "low": 152.79, "close": 154.1, "volume": 19500, "id": "19961101_BANPU" }
{"index": {"_index": "set_eod", "_type": "eod", "_id": "19961101_BAT-3K"}}
{"symbol": "BAT-3K", "eodDate": "1996-11-01T00:00:00", "open": 73.5, "high": 73.5, "low": 73.5, "close": 73.5, "volume": 300, "id": "19961101_BAT-3K" }
{"index": {"_index": "set_eod", "_type": "eod", "_id": "19961101_BAY"}}
{"symbol": "BAY", "eodDate": "1996-11-01T00:00:00", "open": 63.504, "high": 64.368, "low": 63.072, "close": 64.368, "volume": 230063, "id": "19961101_BAY" }
{"index": {"_index": "set_eod", "_type": "eod", "_id": "19961101_BBL"}}
{"symbol": "BBL", "eodDate": "1996-11-01T00:00:00", "open": 190, "high": 194, "low": 190, "close": 194, "volume": 614200, "id": "19961101_BBL" }
{"index": {"_index": "set_eod", "_type": "eod", "_id": "19961101_BCP"}}
{"symbol": "BCP", "eodDate": "1996-11-01T00:00:00", "open": 26.25, "high": 27, "low": 26.25, "close": 27, "volume": 101400, "id": "19961101_BCP" }
{"index": {"_index": "set_eod", "_type": "eod", "_id": "19961101_BDMS"}}
{"symbol": "BDMS", "eodDate": "1996-11-01T00:00:00", "open": 2.6329, "high": 2.6711, "low": 2.6329, "close": 2.6329, "volume": 53724, "id": "19961101_BDMS" }
{"index": {"_index": "set_eod", "_type": "eod", "_id": "19961101_BEC"}}
{"symbol": "BEC", "eodDate": "1996-11-01T00:00:00", "open": 24.4, "high": 24.8, "low": 24.4, "close": 24.8, "volume": 236000, "id": "19961101_BEC" }
{"index": {"_index": "set_eod", "_type": "eod", "_id": "19961101_BFIT"}}
{"symbol": "BFIT", "eodDate": "1996-11-01T00:00:00", "open": 47.75, "high": 49.5, "low": 47.75, "close": 49.5, "volume": 89000, "id": "19961101_BFIT" }
{"index": {"_index": "set_eod", "_type": "eod", "_id": "19961101_BH"}}
{"symbol": "BH", "eodDate": "1996-11-01T00:00:00", "open": 3.55, "high": 3.6, "low": 3.55, "close": 3.6, "volume": 38000, "id": "19961101_BH" }
{"index": {"_index": "set_eod", "_type": "eod", "_id": "19961101_BIGC"}}
{"symbol": "BIGC", "eodDate": "1996-11-01T00:00:00", "open": 30, "high": 30.75, "low": 29.75, "close": 30.75, "volume": 163700, "id": "19961101_BIGC" }
{"index": {"_index": "set_eod", "_type": "eod", "_id": "19961101_BJC"}}
{"symbol": "BJC", "eodDate": "1996-11-01T00:00:00", "open": 9.15, "high": 9.25, "low": 9.15, "close": 9.25, "volume": 600, "id": "19961101_BJC" }
{"index": {"_index": "set_eod", "_type": "eod", "_id": "19961101_BKI"}}
{"symbol": "BKI", "eodDate": "1996-11-01T00:00:00", "open": 155.553, "high": 155.553, "low": 155.553, "close": 155.553, "volume": 2250, "id": "19961101_BKI" }
{"index": {"_index": "set_eod", "_type": "eod", "_id": "19961101_BLAND"}}
{"symbol": "BLAND", "eodDate": "1996-11-01T00:00:00", "open": 1.525, "high": 1.55, "low": 1.5, "close": 1.525, "volume": 1308000, "id": "19961101_BLAND" }
{"index": {"_index": "set_eod", "_type": "eod", "_id": "19961101_BTNC"}}
{"symbol": "BTNC", "eodDate": "1996-11-01T00:00:00", "open": 14.75, "high": 15, "low": 14.25, "close": 14.25, "volume": 15500, "id": "19961101_BTNC" }
{"index": {"_index": "set_eod", "_type": "eod", "_id": "19961101_BTS"}}
{"symbol": "BTS", "eodDate": "1996-11-01T00:00:00", "open": 17.1881, "high": 17.1881, "low": 16.0108, "close": 16.0108, "volume": 372261, "id": "19961101_BTS" }
{"index": {"_index": "set_eod", "_type": "eod", "_id": "19961101_CFRESH"}}
{"symbol": "CFRESH", "eodDate": "1996-11-01T00:00:00", "open": 0.8501, "high": 0.8501, "low": 0.825, "close": 0.825, "volume": 884976, "id": "19961101_CFRESH" }
{"index": {"_index": "set_eod", "_type": "eod", "_id": "19961101_CHOTI"}}
{"symbol": "CHOTI", "eodDate": "1996-11-01T00:00:00", "open": 47.75, "high": 56.5, "low": 47.75, "close": 56.5, "volume": 1400, "id": "19961101_CHOTI" }
{"index": {"_index": "set_eod", "_type": "eod", "_id": "19961101_CIMBT"}}
{"symbol": "CIMBT", "eodDate": "1996-11-01T00:00:00", "open": 42.8076, "high": 42.8076, "low": 42.8076, "close": 42.8076, "volume": 1155, "id": "19961101_CIMBT" }
{"index": {"_index": "set_eod", "_type": "eod", "_id": "19961101_CK"}}
{"symbol": "CK", "eodDate": "1996-11-01T00:00:00", "open": 12.5, "high": 12.5, "low": 12.1, "close": 12.3, "volume": 1036000, "id": "19961101_CK" }
{"index": {"_index": "set_eod", "_type": "eod", "_id": "19961101_CM"}}
{"symbol": "CM", "eodDate": "1996-11-01T00:00:00", "open": 2.1187, "high": 2.1187, "low": 2.1187, "close": 2.1187, "volume": 1462, "id": "19961101_CM" }
{"index": {"_index": "set_eod", "_type": "eod", "_id": "19961101_CNS"}}
{"symbol": "CNS", "eodDate": "1996-11-01T00:00:00", "open": 27.25, "high": 27.75, "low": 27, "close": 27, "volume": 181700, "id": "19961101_CNS" }
{"index": {"_index": "set_eod", "_type": "eod", "_id": "19961101_CNT"}}
{"symbol": "CNT", "eodDate": "1996-11-01T00:00:00", "open": 7.1, "high": 7.2, "low": 6.9, "close": 7, "volume": 16552, "id": "19961101_CNT" }
{"index": {"_index": "set_eod", "_type": "eod", "_id": "19961101_CPF"}}
{"symbol": "CPF", "eodDate": "1996-11-01T00:00:00", "open": 4.2898, "high": 4.3431, "low": 4.2632, "close": 4.3164, "volume": 549827, "id": "19961101_CPF" }
{"index": {"_index": "set_eod", "_type": "eod", "_id": "19961101_CPH"}}
{"symbol": "CPH", "eodDate": "1996-11-01T00:00:00", "open": 110, "high": 110, "low": 110, "close": 110, "volume": 4200, "id": "19961101_CPH" }
{"index": {"_index": "set_eod", "_type": "eod", "_id": "19961101_CWT"}}
{"symbol": "CWT", "eodDate": "1996-11-01T00:00:00", "open": 9.25, "high": 10, "low": 9.125, "close": 10, "volume": 71600, "id": "19961101_CWT" }
{"index": {"_index": "set_eod", "_type": "eod", "_id": "19961101_DCC"}}
{"symbol": "DCC", "eodDate": "1996-11-01T00:00:00", "open": 1.45, "high": 1.45, "low": 1.45, "close": 1.45, "volume": 9000, "id": "19961101_DCC" }
{"index": {"_index": "set_eod", "_type": "eod", "_id": "19961101_DELTA"}}
{"symbol": "DELTA", "eodDate": "1996-11-01T00:00:00", "open": 9.7, "high": 9.75, "low": 9.7, "close": 9.75, "volume": 16000, "id": "19961101_DELTA" }
{"index": {"_index": "set_eod", "_type": "eod", "_id": "19961101_DRACO"}}
{"symbol": "DRACO", "eodDate": "1996-11-01T00:00:00", "open": 1.25, "high": 1.325, "low": 1.25, "close": 1.325, "volume": 1300, "id": "19961101_DRACO" }
{"index": {"_index": "set_eod", "_type": "eod", "_id": "19961101_DTCI"}}
{"symbol": "DTCI", "eodDate": "1996-11-01T00:00:00", "open": 13.5, "high": 13.5, "low": 13.5, "close": 13.5, "volume": 900, "id": "19961101_DTCI" }
{"index": {"_index": "set_eod", "_type": "eod", "_id": "19961101_EE"}}
{"symbol": "EE", "eodDate": "1996-11-01T00:00:00", "open": 0.99, "high": 0.99, "low": 0.98, "close": 0.99, "volume": 49000, "id": "19961101_EE" }
{"index": {"_index": "set_eod", "_type": "eod", "_id": "19961101_EGCO"}}
{"symbol": "EGCO", "eodDate": "1996-11-01T00:00:00", "open": 69.5, "high": 71, "low": 69, "close": 70.5, "volume": 105900, "id": "19961101_EGCO" }
{"index": {"_index": "set_eod", "_type": "eod", "_id": "19961101_EMC"}}
{"symbol": "EMC", "eodDate": "1996-11-01T00:00:00", "open": 96, "high": 98, "low": 96, "close": 98, "volume": 1490, "id": "19961101_EMC" }
{"index": {"_index": "set_eod", "_type": "eod", "_id": "19961101_EPCO"}}
{"symbol": "EPCO", "eodDate": "1996-11-01T00:00:00", "open": 7.425, "high": 7.5, "low": 7.425, "close": 7.425, "volume": 40000, "id": "19961101_EPCO" }
{"index": {"_index": "set_eod", "_type": "eod", "_id": "19961101_ERW"}}
{"symbol": "ERW", "eodDate": "1996-11-01T00:00:00", "open": 3.1873, "high": 3.1873, "low": 3.1873, "close": 3.1873, "volume": 691368, "id": "19961101_ERW" }
{"index": {"_index": "set_eod", "_type": "eod", "_id": "19961101_ESTAR"}}
{"symbol": "ESTAR", "eodDate": "1996-11-01T00:00:00", "open": 1.1, "high": 1.125, "low": 1.1, "close": 1.125, "volume": 34800, "id": "19961101_ESTAR" }
{"index": {"_index": "set_eod", "_type": "eod", "_id": "19961101_EVER"}}
{"symbol": "EVER", "eodDate": "1996-11-01T00:00:00", "open": 17.8108, "high": 18.0155, "low": 17.8108, "close": 18.0155, "volume": 14500, "id": "19961101_EVER" }
{"index": {"_index": "set_eod", "_type": "eod", "_id": "19961101_F&D"}}
{"symbol": "F&D", "eodDate": "1996-11-01T00:00:00", "open": 20.5, "high": 22, "low": 20.25, "close": 22, "volume": 3600, "id": "19961101_F&D" }
{"index": {"_index": "set_eod", "_type": "eod", "_id": "19961101_FE"}}
{"symbol": "FE", "eodDate": "1996-11-01T00:00:00", "open": 130, "high": 130, "low": 128, "close": 128, "volume": 400, "id": "19961101_FE" }
{"index": {"_index": "set_eod", "_type": "eod", "_id": "19961101_GEL"}}
{"symbol": "GEL", "eodDate": "1996-11-01T00:00:00", "open": 3.6762, "high": 3.6762, "low": 3.6762, "close": 3.6762, "volume": 22196, "id": "19961101_GEL" }
{"index": {"_index": "set_eod", "_type": "eod", "_id": "19961101_GFPT"}}
{"symbol": "GFPT", "eodDate": "1996-11-01T00:00:00", "open": 0.3386, "high": 0.345, "low": 0.3258, "close": 0.345, "volume": 34430, "id": "19961101_GFPT" }
{"index": {"_index": "set_eod", "_type": "eod", "_id": "19961101_GJS"}}
{"symbol": "GJS", "eodDate": "1996-11-01T00:00:00", "open": 6.2, "high": 6.4, "low": 6.2, "close": 6.4, "volume": 141000, "id": "19961101_GJS" }
{"index": {"_index": "set_eod", "_type": "eod", "_id": "19961101_GOLD"}}
{"symbol": "GOLD", "eodDate": "1996-11-01T00:00:00", "open": 7.9, "high": 8.1, "low": 7.9, "close": 8.1, "volume": 11200, "id": "19961101_GOLD" }
{"index": {"_index": "set_eod", "_type": "eod", "_id": "19961101_GRAMMY"}}
{"symbol": "GRAMMY", "eodDate": "1996-11-01T00:00:00", "open": 28, "high": 28, "low": 28, "close": 28, "volume": 20000, "id": "19961101_GRAMMY" }
{"index": {"_index": "set_eod", "_type": "eod", "_id": "19961101_HANA"}}
{"symbol": "HANA", "eodDate": "1996-11-01T00:00:00", "open": 6.95, "high": 6.95, "low": 6.8961, "close": 6.95, "volume": 163338, "id": "19961101_HANA" }
{"index": {"_index": "set_eod", "_type": "eod", "_id": "19961101_IEC"}}
{"symbol": "IEC", "eodDate": "1996-11-01T00:00:00", "open": 0.72, "high": 0.72, "low": 0.705, "close": 0.71, "volume": 7050000, "id": "19961101_IEC" }
{"index": {"_index": "set_eod", "_type": "eod", "_id": "19961101_IFEC"}}
{"symbol": "IFEC", "eodDate": "1996-11-01T00:00:00", "open": 2.9, "high": 2.9, "low": 2.9, "close": 2.9, "volume": 4000, "id": "19961101_IFEC" }
{"index": {"_index": "set_eod", "_type": "eod", "_id": "19961101_INTUCH"}}
{"symbol": "INTUCH", "eodDate": "1996-11-01T00:00:00", "open": 22.7122, "high": 22.7122, "low": 22.1583, "close": 22.1583, "volume": 765817, "id": "19961101_INTUCH" }
{"index": {"_index": "set_eod", "_type": "eod", "_id": "19961101_IRC"}}
{"symbol": "IRC", "eodDate": "1996-11-01T00:00:00", "open": 3.425, "high": 3.775, "low": 3.425, "close": 3.775, "volume": 10000, "id": "19961101_IRC" }
{"index": {"_index": "set_eod", "_type": "eod", "_id": "19961101_IRPC"}}
{"symbol": "IRPC", "eodDate": "1996-11-01T00:00:00", "open": 10.779, "high": 11.1056, "low": 10.6701, "close": 11.1056, "volume": 413534, "id": "19961101_IRPC" }
{"index": {"_index": "set_eod", "_type": "eod", "_id": "19961101_ITD"}}
{"symbol": "ITD", "eodDate": "1996-11-01T00:00:00", "open": 13.9, "high": 14.1, "low": 13.7, "close": 14.1, "volume": 698000, "id": "19961101_ITD" }
{"index": {"_index": "set_eod", "_type": "eod", "_id": "19961101_JAS"}}
{"symbol": "JAS", "eodDate": "1996-11-01T00:00:00", "open": 7, "high": 7, "low": 6.8, "close": 6.9, "volume": 215000, "id": "19961101_JAS" }
{"index": {"_index": "set_eod", "_type": "eod", "_id": "19961101_JUTHA"}}
{"symbol": "JUTHA", "eodDate": "1996-11-01T00:00:00", "open": 9.4, "high": 9.4, "low": 9.3, "close": 9.4, "volume": 4100, "id": "19961101_JUTHA" }
{"index": {"_index": "set_eod", "_type": "eod", "_id": "19961101_KBANK"}}
{"symbol": "KBANK", "eodDate": "1996-11-01T00:00:00", "open": 93.2419, "high": 93.9032, "low": 92.5806, "close": 93.2419, "volume": 3576492, "id": "19961101_KBANK" }
{"index": {"_index": "set_eod", "_type": "eod", "_id": "19961101_KC"}}
{"symbol": "KC", "eodDate": "1996-11-01T00:00:00", "open": 51.5625, "high": 51.5625, "low": 51.5625, "close": 51.5625, "volume": 3490, "id": "19961101_KC" }
{"index": {"_index": "set_eod", "_type": "eod", "_id": "19961101_KCE"}}
{"symbol": "KCE", "eodDate": "1996-11-01T00:00:00", "open": 7.3095, "high": 7.3825, "low": 7.2363, "close": 7.2363, "volume": 16416, "id": "19961101_KCE" }
{"index": {"_index": "set_eod", "_type": "eod", "_id": "19961101_KGI"}}
{"symbol": "KGI", "eodDate": "1996-11-01T00:00:00", "open": 16.2202, "high": 16.3747, "low": 15.9113, "close": 15.9113, "volume": 888020, "id": "19961101_KGI" }
{"index": {"_index": "set_eod", "_type": "eod", "_id": "19961101_KKP"}}
{"symbol": "KKP", "eodDate": "1996-11-01T00:00:00", "open": 46, "high": 47, "low": 45.5, "close": 45.75, "volume": 51800, "id": "19961101_KKP" }
{"index": {"_index": "set_eod", "_type": "eod", "_id": "19961101_KTB"}}
{"symbol": "KTB", "eodDate": "1996-11-01T00:00:00", "open": 70, "high": 70, "low": 69, "close": 70, "volume": 476900, "id": "19961101_KTB" }
{"index": {"_index": "set_eod", "_type": "eod", "_id": "19961101_KWG"}}
{"symbol": "KWG", "eodDate": "1996-11-01T00:00:00", "open": 99.7062, "high": 104.409, "low": 99.7062, "close": 104.409, "volume": 1435, "id": "19961101_KWG" }
{"index": {"_index": "set_eod", "_type": "eod", "_id": "19961101_KYE"}}
{"symbol": "KYE", "eodDate": "1996-11-01T00:00:00", "open": 93, "high": 96, "low": 90, "close": 96, "volume": 11900, "id": "19961101_KYE" }
{"index": {"_index": "set_eod", "_type": "eod", "_id": "19961101_LANNA"}}
{"symbol": "LANNA", "eodDate": "1996-11-01T00:00:00", "open": 20.8, "high": 21, "low": 20.8, "close": 20.8, "volume": 143000, "id": "19961101_LANNA" }
{"index": {"_index": "set_eod", "_type": "eod", "_id": "19961101_LH"}}
{"symbol": "LH", "eodDate": "1996-11-01T00:00:00", "open": 10.3071, "high": 10.4901, "low": 10.3071, "close": 10.4901, "volume": 1182180, "id": "19961101_LH" }
{"index": {"_index": "set_eod", "_type": "eod", "_id": "19961101_LOXLEY"}}
{"symbol": "LOXLEY", "eodDate": "1996-11-01T00:00:00", "open": 18.5, "high": 18.6, "low": 18.5, "close": 18.6, "volume": 85000, "id": "19961101_LOXLEY" }
{"index": {"_index": "set_eod", "_type": "eod", "_id": "19961101_LPN"}}
{"symbol": "LPN", "eodDate": "1996-11-01T00:00:00", "open": 2.425, "high": 2.522, "low": 2.2633, "close": 2.3603, "volume": 428357, "id": "19961101_LPN" }
{"index": {"_index": "set_eod", "_type": "eod", "_id": "19961101_LRH"}}
{"symbol": "LRH", "eodDate": "1996-11-01T00:00:00", "open": 6.1689, "high": 6.1689, "low": 6.1689, "close": 6.1689, "volume": 2147, "id": "19961101_LRH" }
{"index": {"_index": "set_eod", "_type": "eod", "_id": "19961101_LST"}}
{"symbol": "LST", "eodDate": "1996-11-01T00:00:00", "open": 1.9552, "high": 1.9552, "low": 1.9386, "close": 1.9386, "volume": 16800, "id": "19961101_LST" }
{"index": {"_index": "set_eod", "_type": "eod", "_id": "19961101_MAKRO"}}
{"symbol": "MAKRO", "eodDate": "1996-11-01T00:00:00", "open": 109, "high": 109, "low": 107, "close": 107, "volume": 21600, "id": "19961101_MAKRO" }
{"index": {"_index": "set_eod", "_type": "eod", "_id": "19961101_MALEE"}}
{"symbol": "MALEE", "eodDate": "1996-11-01T00:00:00", "open": 13.25, "high": 13.5, "low": 12.5, "close": 12.75, "volume": 88800, "id": "19961101_MALEE" }
{"index": {"_index": "set_eod", "_type": "eod", "_id": "19961101_MANRIN"}}
{"symbol": "MANRIN", "eodDate": "1996-11-01T00:00:00", "open": 14.75, "high": 14.75, "low": 14, "close": 14, "volume": 4000, "id": "19961101_MANRIN" }
{"index": {"_index": "set_eod", "_type": "eod", "_id": "19961101_MATI"}}
{"symbol": "MATI", "eodDate": "1996-11-01T00:00:00", "open": 9.8, "high": 9.9, "low": 9, "close": 9.9, "volume": 22000, "id": "19961101_MATI" }
{"index": {"_index": "set_eod", "_type": "eod", "_id": "19961101_MAX"}}
{"symbol": "MAX", "eodDate": "1996-11-01T00:00:00", "open": 21.4, "high": 21.4, "low": 21, "close": 21, "volume": 83000, "id": "19961101_MAX" }
{"index": {"_index": "set_eod", "_type": "eod", "_id": "19961101_MBK"}}
{"symbol": "MBK", "eodDate": "1996-11-01T00:00:00", "open": 23.75, "high": 24, "low": 23.75, "close": 24, "volume": 288000, "id": "19961101_MBK" }
{"index": {"_index": "set_eod", "_type": "eod", "_id": "19961101_MDX"}}
{"symbol": "MDX", "eodDate": "1996-11-01T00:00:00", "open": 15.75, "high": 16, "low": 15.5, "close": 16, "volume": 35900, "id": "19961101_MDX" }
{"index": {"_index": "set_eod", "_type": "eod", "_id": "19961101_METCO"}}
{"symbol": "METCO", "eodDate": "1996-11-01T00:00:00", "open": 41, "high": 42, "low": 41, "close": 41.75, "volume": 40900, "id": "19961101_METCO" }
{"index": {"_index": "set_eod", "_type": "eod", "_id": "19961101_MFC"}}
{"symbol": "MFC", "eodDate": "1996-11-01T00:00:00", "open": 19.5, "high": 21, "low": 19.5, "close": 20, "volume": 27000, "id": "19961101_MFC" }
{"index": {"_index": "set_eod", "_type": "eod", "_id": "19961101_MINT"}}
{"symbol": "MINT", "eodDate": "1996-11-01T00:00:00", "open": 0.9495, "high": 0.9495, "low": 0.9495, "close": 0.9495, "volume": 32200, "id": "19961101_MINT" }
{"index": {"_index": "set_eod", "_type": "eod", "_id": "19961101_MK"}}
{"symbol": "MK", "eodDate": "1996-11-01T00:00:00", "open": 3.35, "high": 3.45, "low": 3.3, "close": 3.45, "volume": 56000, "id": "19961101_MK" }
{"index": {"_index": "set_eod", "_type": "eod", "_id": "19961101_MODERN"}}
{"symbol": "MODERN", "eodDate": "1996-11-01T00:00:00", "open": 13.5, "high": 14, "low": 13.5, "close": 14, "volume": 7000, "id": "19961101_MODERN" }
{"index": {"_index": "set_eod", "_type": "eod", "_id": "19961101_MSC"}}
{"symbol": "MSC", "eodDate": "1996-11-01T00:00:00", "open": 2.9, "high": 3, "low": 2.875, "close": 3, "volume": 121000, "id": "19961101_MSC" }
{"index": {"_index": "set_eod", "_type": "eod", "_id": "19961101_NC"}}
{"symbol": "NC", "eodDate": "1996-11-01T00:00:00", "open": 17.8898, "high": 18.1349, "low": 17.8898, "close": 18.1349, "volume": 1938, "id": "19961101_NC" }
{"index": {"_index": "set_eod", "_type": "eod", "_id": "19961101_NEP"}}
{"symbol": "NEP", "eodDate": "1996-11-01T00:00:00", "open": 0.53, "high": 0.54, "low": 0.53, "close": 0.54, "volume": 109000, "id": "19961101_NEP" }
{"index": {"_index": "set_eod", "_type": "eod", "_id": "19961101_NMG"}}
{"symbol": "NMG", "eodDate": "1996-11-01T00:00:00", "open": 79.5, "high": 80.5, "low": 79.5, "close": 80.5, "volume": 60600, "id": "19961101_NMG" }
{"index": {"_index": "set_eod", "_type": "eod", "_id": "19961101_NPP"}}
{"symbol": "NPP", "eodDate": "1996-11-01T00:00:00", "open": 80.5, "high": 83, "low": 80.5, "close": 83, "volume": 11000, "id": "19961101_NPP" }
{"index": {"_index": "set_eod", "_type": "eod", "_id": "19961101_NTV"}}
{"symbol": "NTV", "eodDate": "1996-11-01T00:00:00", "open": 28.75, "high": 28.75, "low": 28.75, "close": 28.75, "volume": 100, "id": "19961101_NTV" }
{"index": {"_index": "set_eod", "_type": "eod", "_id": "19961101_NWR"}}
{"symbol": "NWR", "eodDate": "1996-11-01T00:00:00", "open": 120.238, "high": 126.971, "low": 118.314, "close": 126.009, "volume": 2105, "id": "19961101_NWR" }
{"index": {"_index": "set_eod", "_type": "eod", "_id": "19961101_OCC"}}
{"symbol": "OCC", "eodDate": "1996-11-01T00:00:00", "open": 36, "high": 40, "low": 35.5, "close": 40, "volume": 3100, "id": "19961101_OCC" }
{"index": {"_index": "set_eod", "_type": "eod", "_id": "19961101_OGC"}}
{"symbol": "OGC", "eodDate": "1996-11-01T00:00:00", "open": 16.5, "high": 16.5, "low": 16.5, "close": 16.5, "volume": 100, "id": "19961101_OGC" }
{"index": {"_index": "set_eod", "_type": "eod", "_id": "19961101_PAF"}}
{"symbol": "PAF", "eodDate": "1996-11-01T00:00:00", "open": 4.5086, "high": 4.5086, "low": 4.0445, "close": 4.4423, "volume": 109724, "id": "19961101_PAF" }
{"index": {"_index": "set_eod", "_type": "eod", "_id": "19961101_PATO"}}
{"symbol": "PATO", "eodDate": "1996-11-01T00:00:00", "open": 4.65, "high": 4.7, "low": 4.65, "close": 4.7, "volume": 12000, "id": "19961101_PATO" }
{"index": {"_index": "set_eod", "_type": "eod", "_id": "19961101_PDI"}}
{"symbol": "PDI", "eodDate": "1996-11-01T00:00:00", "open": 9.8, "high": 10.25, "low": 9.5, "close": 10.25, "volume": 179050, "id": "19961101_PDI" }
{"index": {"_index": "set_eod", "_type": "eod", "_id": "19961101_PF"}}
{"symbol": "PF", "eodDate": "1996-11-01T00:00:00", "open": 36.5, "high": 38.25, "low": 36.5, "close": 36.5, "volume": 75387, "id": "19961101_PF" }
{"index": {"_index": "set_eod", "_type": "eod", "_id": "19961101_PK"}}
{"symbol": "PK", "eodDate": "1996-11-01T00:00:00", "open": 2, "high": 2, "low": 1.975, "close": 1.975, "volume": 20000, "id": "19961101_PK" }
{"index": {"_index": "set_eod", "_type": "eod", "_id": "19961101_PL"}}
{"symbol": "PL", "eodDate": "1996-11-01T00:00:00", "open": 2.375, "high": 2.375, "low": 2.325, "close": 2.35, "volume": 125000, "id": "19961101_PL" }
{"index": {"_index": "set_eod", "_type": "eod", "_id": "19961101_POST"}}
{"symbol": "POST", "eodDate": "1996-11-01T00:00:00", "open": 5.45, "high": 5.45, "low": 5.2, "close": 5.2, "volume": 91460, "id": "19961101_POST" }
{"index": {"_index": "set_eod", "_type": "eod", "_id": "19961101_PRANDA"}}
{"symbol": "PRANDA", "eodDate": "1996-11-01T00:00:00", "open": 3.275, "high": 3.4, "low": 3.1, "close": 3.4, "volume": 22000, "id": "19961101_PRANDA" }
{"index": {"_index": "set_eod", "_type": "eod", "_id": "19961101_PRECHA"}}
{"symbol": "PRECHA", "eodDate": "1996-11-01T00:00:00", "open": 33.2, "high": 33.4, "low": 33.2, "close": 33.4, "volume": 28000, "id": "19961101_PRECHA" }
{"index": {"_index": "set_eod", "_type": "eod", "_id": "19961101_PRG"}}
{"symbol": "PRG", "eodDate": "1996-11-01T00:00:00", "open": 21.5, "high": 22, "low": 21.5, "close": 21.75, "volume": 11000, "id": "19961101_PRG" }
{"index": {"_index": "set_eod", "_type": "eod", "_id": "19961101_PSL"}}
{"symbol": "PSL", "eodDate": "1996-11-01T00:00:00", "open": 2.675, "high": 2.675, "low": 2.65, "close": 2.675, "volume": 1126000, "id": "19961101_PSL" }
{"index": {"_index": "set_eod", "_type": "eod", "_id": "19961101_PTTEP"}}
{"symbol": "PTTEP", "eodDate": "1996-11-01T00:00:00", "open": 35, "high": 35.4, "low": 35, "close": 35.2, "volume": 204000, "id": "19961101_PTTEP" }
{"index": {"_index": "set_eod", "_type": "eod", "_id": "19961101_QH"}}
{"symbol": "QH", "eodDate": "1996-11-01T00:00:00", "open": 5.1651, "high": 5.502, "low": 5.0529, "close": 5.3336, "volume": 2692462, "id": "19961101_QH" }
{"index": {"_index": "set_eod", "_type": "eod", "_id": "19961101_RAM"}}
{"symbol": "RAM", "eodDate": "1996-11-01T00:00:00", "open": 39.5, "high": 39.5, "low": 39.5, "close": 39.5, "volume": 100, "id": "19961101_RAM" }
{"index": {"_index": "set_eod", "_type": "eod", "_id": "19961101_RCL"}}
{"symbol": "RCL", "eodDate": "1996-11-01T00:00:00", "open": 10.6494, "high": 10.7294, "low": 10.5693, "close": 10.7294, "volume": 114890, "id": "19961101_RCL" }
{"index": {"_index": "set_eod", "_type": "eod", "_id": "19961101_RML"}}
{"symbol": "RML", "eodDate": "1996-11-01T00:00:00", "open": 0.824, "high": 0.8416, "low": 0.8065, "close": 0.8416, "volume": 119777, "id": "19961101_RML" }
{"index": {"_index": "set_eod", "_type": "eod", "_id": "19961101_ROBINS"}}
{"symbol": "ROBINS", "eodDate": "1996-11-01T00:00:00", "open": 36.5, "high": 37, "low": 36.5, "close": 36.5, "volume": 28000, "id": "19961101_ROBINS" }
{"index": {"_index": "set_eod", "_type": "eod", "_id": "19961101_ROCK"}}
{"symbol": "ROCK", "eodDate": "1996-11-01T00:00:00", "open": 35.25, "high": 38.75, "low": 31.75, "close": 38.75, "volume": 1400, "id": "19961101_ROCK" }
{"index": {"_index": "set_eod", "_type": "eod", "_id": "19961101_ROJNA"}}
{"symbol": "ROJNA", "eodDate": "1996-11-01T00:00:00", "open": 14.9, "high": 15.9, "low": 14.9, "close": 15.9, "volume": 2000, "id": "19961101_ROJNA" }
{"index": {"_index": "set_eod", "_type": "eod", "_id": "19961101_SAMART"}}
{"symbol": "SAMART", "eodDate": "1996-11-01T00:00:00", "open": 15, "high": 15.1, "low": 15, "close": 15.1, "volume": 30000, "id": "19961101_SAMART" }
{"index": {"_index": "set_eod", "_type": "eod", "_id": "19961101_SAMCO"}}
{"symbol": "SAMCO", "eodDate": "1996-11-01T00:00:00", "open": 2.925, "high": 3.025, "low": 2.9, "close": 3.025, "volume": 303010, "id": "19961101_SAMCO" }
{"index": {"_index": "set_eod", "_type": "eod", "_id": "19961101_SAMTEL"}}
{"symbol": "SAMTEL", "eodDate": "1996-11-01T00:00:00", "open": 7.15, "high": 7.45, "low": 7.1, "close": 7.45, "volume": 132000, "id": "19961101_SAMTEL" }
{"index": {"_index": "set_eod", "_type": "eod", "_id": "19961101_SAUCE"}}
{"symbol": "SAUCE", "eodDate": "1996-11-01T00:00:00", "open": 91, "high": 96, "low": 91, "close": 96, "volume": 900, "id": "19961101_SAUCE" }
{"index": {"_index": "set_eod", "_type": "eod", "_id": "19961101_SAWANG"}}
{"symbol": "SAWANG", "eodDate": "1996-11-01T00:00:00", "open": 14.25, "high": 14.75, "low": 14.25, "close": 14.75, "volume": 2800, "id": "19961101_SAWANG" }
{"index": {"_index": "set_eod", "_type": "eod", "_id": "19961101_SCB"}}
{"symbol": "SCB", "eodDate": "1996-11-01T00:00:00", "open": 179.016, "high": 181.77, "low": 179.016, "close": 179.934, "volume": 122871, "id": "19961101_SCB" }
{"index": {"_index": "set_eod", "_type": "eod", "_id": "19961101_SCC"}}
{"symbol": "SCC", "eodDate": "1996-11-01T00:00:00", "open": 83.2, "high": 84.4, "low": 83.2, "close": 84, "volume": 144000, "id": "19961101_SCC" }
{"index": {"_index": "set_eod", "_type": "eod", "_id": "19961101_SCCC"}}
{"symbol": "SCCC", "eodDate": "1996-11-01T00:00:00", "open": 158, "high": 164, "low": 158, "close": 161, "volume": 61300, "id": "19961101_SCCC" }
{"index": {"_index": "set_eod", "_type": "eod", "_id": "19961101_SE-ED"}}
{"symbol": "SE-ED", "eodDate": "1996-11-01T00:00:00", "open": 3.5721, "high": 3.5721, "low": 3.4775, "close": 3.5011, "volume": 61290, "id": "19961101_SE-ED" }
{"index": {"_index": "set_eod", "_type": "eod", "_id": "19961101_SFP"}}
{"symbol": "SFP", "eodDate": "1996-11-01T00:00:00", "open": 88, "high": 88, "low": 87, "close": 87, "volume": 10000, "id": "19961101_SFP" }
{"index": {"_index": "set_eod", "_type": "eod", "_id": "19961101_SHANG"}}
{"symbol": "SHANG", "eodDate": "1996-11-01T00:00:00", "open": 23, "high": 23.25, "low": 23, "close": 23.25, "volume": 2800, "id": "19961101_SHANG" }
{"index": {"_index": "set_eod", "_type": "eod", "_id": "19961101_SINGER"}}
{"symbol": "SINGER", "eodDate": "1996-11-01T00:00:00", "open": 15.7, "high": 15.7, "low": 15.7, "close": 15.7, "volume": 42000, "id": "19961101_SINGER" }
{"index": {"_index": "set_eod", "_type": "eod", "_id": "19961101_SIRI"}}
{"symbol": "SIRI", "eodDate": "1996-11-01T00:00:00", "open": 20.7636, "high": 20.9523, "low": 19.631, "close": 20.9523, "volume": 1854, "id": "19961101_SIRI" }
{"index": {"_index": "set_eod", "_type": "eod", "_id": "19961101_SITHAI"}}
{"symbol": "SITHAI", "eodDate": "1996-11-01T00:00:00", "open": 130, "high": 133, "low": 129, "close": 133, "volume": 35800, "id": "19961101_SITHAI" }
{"index": {"_index": "set_eod", "_type": "eod", "_id": "19961101_SKR"}}
{"symbol": "SKR", "eodDate": "1996-11-01T00:00:00", "open": 6.4, "high": 7.4, "low": 6.3, "close": 7.4, "volume": 104300, "id": "19961101_SKR" }
{"index": {"_index": "set_eod", "_type": "eod", "_id": "19961101_SMPC"}}
{"symbol": "SMPC", "eodDate": "1996-11-01T00:00:00", "open": 5.3, "high": 5.7, "low": 5.2, "close": 5.7, "volume": 2800, "id": "19961101_SMPC" }
{"index": {"_index": "set_eod", "_type": "eod", "_id": "19961101_SPALI"}}
{"symbol": "SPALI", "eodDate": "1996-11-01T00:00:00", "open": 3.075, "high": 3.075, "low": 2.9, "close": 3, "volume": 991000, "id": "19961101_SPALI" }
{"index": {"_index": "set_eod", "_type": "eod", "_id": "19961101_SPC"}}
{"symbol": "SPC", "eodDate": "1996-11-01T00:00:00", "open": 6.2, "high": 6.2, "low": 6, "close": 6, "volume": 7000, "id": "19961101_SPC" }
{"index": {"_index": "set_eod", "_type": "eod", "_id": "19961101_SPORT"}}
{"symbol": "SPORT", "eodDate": "1996-11-01T00:00:00", "open": 12, "high": 12, "low": 11.9, "close": 12, "volume": 30000, "id": "19961101_SPORT" }
{"index": {"_index": "set_eod", "_type": "eod", "_id": "19961101_SSC"}}
{"symbol": "SSC", "eodDate": "1996-11-01T00:00:00", "open": 51.8, "high": 51.8, "low": 51.8, "close": 51.8, "volume": 20000, "id": "19961101_SSC" }
{"index": {"_index": "set_eod", "_type": "eod", "_id": "19961101_SSF"}}
{"symbol": "SSF", "eodDate": "1996-11-01T00:00:00", "open": 0.676, "high": 0.7872, "low": 0.676, "close": 0.7872, "volume": 108102, "id": "19961101_SSF" }
{"index": {"_index": "set_eod", "_type": "eod", "_id": "19961101_SSI"}}
{"symbol": "SSI", "eodDate": "1996-11-01T00:00:00", "open": 0.96, "high": 1, "low": 0.96, "close": 1, "volume": 5080000, "id": "19961101_SSI" }
{"index": {"_index": "set_eod", "_type": "eod", "_id": "19961101_STA"}}
{"symbol": "STA", "eodDate": "1996-11-01T00:00:00", "open": 3.0208, "high": 3.0208, "low": 3.0208, "close": 3.0208, "volume": 174455, "id": "19961101_STA" }
{"index": {"_index": "set_eod", "_type": "eod", "_id": "19961101_STEC"}}
{"symbol": "STEC", "eodDate": "1996-11-01T00:00:00", "open": 6.6, "high": 6.85, "low": 6.6, "close": 6.85, "volume": 100000, "id": "19961101_STEC" }
{"index": {"_index": "set_eod", "_type": "eod", "_id": "19961101_STPI"}}
{"symbol": "STPI", "eodDate": "1996-11-01T00:00:00", "open": 2.15, "high": 2.3, "low": 2.125, "close": 2.175, "volume": 277000, "id": "19961101_STPI" }
{"index": {"_index": "set_eod", "_type": "eod", "_id": "19961101_SUC"}}
{"symbol": "SUC", "eodDate": "1996-11-01T00:00:00", "open": 26.25, "high": 26.25, "low": 26, "close": 26.25, "volume": 83000, "id": "19961101_SUC" }
{"index": {"_index": "set_eod", "_type": "eod", "_id": "19961101_SUSCO"}}
{"symbol": "SUSCO", "eodDate": "1996-11-01T00:00:00", "open": 0.76, "high": 0.8, "low": 0.76, "close": 0.8, "volume": 435500, "id": "19961101_SUSCO" }
{"index": {"_index": "set_eod", "_type": "eod", "_id": "19961101_SVH"}}
{"symbol": "SVH", "eodDate": "1996-11-01T00:00:00", "open": 17.25, "high": 17.25, "low": 17.25, "close": 17.25, "volume": 2300, "id": "19961101_SVH" }
{"index": {"_index": "set_eod", "_type": "eod", "_id": "19961101_SVOA"}}
{"symbol": "SVOA", "eodDate": "1996-11-01T00:00:00", "open": 2.025, "high": 2.1, "low": 2, "close": 2.1, "volume": 112000, "id": "19961101_SVOA" }
{"index": {"_index": "set_eod", "_type": "eod", "_id": "19961101_SYNTEC"}}
{"symbol": "SYNTEC", "eodDate": "1996-11-01T00:00:00", "open": 8.7, "high": 8.9395, "low": 8.7, "close": 8.9395, "volume": 5400, "id": "19961101_SYNTEC" }
{"index": {"_index": "set_eod", "_type": "eod", "_id": "19961101_TASCO"}}
{"symbol": "TASCO", "eodDate": "1996-11-01T00:00:00", "open": 138, "high": 138, "low": 137, "close": 138, "volume": 47200, "id": "19961101_TASCO" }
{"index": {"_index": "set_eod", "_type": "eod", "_id": "19961101_TBSP"}}
{"symbol": "TBSP", "eodDate": "1996-11-01T00:00:00", "open": 27, "high": 27, "low": 26.5, "close": 26.5, "volume": 2900, "id": "19961101_TBSP" }
{"index": {"_index": "set_eod", "_type": "eod", "_id": "19961101_TC"}}
{"symbol": "TC", "eodDate": "1996-11-01T00:00:00", "open": 9.3, "high": 9.3, "low": 9.3, "close": 9.3, "volume": 100, "id": "19961101_TC" }
{"index": {"_index": "set_eod", "_type": "eod", "_id": "19961101_TCAP"}}
{"symbol": "TCAP", "eodDate": "1996-11-01T00:00:00", "open": 47.5893, "high": 48.3214, "low": 46.8571, "close": 47.8333, "volume": 1707146, "id": "19961101_TCAP" }
{"index": {"_index": "set_eod", "_type": "eod", "_id": "19961101_TCB"}}
{"symbol": "TCB", "eodDate": "1996-11-01T00:00:00", "open": 10, "high": 10, "low": 9.75, "close": 9.75, "volume": 16000, "id": "19961101_TCB" }
{"index": {"_index": "set_eod", "_type": "eod", "_id": "19961101_TCC"}}
{"symbol": "TCC", "eodDate": "1996-11-01T00:00:00", "open": 9.6, "high": 9.6, "low": 9.6, "close": 9.6, "volume": 1100, "id": "19961101_TCC" }
{"index": {"_index": "set_eod", "_type": "eod", "_id": "19961101_TCJ"}}
{"symbol": "TCJ", "eodDate": "1996-11-01T00:00:00", "open": 139, "high": 141, "low": 139, "close": 141, "volume": 29000, "id": "19961101_TCJ" }
{"index": {"_index": "set_eod", "_type": "eod", "_id": "19961101_TF"}}
{"symbol": "TF", "eodDate": "1996-11-01T00:00:00", "open": 137, "high": 137, "low": 137, "close": 137, "volume": 16500, "id": "19961101_TF" }
{"index": {"_index": "set_eod", "_type": "eod", "_id": "19961101_TFD"}}
{"symbol": "TFD", "eodDate": "1996-11-01T00:00:00", "open": 3.1188, "high": 3.1188, "low": 3.1188, "close": 3.1188, "volume": 5450, "id": "19961101_TFD" }
{"index": {"_index": "set_eod", "_type": "eod", "_id": "19961101_TFI"}}
{"symbol": "TFI", "eodDate": "1996-11-01T00:00:00", "open": 0.6521, "high": 0.6782, "low": 0.6521, "close": 0.6782, "volume": 21085, "id": "19961101_TFI" }
{"index": {"_index": "set_eod", "_type": "eod", "_id": "19961101_TGCI"}}
{"symbol": "TGCI", "eodDate": "1996-11-01T00:00:00", "open": 2.775, "high": 2.775, "low": 2.775, "close": 2.775, "volume": 30000, "id": "19961101_TGCI" }
{"index": {"_index": "set_eod", "_type": "eod", "_id": "19961101_TGPRO"}}
{"symbol": "TGPRO", "eodDate": "1996-11-01T00:00:00", "open": 21.2836, "high": 21.6325, "low": 20.9347, "close": 21.2836, "volume": 33676, "id": "19961101_TGPRO" }
{"index": {"_index": "set_eod", "_type": "eod", "_id": "19961101_TH"}}
{"symbol": "TH", "eodDate": "1996-11-01T00:00:00", "open": 2.125, "high": 2.125, "low": 2.125, "close": 2.125, "volume": 1000, "id": "19961101_TH" }
{"index": {"_index": "set_eod", "_type": "eod", "_id": "19961101_THAI"}}
{"symbol": "THAI", "eodDate": "1996-11-01T00:00:00", "open": 45, "high": 45.25, "low": 45, "close": 45.25, "volume": 78200, "id": "19961101_THAI" }
{"index": {"_index": "set_eod", "_type": "eod", "_id": "19961101_THCOM"}}
{"symbol": "THCOM", "eodDate": "1996-11-01T00:00:00", "open": 18.25, "high": 18.625, "low": 18.125, "close": 18.625, "volume": 245600, "id": "19961101_THCOM" }
{"index": {"_index": "set_eod", "_type": "eod", "_id": "19961101_THL"}}
{"symbol": "THL", "eodDate": "1996-11-01T00:00:00", "open": 1.0704, "high": 1.1169, "low": 1.0704, "close": 1.1169, "volume": 24710, "id": "19961101_THL" }
{"index": {"_index": "set_eod", "_type": "eod", "_id": "19961101_TIP"}}
{"symbol": "TIP", "eodDate": "1996-11-01T00:00:00", "open": 7.7, "high": 7.8, "low": 7.7, "close": 7.8, "volume": 30000, "id": "19961101_TIP" }
{"index": {"_index": "set_eod", "_type": "eod", "_id": "19961101_TISCO"}}
{"symbol": "TISCO", "eodDate": "1996-11-01T00:00:00", "open": 121, "high": 124, "low": 121, "close": 122, "volume": 229400, "id": "19961101_TISCO" }
{"index": {"_index": "set_eod", "_type": "eod", "_id": "19961101_TLUXE"}}
{"symbol": "TLUXE", "eodDate": "1996-11-01T00:00:00", "open": 2.3698, "high": 2.3698, "low": 2.3698, "close": 2.3698, "volume": 1000, "id": "19961101_TLUXE" }
{"index": {"_index": "set_eod", "_type": "eod", "_id": "19961101_TMB"}}
{"symbol": "TMB", "eodDate": "1996-11-01T00:00:00", "open": 48.4626, "high": 48.4626, "low": 47.6481, "close": 48.0553, "volume": 528890, "id": "19961101_TMB" }
{"index": {"_index": "set_eod", "_type": "eod", "_id": "19961101_TPC"}}
{"symbol": "TPC", "eodDate": "1996-11-01T00:00:00", "open": 7.8, "high": 7.95, "low": 7.6, "close": 7.95, "volume": 154000, "id": "19961101_TPC" }
{"index": {"_index": "set_eod", "_type": "eod", "_id": "19961101_TPIPL"}}
{"symbol": "TPIPL", "eodDate": "1996-11-01T00:00:00", "open": 41.0337, "high": 42.5395, "low": 41.0337, "close": 41.7866, "volume": 191675, "id": "19961101_TPIPL" }
{"index": {"_index": "set_eod", "_type": "eod", "_id": "19961101_TPP"}}
{"symbol": "TPP", "eodDate": "1996-11-01T00:00:00", "open": 7, "high": 7, "low": 7, "close": 7, "volume": 100, "id": "19961101_TPP" }
{"index": {"_index": "set_eod", "_type": "eod", "_id": "19961101_TRITN"}}
{"symbol": "TRITN", "eodDate": "1996-11-01T00:00:00", "open": 6.4215, "high": 6.469, "low": 6.4215, "close": 6.469, "volume": 110415, "id": "19961101_TRITN" }
{"index": {"_index": "set_eod", "_type": "eod", "_id": "19961101_TRU"}}
{"symbol": "TRU", "eodDate": "1996-11-01T00:00:00", "open": 11.76, "high": 11.84, "low": 11.6, "close": 11.84, "volume": 163750, "id": "19961101_TRU" }
{"index": {"_index": "set_eod", "_type": "eod", "_id": "19961101_TRUE"}}
{"symbol": "TRUE", "eodDate": "1996-11-01T00:00:00", "open": 48.75, "high": 49.25, "low": 48.5, "close": 48.5, "volume": 761412, "id": "19961101_TRUE" }
{"index": {"_index": "set_eod", "_type": "eod", "_id": "19961101_TTA"}}
{"symbol": "TTA", "eodDate": "1996-11-01T00:00:00", "open": 3.6372, "high": 3.7509, "low": 3.4099, "close": 3.7509, "volume": 347530, "id": "19961101_TTA" }
{"index": {"_index": "set_eod", "_type": "eod", "_id": "19961101_TTI"}}
{"symbol": "TTI", "eodDate": "1996-11-01T00:00:00", "open": 27, "high": 27, "low": 27, "close": 27, "volume": 100, "id": "19961101_TTI" }
{"index": {"_index": "set_eod", "_type": "eod", "_id": "19961101_TU"}}
{"symbol": "TU", "eodDate": "1996-11-01T00:00:00", "open": 2.95, "high": 3, "low": 2.95, "close": 3, "volume": 17000, "id": "19961101_TU" }
{"index": {"_index": "set_eod", "_type": "eod", "_id": "19961101_TVI"}}
{"symbol": "TVI", "eodDate": "1996-11-01T00:00:00", "open": 48, "high": 48.5, "low": 48, "close": 48.5, "volume": 2000, "id": "19961101_TVI" }
{"index": {"_index": "set_eod", "_type": "eod", "_id": "19961101_TWP"}}
{"symbol": "TWP", "eodDate": "1996-11-01T00:00:00", "open": 19.75, "high": 21, "low": 19.75, "close": 20.75, "volume": 73700, "id": "19961101_TWP" }
{"index": {"_index": "set_eod", "_type": "eod", "_id": "19961101_U"}}
{"symbol": "U", "eodDate": "1996-11-01T00:00:00", "open": 771.879, "high": 771.879, "low": 771.879, "close": 771.879, "volume": 69, "id": "19961101_U" }
{"index": {"_index": "set_eod", "_type": "eod", "_id": "19961101_UMI"}}
{"symbol": "UMI", "eodDate": "1996-11-01T00:00:00", "open": 1.0297, "high": 1.0941, "low": 1.0297, "close": 1.0941, "volume": 6992, "id": "19961101_UMI" }
{"index": {"_index": "set_eod", "_type": "eod", "_id": "19961101_UP"}}
{"symbol": "UP", "eodDate": "1996-11-01T00:00:00", "open": 16.5, "high": 16.5, "low": 16.5, "close": 16.5, "volume": 3000, "id": "19961101_UP" }
{"index": {"_index": "set_eod", "_type": "eod", "_id": "19961101_UPOIC"}}
{"symbol": "UPOIC", "eodDate": "1996-11-01T00:00:00", "open": 3.1, "high": 3.3, "low": 3.1, "close": 3.3, "volume": 51000, "id": "19961101_UPOIC" }
{"index": {"_index": "set_eod", "_type": "eod", "_id": "19961101_UT"}}
{"symbol": "UT", "eodDate": "1996-11-01T00:00:00", "open": 9.5, "high": 9.5, "low": 9.5, "close": 9.5, "volume": 100, "id": "19961101_UT" }
{"index": {"_index": "set_eod", "_type": "eod", "_id": "19961101_UV"}}
{"symbol": "UV", "eodDate": "1996-11-01T00:00:00", "open": 2.725, "high": 2.975, "low": 2.725, "close": 2.975, "volume": 7000, "id": "19961101_UV" }
{"index": {"_index": "set_eod", "_type": "eod", "_id": "19961101_VIBHA"}}
{"symbol": "VIBHA", "eodDate": "1996-11-01T00:00:00", "open": 1.15, "high": 1.2, "low": 1.15, "close": 1.2, "volume": 77000, "id": "19961101_VIBHA" }
{"index": {"_index": "set_eod", "_type": "eod", "_id": "19961101_VNT"}}
{"symbol": "VNT", "eodDate": "1996-11-01T00:00:00", "open": 7.7, "high": 7.8, "low": 7.6, "close": 7.8, "volume": 97597, "id": "19961101_VNT" }
{"index": {"_index": "set_eod", "_type": "eod", "_id": "19961101_WAVE"}}
{"symbol": "WAVE", "eodDate": "1996-11-01T00:00:00", "open": 70.8051, "high": 70.8051, "low": 69.6988, "close": 70.0676, "volume": 10711, "id": "19961101_WAVE" }
{"index": {"_index": "set_eod", "_type": "eod", "_id": "19961101_WIIK"}}
{"symbol": "WIIK", "eodDate": "1996-11-01T00:00:00", "open": 2.75, "high": 2.75, "low": 2.7, "close": 2.75, "volume": 56000, "id": "19961101_WIIK" }
{"index": {"_index": "set_eod", "_type": "eod", "_id": "19961101_YCI"}}
{"symbol": "YCI", "eodDate": "1996-11-01T00:00:00", "open": 21, "high": 22, "low": 21, "close": 22, "volume": 3600, "id": "19961101_YCI" }
{"index": {"_index": "set_eod", "_type": "eod", "_id": "19961101_ZMICO"}}
{"symbol": "ZMICO", "eodDate": "1996-11-01T00:00:00", "open": 2.85, "high": 2.9, "low": 2.85, "close": 2.9, "volume": 50000, "id": "19961101_ZMICO" }
{"index": {"_index": "set_eod", "_type": "eod", "_id": "19961101_$AGRI"}}
{"symbol": "$AGRI", "eodDate": "1996-11-01T00:00:00", "open": 47.39, "high": 47.39, "low": 47.39, "close": 47.39, "volume": 169801, "id": "19961101_$AGRI" }
{"index": {"_index": "set_eod", "_type": "eod", "_id": "19961101_$BANK"}}
{"symbol": "$BANK", "eodDate": "1996-11-01T00:00:00", "open": 971.84, "high": 971.84, "low": 971.84, "close": 971.84, "volume": 6150209, "id": "19961101_$BANK" }
{"index": {"_index": "set_eod", "_type": "eod", "_id": "19961101_$COMM"}}
{"symbol": "$COMM", "eodDate": "1996-11-01T00:00:00", "open": 3765.72, "high": 3765.72, "low": 3765.72, "close": 3765.72, "volume": 322500, "id": "19961101_$COMM" }
{"index": {"_index": "set_eod", "_type": "eod", "_id": "19961101_$ENERG"}}
{"symbol": "$ENERG", "eodDate": "1996-11-01T00:00:00", "open": 6285.82, "high": 6285.82, "low": 6285.82, "close": 6285.82, "volume": 363000, "id": "19961101_$ENERG" }
{"index": {"_index": "set_eod", "_type": "eod", "_id": "19961101_$ETRON"}}
{"symbol": "$ETRON", "eodDate": "1996-11-01T00:00:00", "open": 440.27, "high": 440.27, "low": 440.27, "close": 440.27, "volume": 94200, "id": "19961101_$ETRON" }
{"index": {"_index": "set_eod", "_type": "eod", "_id": "19961101_$FIN"}}
{"symbol": "$FIN", "eodDate": "1996-11-01T00:00:00", "open": 6238.28, "high": 6238.28, "low": 6238.28, "close": 6238.28, "volume": 8397455, "id": "19961101_$FIN" }
{"index": {"_index": "set_eod", "_type": "eod", "_id": "19961101_$FOOD"}}
{"symbol": "$FOOD", "eodDate": "1996-11-01T00:00:00", "open": 2151.43, "high": 2151.43, "low": 2151.43, "close": 2151.43, "volume": 163550, "id": "19961101_$FOOD" }
{"index": {"_index": "set_eod", "_type": "eod", "_id": "19961101_$HELTH"}}
{"symbol": "$HELTH", "eodDate": "1996-11-01T00:00:00", "open": 197.35, "high": 197.35, "low": 197.35, "close": 197.35, "volume": 145085, "id": "19961101_$HELTH" }
{"index": {"_index": "set_eod", "_type": "eod", "_id": "19961101_$INSUR"}}
{"symbol": "$INSUR", "eodDate": "1996-11-01T00:00:00", "open": 3338.52, "high": 3338.52, "low": 3338.52, "close": 3338.52, "volume": 20200, "id": "19961101_$INSUR" }
{"index": {"_index": "set_eod", "_type": "eod", "_id": "19961101_$MINE"}}
{"symbol": "$MINE", "eodDate": "1996-11-01T00:00:00", "open": 12.39, "high": 12.39, "low": 12.39, "close": 12.39, "volume": 181350, "id": "19961101_$MINE" }
{"index": {"_index": "set_eod", "_type": "eod", "_id": "19961101_$PKG"}}
{"symbol": "$PKG", "eodDate": "1996-11-01T00:00:00", "open": 1323.28, "high": 1323.28, "low": 1323.28, "close": 1323.28, "volume": 115400, "id": "19961101_$PKG" }
{"index": {"_index": "set_eod", "_type": "eod", "_id": "19961101_$PROF"}}
{"symbol": "$PROF", "eodDate": "1996-11-01T00:00:00", "open": 209.13, "high": 209.13, "low": 209.13, "close": 209.13, "volume": 400, "id": "19961101_$PROF" }
{"index": {"_index": "set_eod", "_type": "eod", "_id": "19961101_$PROP"}}
{"symbol": "$PROP", "eodDate": "1996-11-01T00:00:00", "open": 530.65, "high": 530.65, "low": 530.65, "close": 530.65, "volume": 4052631, "id": "19961101_$PROP" }
{"index": {"_index": "set_eod", "_type": "eod", "_id": "19961101_$TRANS"}}
{"symbol": "$TRANS", "eodDate": "1996-11-01T00:00:00", "open": 92.44, "high": 92.44, "low": 92.44, "close": 92.44, "volume": 375901, "id": "19961101_$TRANS" }
{"index": {"_index": "set_eod", "_type": "eod", "_id": "19961101_SET"}}
{"symbol": "SET", "eodDate": "1996-11-01T00:00:00", "open": 909.01, "high": 912.52, "low": 907.56, "close": 912.52, "volume": 44200776, "id": "19961101_SET" }
{"index": {"_index": "set_eod", "_type": "eod", "_id": "19961101_ADVANC-F"}}
{"symbol": "ADVANC-F", "eodDate": "1996-11-01T00:00:00", "open": 34.8, "high": 34.8, "low": 34.8, "close": 34.8, "volume": 10000, "id": "19961101_ADVANC-F" }
{"index": {"_index": "set_eod", "_type": "eod", "_id": "19961101_BAY-F"}}
{"symbol": "BAY-F", "eodDate": "1996-11-01T00:00:00", "open": 73, "high": 74.5, "low": 73, "close": 74.05, "volume": 138600, "id": "19961101_BAY-F" }
{"index": {"_index": "set_eod", "_type": "eod", "_id": "19961101_BBL-F"}}
{"symbol": "BBL-F", "eodDate": "1996-11-01T00:00:00", "open": 274, "high": 280, "low": 272, "close": 276.03, "volume": 309800, "id": "19961101_BBL-F" }
{"index": {"_index": "set_eod", "_type": "eod", "_id": "19961101_BKI-F"}}
{"symbol": "BKI-F", "eodDate": "1996-11-01T00:00:00", "open": 242.667, "high": 242.667, "low": 242.667, "close": 242.667, "volume": 8550, "id": "19961101_BKI-F" }
{"index": {"_index": "set_eod", "_type": "eod", "_id": "19961101_BLAND-F"}}
{"symbol": "BLAND-F", "eodDate": "1996-11-01T00:00:00", "open": 2.2, "high": 2.975, "low": 2.2, "close": 2.341, "volume": 759000, "id": "19961101_BLAND-F" }
{"index": {"_index": "set_eod", "_type": "eod", "_id": "19961101_CPF-F"}}
{"symbol": "CPF-F", "eodDate": "1996-11-01T00:00:00", "open": 99, "high": 99, "low": 99, "close": 99, "volume": 1156, "id": "19961101_CPF-F" }
{"index": {"_index": "set_eod", "_type": "eod", "_id": "19961101_CSC-F"}}
{"symbol": "CSC-F", "eodDate": "1996-11-01T00:00:00", "open": 71.5, "high": 71.5, "low": 71.5, "close": 71.5, "volume": 14000, "id": "19961101_CSC-F" }
{"index": {"_index": "set_eod", "_type": "eod", "_id": "19961101_EGCO-F"}}
{"symbol": "EGCO-F", "eodDate": "1996-11-01T00:00:00", "open": 72.5, "high": 76.5, "low": 72.5, "close": 72.87, "volume": 13400, "id": "19961101_EGCO-F" }
{"index": {"_index": "set_eod", "_type": "eod", "_id": "19961101_ICC-F"}}
{"symbol": "ICC-F", "eodDate": "1996-11-01T00:00:00", "open": 165, "high": 165, "low": 165, "close": 165, "volume": 21200, "id": "19961101_ICC-F" }
{"index": {"_index": "set_eod", "_type": "eod", "_id": "19961101_KBANK-F"}}
{"symbol": "KBANK-F", "eodDate": "1996-11-01T00:00:00", "open": 117.603, "high": 119.412, "low": 114.588, "close": 117.175, "volume": 826275, "id": "19961101_KBANK-F" }
{"index": {"_index": "set_eod", "_type": "eod", "_id": "19961101_KTB-F"}}
{"symbol": "KTB-F", "eodDate": "1996-11-01T00:00:00", "open": 69, "high": 70, "low": 69, "close": 69.92, "volume": 460800, "id": "19961101_KTB-F" }
{"index": {"_index": "set_eod", "_type": "eod", "_id": "19961101_LH-F"}}
{"symbol": "LH-F", "eodDate": "1996-11-01T00:00:00", "open": 21.2, "high": 21.4, "low": 21, "close": 21.03, "volume": 741000, "id": "19961101_LH-F" }
{"index": {"_index": "set_eod", "_type": "eod", "_id": "19961101_OHTL-F"}}
{"symbol": "OHTL-F", "eodDate": "1996-11-01T00:00:00", "open": 135, "high": 135, "low": 135, "close": 135, "volume": 1000, "id": "19961101_OHTL-F" }
{"index": {"_index": "set_eod", "_type": "eod", "_id": "19961101_PTTEP-F"}}
{"symbol": "PTTEP-F", "eodDate": "1996-11-01T00:00:00", "open": 183, "high": 183, "low": 182, "close": 182.7, "volume": 96000, "id": "19961101_PTTEP-F" }
{"index": {"_index": "set_eod", "_type": "eod", "_id": "19961101_QH-F"}}
{"symbol": "QH-F", "eodDate": "1996-11-01T00:00:00", "open": 4.6, "high": 4.85, "low": 4.6, "close": 4.738, "volume": 105000, "id": "19961101_QH-F" }
{"index": {"_index": "set_eod", "_type": "eod", "_id": "19961101_RCL-F"}}
{"symbol": "RCL-F", "eodDate": "1996-11-01T00:00:00", "open": 272, "high": 272, "low": 266, "close": 269.46, "volume": 5200, "id": "19961101_RCL-F" }
{"index": {"_index": "set_eod", "_type": "eod", "_id": "19961101_ROBINS-F"}}
{"symbol": "ROBINS-F", "eodDate": "1996-11-01T00:00:00", "open": 42.5, "high": 42.5, "low": 42.5, "close": 42.5, "volume": 5100, "id": "19961101_ROBINS-F" }
{"index": {"_index": "set_eod", "_type": "eod", "_id": "19961101_SCB-F"}}
{"symbol": "SCB-F", "eodDate": "1996-11-01T00:00:00", "open": 230, "high": 230, "low": 226, "close": 227.85, "volume": 71700, "id": "19961101_SCB-F" }
{"index": {"_index": "set_eod", "_type": "eod", "_id": "19961101_SCC-F"}}
{"symbol": "SCC-F", "eodDate": "1996-11-01T00:00:00", "open": 86.8, "high": 89.6, "low": 86.8, "close": 87.762, "volume": 210020, "id": "19961101_SCC-F" }
{"index": {"_index": "set_eod", "_type": "eod", "_id": "19961101_SSI-F"}}
{"symbol": "SSI-F", "eodDate": "1996-11-01T00:00:00", "open": 0.99, "high": 0.99, "low": 0.99, "close": 0.99, "volume": 40000, "id": "19961101_SSI-F" }
{"index": {"_index": "set_eod", "_type": "eod", "_id": "19961101_TCAP-F"}}
{"symbol": "TCAP-F", "eodDate": "1996-11-01T00:00:00", "open": 49.25, "high": 49.5, "low": 48.5, "close": 49.05, "volume": 229800, "id": "19961101_TCAP-F" }
{"index": {"_index": "set_eod", "_type": "eod", "_id": "19961101_TMB-F"}}
{"symbol": "TMB-F", "eodDate": "1996-11-01T00:00:00", "open": 58, "high": 60, "low": 58, "close": 59.08, "volume": 280400, "id": "19961101_TMB-F" }
{"index": {"_index": "set_eod", "_type": "eod", "_id": "19961101_TRUE-F"}}
{"symbol": "TRUE-F", "eodDate": "1996-11-01T00:00:00", "open": 49, "high": 49, "low": 49, "close": 49, "volume": 50000, "id": "19961101_TRUE-F" }
{"index": {"_index": "set_eod", "_type": "eod", "_id": "19961101_APX"}}
{"symbol": "APX", "eodDate": "1996-11-01T00:00:00", "open": 25.8107, "high": 26.5929, "low": 25.8107, "close": 26.5929, "volume": 9109, "id": "19961101_APX" }
{"index": {"_index": "set_eod", "_type": "eod", "_id": "19961101_BECL"}}
{"symbol": "BECL", "eodDate": "1996-11-01T00:00:00", "open": 27.5, "high": 28, "low": 27.5, "close": 27.75, "volume": 181100, "id": "19961101_BECL" }
{"index": {"_index": "set_eod", "_type": "eod", "_id": "19961101_BRC"}}
{"symbol": "BRC", "eodDate": "1996-11-01T00:00:00", "open": 8.9, "high": 9.4, "low": 8.9, "close": 9.4, "volume": 154600, "id": "19961101_BRC" }
{"index": {"_index": "set_eod", "_type": "eod", "_id": "19961101_CGS"}}
{"symbol": "CGS", "eodDate": "1996-11-01T00:00:00", "open": 2.0272, "high": 2.049, "low": 1.9837, "close": 2.049, "volume": 371585, "id": "19961101_CGS" }
{"index": {"_index": "set_eod", "_type": "eod", "_id": "19961101_CPICO"}}
{"symbol": "CPICO", "eodDate": "1996-11-01T00:00:00", "open": 44.5, "high": 45, "low": 43.5, "close": 45, "volume": 3200, "id": "19961101_CPICO" }
{"index": {"_index": "set_eod", "_type": "eod", "_id": "19961101_DTM"}}
{"symbol": "DTM", "eodDate": "1996-11-01T00:00:00", "open": 5.7129, "high": 5.8633, "low": 5.6378, "close": 5.7881, "volume": 163429, "id": "19961101_DTM" }
{"index": {"_index": "set_eod", "_type": "eod", "_id": "19961101_HEMRAJ"}}
{"symbol": "HEMRAJ", "eodDate": "1996-11-01T00:00:00", "open": 3.434, "high": 3.5252, "low": 3.434, "close": 3.5252, "volume": 467264, "id": "19961101_HEMRAJ" }
{"index": {"_index": "set_eod", "_type": "eod", "_id": "19961101_ICBCT"}}
{"symbol": "ICBCT", "eodDate": "1996-11-01T00:00:00", "open": 141.6, "high": 145.2, "low": 141.6, "close": 145.2, "volume": 17500, "id": "19961101_ICBCT" }
{"index": {"_index": "set_eod", "_type": "eod", "_id": "19961101_MGR"}}
{"symbol": "MGR", "eodDate": "1996-11-01T00:00:00", "open": 92, "high": 95.5, "low": 91, "close": 95.5, "volume": 1800, "id": "19961101_MGR" }
{"index": {"_index": "set_eod", "_type": "eod", "_id": "19961101_NFC"}}
{"symbol": "NFC", "eodDate": "1996-11-01T00:00:00", "open": 7.9333, "high": 7.9333, "low": 7.7067, "close": 7.9333, "volume": 507970, "id": "19961101_NFC" }
{"index": {"_index": "set_eod", "_type": "eod", "_id": "19961101_PA"}}
{"symbol": "PA", "eodDate": "1996-11-01T00:00:00", "open": 7, "high": 7, "low": 6.5, "close": 6.9, "volume": 3500, "id": "19961101_PA" }
{"index": {"_index": "set_eod", "_type": "eod", "_id": "19961101_PHATRA"}}
{"symbol": "PHATRA", "eodDate": "1996-11-01T00:00:00", "open": 86, "high": 87.5, "low": 86, "close": 87, "volume": 259600, "id": "19961101_PHATRA" }
{"index": {"_index": "set_eod", "_type": "eod", "_id": "19961101_POMPUI"}}
{"symbol": "POMPUI", "eodDate": "1996-11-01T00:00:00", "open": 26, "high": 28, "low": 26, "close": 28, "volume": 7700, "id": "19961101_POMPUI" }
{"index": {"_index": "set_eod", "_type": "eod", "_id": "19961101_PYT"}}
{"symbol": "PYT", "eodDate": "1996-11-01T00:00:00", "open": 24, "high": 24.25, "low": 24, "close": 24.25, "volume": 17000, "id": "19961101_PYT" }
{"index": {"_index": "set_eod", "_type": "eod", "_id": "19961101_SAFARI"}}
{"symbol": "SAFARI", "eodDate": "1996-11-01T00:00:00", "open": 77.4265, "high": 78.2206, "low": 77.4265, "close": 78.2206, "volume": 36266, "id": "19961101_SAFARI" }
{"index": {"_index": "set_eod", "_type": "eod", "_id": "19961101_SCAN"}}
{"symbol": "SCAN", "eodDate": "1996-11-01T00:00:00", "open": 23.75, "high": 23.75, "low": 23.25, "close": 23.5, "volume": 10100, "id": "19961101_SCAN" }
{"index": {"_index": "set_eod", "_type": "eod", "_id": "19961101_SCIB"}}
{"symbol": "SCIB", "eodDate": "1996-11-01T00:00:00", "open": 30.5849, "high": 31.1122, "low": 30.5849, "close": 31.1122, "volume": 267375, "id": "19961101_SCIB" }
{"index": {"_index": "set_eod", "_type": "eod", "_id": "19961101_SGF"}}
{"symbol": "SGF", "eodDate": "1996-11-01T00:00:00", "open": 5.4061, "high": 5.5965, "low": 5.4061, "close": 5.5965, "volume": 45309, "id": "19961101_SGF" }
{"index": {"_index": "set_eod", "_type": "eod", "_id": "19961101_SICCO"}}
{"symbol": "SICCO", "eodDate": "1996-11-01T00:00:00", "open": 26.1461, "high": 26.1461, "low": 26.1461, "close": 26.1461, "volume": 279, "id": "19961101_SICCO" }
{"index": {"_index": "set_eod", "_type": "eod", "_id": "19961101_SMG"}}
{"symbol": "SMG", "eodDate": "1996-11-01T00:00:00", "open": 14.3089, "high": 14.3089, "low": 14.3089, "close": 14.3089, "volume": 3843, "id": "19961101_SMG" }
{"index": {"_index": "set_eod", "_type": "eod", "_id": "19961101_SPSU"}}
{"symbol": "SPSU", "eodDate": "1996-11-01T00:00:00", "open": 18.75, "high": 19.375, "low": 18.75, "close": 19.375, "volume": 2000, "id": "19961101_SPSU" }
{"index": {"_index": "set_eod", "_type": "eod", "_id": "19961101_TCP"}}
{"symbol": "TCP", "eodDate": "1996-11-01T00:00:00", "open": 20.6536, "high": 21.9608, "low": 20.6536, "close": 21.4379, "volume": 47430, "id": "19961101_TCP" }
{"index": {"_index": "set_eod", "_type": "eod", "_id": "19961101_TRS"}}
{"symbol": "TRS", "eodDate": "1996-11-01T00:00:00", "open": 16.3704, "high": 16.3704, "low": 16.3704, "close": 16.3704, "volume": 635, "id": "19961101_TRS" }
{"index": {"_index": "set_eod", "_type": "eod", "_id": "19961101_TT&T"}}
{"symbol": "TT&T", "eodDate": "1996-11-01T00:00:00", "open": 33.5335, "high": 33.7331, "low": 32.3358, "close": 33.7331, "volume": 39828, "id": "19961101_TT&T" }
{"index": {"_index": "set_eod", "_type": "eod", "_id": "19961101_VGM"}}
{"symbol": "VGM", "eodDate": "1996-11-01T00:00:00", "open": 6.1425, "high": 6.24, "low": 6.11, "close": 6.24, "volume": 20000, "id": "19961101_VGM" }
{"index": {"_index": "set_eod", "_type": "eod", "_id": "19961101_VI"}}
{"symbol": "VI", "eodDate": "1996-11-01T00:00:00", "open": 23.5, "high": 23.75, "low": 23, "close": 23.75, "volume": 16400, "id": "19961101_VI" }
