{"index": {"_index": "set_eod", "_type": "eod", "_id": "20060120_A"}}
{"symbol": "A", "eodDate": "2006-01-20T00:00:00", "open": 4.7, "high": 4.86, "low": 4.52, "close": 4.52, "volume": 15364600, "id": "20060120_A" }
{"index": {"_index": "set_eod", "_type": "eod", "_id": "20060120_ACAP"}}
{"symbol": "ACAP", "eodDate": "2006-01-20T00:00:00", "open": 6.85, "high": 7.05, "low": 6.5, "close": 6.9, "volume": 166500, "id": "20060120_ACAP" }
{"index": {"_index": "set_eod", "_type": "eod", "_id": "20060120_ACC"}}
{"symbol": "ACC", "eodDate": "2006-01-20T00:00:00", "open": 3.08, "high": 3.2, "low": 2.94, "close": 3, "volume": 25225800, "id": "20060120_ACC" }
{"index": {"_index": "set_eod", "_type": "eod", "_id": "20060120_ADAM"}}
{"symbol": "ADAM", "eodDate": "2006-01-20T00:00:00", "open": 0.9897, "high": 1.0066, "low": 0.9728, "close": 0.9728, "volume": 855408, "id": "20060120_ADAM" }
{"index": {"_index": "set_eod", "_type": "eod", "_id": "20060120_ADVANC"}}
{"symbol": "ADVANC", "eodDate": "2006-01-20T00:00:00", "open": 106, "high": 107, "low": 103, "close": 104, "volume": 3759624, "id": "20060120_ADVANC" }
{"index": {"_index": "set_eod", "_type": "eod", "_id": "20060120_AEC"}}
{"symbol": "AEC", "eodDate": "2006-01-20T00:00:00", "open": 7.4, "high": 7.55, "low": 7.3, "close": 7.3, "volume": 1573000, "id": "20060120_AEC" }
{"index": {"_index": "set_eod", "_type": "eod", "_id": "20060120_AEONTS"}}
{"symbol": "AEONTS", "eodDate": "2006-01-20T00:00:00", "open": 34, "high": 34, "low": 34, "close": 34, "volume": 300, "id": "20060120_AEONTS" }
{"index": {"_index": "set_eod", "_type": "eod", "_id": "20060120_AF"}}
{"symbol": "AF", "eodDate": "2006-01-20T00:00:00", "open": 6.3, "high": 6.4, "low": 6.3, "close": 6.3, "volume": 11600, "id": "20060120_AF" }
{"index": {"_index": "set_eod", "_type": "eod", "_id": "20060120_AH"}}
{"symbol": "AH", "eodDate": "2006-01-20T00:00:00", "open": 27.5, "high": 27.5, "low": 27, "close": 27, "volume": 2253904, "id": "20060120_AH" }
{"index": {"_index": "set_eod", "_type": "eod", "_id": "20060120_AHC"}}
{"symbol": "AHC", "eodDate": "2006-01-20T00:00:00", "open": 73, "high": 74, "low": 73, "close": 74, "volume": 7300, "id": "20060120_AHC" }
{"index": {"_index": "set_eod", "_type": "eod", "_id": "20060120_AI"}}
{"symbol": "AI", "eodDate": "2006-01-20T00:00:00", "open": 11.3, "high": 11.3, "low": 11.2, "close": 11.3, "volume": 168000, "id": "20060120_AI" }
{"index": {"_index": "set_eod", "_type": "eod", "_id": "20060120_AIT"}}
{"symbol": "AIT", "eodDate": "2006-01-20T00:00:00", "open": 8.7333, "high": 9.0667, "low": 8.6667, "close": 8.9333, "volume": 468300, "id": "20060120_AIT" }
{"index": {"_index": "set_eod", "_type": "eod", "_id": "20060120_AJ"}}
{"symbol": "AJ", "eodDate": "2006-01-20T00:00:00", "open": 3.18, "high": 3.24, "low": 3.18, "close": 3.22, "volume": 119407, "id": "20060120_AJ" }
{"index": {"_index": "set_eod", "_type": "eod", "_id": "20060120_AMANAH"}}
{"symbol": "AMANAH", "eodDate": "2006-01-20T00:00:00", "open": 0.88, "high": 0.9, "low": 0.86, "close": 0.86, "volume": 5652900, "id": "20060120_AMANAH" }
{"index": {"_index": "set_eod", "_type": "eod", "_id": "20060120_AMARIN"}}
{"symbol": "AMARIN", "eodDate": "2006-01-20T00:00:00", "open": 10.2, "high": 10.3, "low": 10.2, "close": 10.3, "volume": 7000, "id": "20060120_AMARIN" }
{"index": {"_index": "set_eod", "_type": "eod", "_id": "20060120_AMATA"}}
{"symbol": "AMATA", "eodDate": "2006-01-20T00:00:00", "open": 15.8, "high": 16.8, "low": 15.8, "close": 16.5, "volume": 8306556, "id": "20060120_AMATA" }
{"index": {"_index": "set_eod", "_type": "eod", "_id": "20060120_AMC"}}
{"symbol": "AMC", "eodDate": "2006-01-20T00:00:00", "open": 4.9259, "high": 4.9457, "low": 4.9259, "close": 4.9457, "volume": 23454, "id": "20060120_AMC" }
{"index": {"_index": "set_eod", "_type": "eod", "_id": "20060120_AOT"}}
{"symbol": "AOT", "eodDate": "2006-01-20T00:00:00", "open": 51, "high": 51.5, "low": 50.5, "close": 50.5, "volume": 1409300, "id": "20060120_AOT" }
{"index": {"_index": "set_eod", "_type": "eod", "_id": "20060120_AP"}}
{"symbol": "AP", "eodDate": "2006-01-20T00:00:00", "open": 3.9, "high": 4.08, "low": 3.9, "close": 4.06, "volume": 8257324, "id": "20060120_AP" }
{"index": {"_index": "set_eod", "_type": "eod", "_id": "20060120_APURE"}}
{"symbol": "APURE", "eodDate": "2006-01-20T00:00:00", "open": 5.2, "high": 5.4222, "low": 5.2, "close": 5.3778, "volume": 27604238, "id": "20060120_APURE" }
{"index": {"_index": "set_eod", "_type": "eod", "_id": "20060120_AQ"}}
{"symbol": "AQ", "eodDate": "2006-01-20T00:00:00", "open": 3.4259, "high": 3.4447, "low": 3.351, "close": 3.3885, "volume": 4116729, "id": "20060120_AQ" }
{"index": {"_index": "set_eod", "_type": "eod", "_id": "20060120_ASIAN"}}
{"symbol": "ASIAN", "eodDate": "2006-01-20T00:00:00", "open": 4.92, "high": 4.92, "low": 4.9, "close": 4.92, "volume": 33100, "id": "20060120_ASIAN" }
{"index": {"_index": "set_eod", "_type": "eod", "_id": "20060120_ASIMAR"}}
{"symbol": "ASIMAR", "eodDate": "2006-01-20T00:00:00", "open": 1.41, "high": 1.42, "low": 1.4, "close": 1.4, "volume": 901500, "id": "20060120_ASIMAR" }
{"index": {"_index": "set_eod", "_type": "eod", "_id": "20060120_ASK"}}
{"symbol": "ASK", "eodDate": "2006-01-20T00:00:00", "open": 7.1044, "high": 7.1538, "low": 7.1044, "close": 7.1538, "volume": 2128, "id": "20060120_ASK" }
{"index": {"_index": "set_eod", "_type": "eod", "_id": "20060120_ASP"}}
{"symbol": "ASP", "eodDate": "2006-01-20T00:00:00", "open": 5.35, "high": 5.35, "low": 5.1, "close": 5.1, "volume": 51470900, "id": "20060120_ASP" }
{"index": {"_index": "set_eod", "_type": "eod", "_id": "20060120_AYUD"}}
{"symbol": "AYUD", "eodDate": "2006-01-20T00:00:00", "open": 16.6, "high": 16.6, "low": 16.5, "close": 16.5, "volume": 75300, "id": "20060120_AYUD" }
{"index": {"_index": "set_eod", "_type": "eod", "_id": "20060120_BAFS"}}
{"symbol": "BAFS", "eodDate": "2006-01-20T00:00:00", "open": 7.4557, "high": 7.4974, "low": 7.4557, "close": 7.4557, "volume": 109556, "id": "20060120_BAFS" }
{"index": {"_index": "set_eod", "_type": "eod", "_id": "20060120_BANPU"}}
{"symbol": "BANPU", "eodDate": "2006-01-20T00:00:00", "open": 133, "high": 135, "low": 132, "close": 133, "volume": 2037300, "id": "20060120_BANPU" }
{"index": {"_index": "set_eod", "_type": "eod", "_id": "20060120_BAT-3K"}}
{"symbol": "BAT-3K", "eodDate": "2006-01-20T00:00:00", "open": 59.5, "high": 59.5, "low": 58.5, "close": 59, "volume": 49700, "id": "20060120_BAT-3K" }
{"index": {"_index": "set_eod", "_type": "eod", "_id": "20060120_BAY"}}
{"symbol": "BAY", "eodDate": "2006-01-20T00:00:00", "open": 16, "high": 16.2, "low": 15.7, "close": 16, "volume": 18526840, "id": "20060120_BAY" }
{"index": {"_index": "set_eod", "_type": "eod", "_id": "20060120_BBL"}}
{"symbol": "BBL", "eodDate": "2006-01-20T00:00:00", "open": 113, "high": 113, "low": 111, "close": 111, "volume": 4816817, "id": "20060120_BBL" }
{"index": {"_index": "set_eod", "_type": "eod", "_id": "20060120_BCH"}}
{"symbol": "BCH", "eodDate": "2006-01-20T00:00:00", "open": 1.5429, "high": 1.5543, "low": 1.5314, "close": 1.5314, "volume": 511400, "id": "20060120_BCH" }
{"index": {"_index": "set_eod", "_type": "eod", "_id": "20060120_BCP"}}
{"symbol": "BCP", "eodDate": "2006-01-20T00:00:00", "open": 14, "high": 14.1, "low": 14, "close": 14, "volume": 853600, "id": "20060120_BCP" }
{"index": {"_index": "set_eod", "_type": "eod", "_id": "20060120_BDMS"}}
{"symbol": "BDMS", "eodDate": "2006-01-20T00:00:00", "open": 24.5, "high": 24.5, "low": 23.9, "close": 23.9, "volume": 398800, "id": "20060120_BDMS" }
{"index": {"_index": "set_eod", "_type": "eod", "_id": "20060120_BEC"}}
{"symbol": "BEC", "eodDate": "2006-01-20T00:00:00", "open": 13.5, "high": 13.6, "low": 13.4, "close": 13.4, "volume": 577300, "id": "20060120_BEC" }
{"index": {"_index": "set_eod", "_type": "eod", "_id": "20060120_BFIT"}}
{"symbol": "BFIT", "eodDate": "2006-01-20T00:00:00", "open": 13.2, "high": 13.2, "low": 12.6, "close": 12.6, "volume": 1564700, "id": "20060120_BFIT" }
{"index": {"_index": "set_eod", "_type": "eod", "_id": "20060120_BH"}}
{"symbol": "BH", "eodDate": "2006-01-20T00:00:00", "open": 33.5, "high": 33.5, "low": 31, "close": 31, "volume": 88111888, "id": "20060120_BH" }
{"index": {"_index": "set_eod", "_type": "eod", "_id": "20060120_BIGC"}}
{"symbol": "BIGC", "eodDate": "2006-01-20T00:00:00", "open": 33, "high": 33.5, "low": 33, "close": 33.25, "volume": 8000, "id": "20060120_BIGC" }
{"index": {"_index": "set_eod", "_type": "eod", "_id": "20060120_BJC"}}
{"symbol": "BJC", "eodDate": "2006-01-20T00:00:00", "open": 5, "high": 5, "low": 5, "close": 5, "volume": 4000, "id": "20060120_BJC" }
{"index": {"_index": "set_eod", "_type": "eod", "_id": "20060120_BKI"}}
{"symbol": "BKI", "eodDate": "2006-01-20T00:00:00", "open": 186.667, "high": 186.667, "low": 186.667, "close": 186.667, "volume": 3000, "id": "20060120_BKI" }
{"index": {"_index": "set_eod", "_type": "eod", "_id": "20060120_BKKCP"}}
{"symbol": "BKKCP", "eodDate": "2006-01-20T00:00:00", "open": 8.9, "high": 8.9, "low": 8.9, "close": 8.9, "volume": 100000, "id": "20060120_BKKCP" }
{"index": {"_index": "set_eod", "_type": "eod", "_id": "20060120_BLAND"}}
{"symbol": "BLAND", "eodDate": "2006-01-20T00:00:00", "open": 0.66, "high": 0.71, "low": 0.66, "close": 0.69, "volume": 219529328, "id": "20060120_BLAND" }
{"index": {"_index": "set_eod", "_type": "eod", "_id": "20060120_BLISS"}}
{"symbol": "BLISS", "eodDate": "2006-01-20T00:00:00", "open": 2.4673, "high": 2.4673, "low": 2.4102, "close": 2.4245, "volume": 342400, "id": "20060120_BLISS" }
{"index": {"_index": "set_eod", "_type": "eod", "_id": "20060120_BOL"}}
{"symbol": "BOL", "eodDate": "2006-01-20T00:00:00", "open": 0.19, "high": 0.19, "low": 0.19, "close": 0.19, "volume": 17500, "id": "20060120_BOL" }
{"index": {"_index": "set_eod", "_type": "eod", "_id": "20060120_BROOK"}}
{"symbol": "BROOK", "eodDate": "2006-01-20T00:00:00", "open": 0.71, "high": 0.73, "low": 0.67, "close": 0.68, "volume": 356000, "id": "20060120_BROOK" }
{"index": {"_index": "set_eod", "_type": "eod", "_id": "20060120_BSBM"}}
{"symbol": "BSBM", "eodDate": "2006-01-20T00:00:00", "open": 1.31, "high": 1.32, "low": 1.26, "close": 1.26, "volume": 6604700, "id": "20060120_BSBM" }
{"index": {"_index": "set_eod", "_type": "eod", "_id": "20060120_BTC"}}
{"symbol": "BTC", "eodDate": "2006-01-20T00:00:00", "open": 1.76, "high": 1.79, "low": 1.74, "close": 1.75, "volume": 2578900, "id": "20060120_BTC" }
{"index": {"_index": "set_eod", "_type": "eod", "_id": "20060120_CCET"}}
{"symbol": "CCET", "eodDate": "2006-01-20T00:00:00", "open": 3.88, "high": 3.9, "low": 3.82, "close": 3.88, "volume": 2315200, "id": "20060120_CCET" }
{"index": {"_index": "set_eod", "_type": "eod", "_id": "20060120_CCP"}}
{"symbol": "CCP", "eodDate": "2006-01-20T00:00:00", "open": 2.34, "high": 2.34, "low": 2.28, "close": 2.32, "volume": 272800, "id": "20060120_CCP" }
{"index": {"_index": "set_eod", "_type": "eod", "_id": "20060120_CEN"}}
{"symbol": "CEN", "eodDate": "2006-01-20T00:00:00", "open": 3.6, "high": 3.62, "low": 3.44, "close": 3.46, "volume": 54371500, "id": "20060120_CEN" }
{"index": {"_index": "set_eod", "_type": "eod", "_id": "20060120_CENTEL"}}
{"symbol": "CENTEL", "eodDate": "2006-01-20T00:00:00", "open": 4.673, "high": 4.9651, "low": 4.673, "close": 4.9651, "volume": 20976900, "id": "20060120_CENTEL" }
{"index": {"_index": "set_eod", "_type": "eod", "_id": "20060120_CFRESH"}}
{"symbol": "CFRESH", "eodDate": "2006-01-20T00:00:00", "open": 2.76, "high": 2.84, "low": 2.76, "close": 2.8, "volume": 698400, "id": "20060120_CFRESH" }
{"index": {"_index": "set_eod", "_type": "eod", "_id": "20060120_CGD"}}
{"symbol": "CGD", "eodDate": "2006-01-20T00:00:00", "open": 0.2235, "high": 0.2235, "low": 0.2235, "close": 0.2235, "volume": 1118, "id": "20060120_CGD" }
{"index": {"_index": "set_eod", "_type": "eod", "_id": "20060120_CHARAN"}}
{"symbol": "CHARAN", "eodDate": "2006-01-20T00:00:00", "open": 43, "high": 43, "low": 43, "close": 43, "volume": 200, "id": "20060120_CHARAN" }
{"index": {"_index": "set_eod", "_type": "eod", "_id": "20060120_CHUO"}}
{"symbol": "CHUO", "eodDate": "2006-01-20T00:00:00", "open": 10.7, "high": 10.9, "low": 10.6, "close": 10.6, "volume": 12000, "id": "20060120_CHUO" }
{"index": {"_index": "set_eod", "_type": "eod", "_id": "20060120_CI"}}
{"symbol": "CI", "eodDate": "2006-01-20T00:00:00", "open": 3.52, "high": 3.7, "low": 3.5, "close": 3.6, "volume": 1774100, "id": "20060120_CI" }
{"index": {"_index": "set_eod", "_type": "eod", "_id": "20060120_CIG"}}
{"symbol": "CIG", "eodDate": "2006-01-20T00:00:00", "open": 1.84, "high": 1.85, "low": 1.83, "close": 1.83, "volume": 96800, "id": "20060120_CIG" }
{"index": {"_index": "set_eod", "_type": "eod", "_id": "20060120_CIMBT"}}
{"symbol": "CIMBT", "eodDate": "2006-01-20T00:00:00", "open": 3.4808, "high": 3.5024, "low": 3.4592, "close": 3.5024, "volume": 13168772, "id": "20060120_CIMBT" }
{"index": {"_index": "set_eod", "_type": "eod", "_id": "20060120_CK"}}
{"symbol": "CK", "eodDate": "2006-01-20T00:00:00", "open": 12.7, "high": 12.8, "low": 12.6, "close": 12.7, "volume": 685000, "id": "20060120_CK" }
{"index": {"_index": "set_eod", "_type": "eod", "_id": "20060120_CMO"}}
{"symbol": "CMO", "eodDate": "2006-01-20T00:00:00", "open": 1.93, "high": 1.93, "low": 1.91, "close": 1.91, "volume": 63500, "id": "20060120_CMO" }
{"index": {"_index": "set_eod", "_type": "eod", "_id": "20060120_CNS"}}
{"symbol": "CNS", "eodDate": "2006-01-20T00:00:00", "open": 47.5, "high": 48.25, "low": 47.5, "close": 48, "volume": 153700, "id": "20060120_CNS" }
{"index": {"_index": "set_eod", "_type": "eod", "_id": "20060120_CNT"}}
{"symbol": "CNT", "eodDate": "2006-01-20T00:00:00", "open": 3.16, "high": 3.26, "low": 3.14, "close": 3.16, "volume": 1539644, "id": "20060120_CNT" }
{"index": {"_index": "set_eod", "_type": "eod", "_id": "20060120_CPALL"}}
{"symbol": "CPALL", "eodDate": "2006-01-20T00:00:00", "open": 6.15, "high": 6.15, "low": 6.1, "close": 6.1, "volume": 1115031, "id": "20060120_CPALL" }
{"index": {"_index": "set_eod", "_type": "eod", "_id": "20060120_CPF"}}
{"symbol": "CPF", "eodDate": "2006-01-20T00:00:00", "open": 5.9, "high": 5.9, "low": 5.75, "close": 5.8, "volume": 11490001, "id": "20060120_CPF" }
{"index": {"_index": "set_eod", "_type": "eod", "_id": "20060120_CPH"}}
{"symbol": "CPH", "eodDate": "2006-01-20T00:00:00", "open": 10.7, "high": 10.7, "low": 10.6, "close": 10.6, "volume": 1400, "id": "20060120_CPH" }
{"index": {"_index": "set_eod", "_type": "eod", "_id": "20060120_CPL"}}
{"symbol": "CPL", "eodDate": "2006-01-20T00:00:00", "open": 15.5, "high": 15.5, "low": 15.5, "close": 15.5, "volume": 1800, "id": "20060120_CPL" }
{"index": {"_index": "set_eod", "_type": "eod", "_id": "20060120_CPN"}}
{"symbol": "CPN", "eodDate": "2006-01-20T00:00:00", "open": 14.5, "high": 14.8, "low": 13.8, "close": 14.5, "volume": 636000, "id": "20060120_CPN" }
{"index": {"_index": "set_eod", "_type": "eod", "_id": "20060120_CPNRF"}}
{"symbol": "CPNRF", "eodDate": "2006-01-20T00:00:00", "open": 10.9, "high": 11, "low": 10.9, "close": 11, "volume": 10000, "id": "20060120_CPNRF" }
{"index": {"_index": "set_eod", "_type": "eod", "_id": "20060120_CPR"}}
{"symbol": "CPR", "eodDate": "2006-01-20T00:00:00", "open": 2.16, "high": 2.18, "low": 2.14, "close": 2.16, "volume": 219800, "id": "20060120_CPR" }
{"index": {"_index": "set_eod", "_type": "eod", "_id": "20060120_CSC"}}
{"symbol": "CSC", "eodDate": "2006-01-20T00:00:00", "open": 11.1, "high": 11.3, "low": 11, "close": 11.3, "volume": 2200, "id": "20060120_CSC" }
{"index": {"_index": "set_eod", "_type": "eod", "_id": "20060120_CSL"}}
{"symbol": "CSL", "eodDate": "2006-01-20T00:00:00", "open": 3.56, "high": 3.92, "low": 3.56, "close": 3.92, "volume": 22351200, "id": "20060120_CSL" }
{"index": {"_index": "set_eod", "_type": "eod", "_id": "20060120_CSP"}}
{"symbol": "CSP", "eodDate": "2006-01-20T00:00:00", "open": 2.36, "high": 2.38, "low": 2.28, "close": 2.32, "volume": 7740500, "id": "20060120_CSP" }
{"index": {"_index": "set_eod", "_type": "eod", "_id": "20060120_CTW"}}
{"symbol": "CTW", "eodDate": "2006-01-20T00:00:00", "open": 7.05, "high": 7.05, "low": 7.05, "close": 7.05, "volume": 435615, "id": "20060120_CTW" }
{"index": {"_index": "set_eod", "_type": "eod", "_id": "20060120_CWT"}}
{"symbol": "CWT", "eodDate": "2006-01-20T00:00:00", "open": 5.3, "high": 5.35, "low": 5.3, "close": 5.3, "volume": 20100, "id": "20060120_CWT" }
{"index": {"_index": "set_eod", "_type": "eod", "_id": "20060120_DCC"}}
{"symbol": "DCC", "eodDate": "2006-01-20T00:00:00", "open": 18.5, "high": 19.1, "low": 18.4, "close": 19, "volume": 2263000, "id": "20060120_DCC" }
{"index": {"_index": "set_eod", "_type": "eod", "_id": "20060120_DCON"}}
{"symbol": "DCON", "eodDate": "2006-01-20T00:00:00", "open": 3.9, "high": 3.9, "low": 3.9, "close": 3.9, "volume": 30000, "id": "20060120_DCON" }
{"index": {"_index": "set_eod", "_type": "eod", "_id": "20060120_DELTA"}}
{"symbol": "DELTA", "eodDate": "2006-01-20T00:00:00", "open": 17.4, "high": 17.7, "low": 17.3, "close": 17.3, "volume": 3900400, "id": "20060120_DELTA" }
{"index": {"_index": "set_eod", "_type": "eod", "_id": "20060120_DRACO"}}
{"symbol": "DRACO", "eodDate": "2006-01-20T00:00:00", "open": 1.51, "high": 1.52, "low": 1.51, "close": 1.52, "volume": 2000, "id": "20060120_DRACO" }
{"index": {"_index": "set_eod", "_type": "eod", "_id": "20060120_DRT"}}
{"symbol": "DRT", "eodDate": "2006-01-20T00:00:00", "open": 1.24, "high": 1.24, "low": 1.23, "close": 1.23, "volume": 1410000, "id": "20060120_DRT" }
{"index": {"_index": "set_eod", "_type": "eod", "_id": "20060120_DTC"}}
{"symbol": "DTC", "eodDate": "2006-01-20T00:00:00", "open": 41.75, "high": 43, "low": 41.75, "close": 42, "volume": 4600, "id": "20060120_DTC" }
{"index": {"_index": "set_eod", "_type": "eod", "_id": "20060120_DTCI"}}
{"symbol": "DTCI", "eodDate": "2006-01-20T00:00:00", "open": 8.45, "high": 8.8, "low": 8.3, "close": 8.6, "volume": 140411, "id": "20060120_DTCI" }
{"index": {"_index": "set_eod", "_type": "eod", "_id": "20060120_EASON"}}
{"symbol": "EASON", "eodDate": "2006-01-20T00:00:00", "open": 2.56, "high": 2.6, "low": 2.54, "close": 2.58, "volume": 676800, "id": "20060120_EASON" }
{"index": {"_index": "set_eod", "_type": "eod", "_id": "20060120_EASTW"}}
{"symbol": "EASTW", "eodDate": "2006-01-20T00:00:00", "open": 4, "high": 4.02, "low": 4, "close": 4, "volume": 808800, "id": "20060120_EASTW" }
{"index": {"_index": "set_eod", "_type": "eod", "_id": "20060120_ECL"}}
{"symbol": "ECL", "eodDate": "2006-01-20T00:00:00", "open": 0.64, "high": 0.65, "low": 0.62, "close": 0.62, "volume": 801300, "id": "20060120_ECL" }
{"index": {"_index": "set_eod", "_type": "eod", "_id": "20060120_EGCO"}}
{"symbol": "EGCO", "eodDate": "2006-01-20T00:00:00", "open": 85, "high": 87, "low": 83, "close": 86.5, "volume": 208040, "id": "20060120_EGCO" }
{"index": {"_index": "set_eod", "_type": "eod", "_id": "20060120_EIC"}}
{"symbol": "EIC", "eodDate": "2006-01-20T00:00:00", "open": 1.98, "high": 1.98, "low": 1.97, "close": 1.97, "volume": 130000, "id": "20060120_EIC" }
{"index": {"_index": "set_eod", "_type": "eod", "_id": "20060120_EMC"}}
{"symbol": "EMC", "eodDate": "2006-01-20T00:00:00", "open": 2.2, "high": 2.2, "low": 2.12, "close": 2.12, "volume": 280770, "id": "20060120_EMC" }
{"index": {"_index": "set_eod", "_type": "eod", "_id": "20060120_ERW"}}
{"symbol": "ERW", "eodDate": "2006-01-20T00:00:00", "open": 2.112, "high": 2.112, "low": 2.08, "close": 2.112, "volume": 131500, "id": "20060120_ERW" }
{"index": {"_index": "set_eod", "_type": "eod", "_id": "20060120_ESTAR"}}
{"symbol": "ESTAR", "eodDate": "2006-01-20T00:00:00", "open": 0.48, "high": 0.49, "low": 0.47, "close": 0.47, "volume": 2109100, "id": "20060120_ESTAR" }
{"index": {"_index": "set_eod", "_type": "eod", "_id": "20060120_EVER"}}
{"symbol": "EVER", "eodDate": "2006-01-20T00:00:00", "open": 2.6041, "high": 2.6368, "low": 2.4403, "close": 2.5058, "volume": 3877244, "id": "20060120_EVER" }
{"index": {"_index": "set_eod", "_type": "eod", "_id": "20060120_FANCY"}}
{"symbol": "FANCY", "eodDate": "2006-01-20T00:00:00", "open": 4.48, "high": 4.48, "low": 4.46, "close": 4.48, "volume": 52000, "id": "20060120_FANCY" }
{"index": {"_index": "set_eod", "_type": "eod", "_id": "20060120_FC"}}
{"symbol": "FC", "eodDate": "2006-01-20T00:00:00", "open": 0.9785, "high": 1.03, "low": 0.9785, "close": 1.0153, "volume": 39100, "id": "20060120_FC" }
{"index": {"_index": "set_eod", "_type": "eod", "_id": "20060120_FER"}}
{"symbol": "FER", "eodDate": "2006-01-20T00:00:00", "open": 2.42, "high": 2.54, "low": 2.38, "close": 2.46, "volume": 7601710, "id": "20060120_FER" }
{"index": {"_index": "set_eod", "_type": "eod", "_id": "20060120_FNS"}}
{"symbol": "FNS", "eodDate": "2006-01-20T00:00:00", "open": 17.1, "high": 17.1, "low": 16.7, "close": 16.8, "volume": 60700, "id": "20060120_FNS" }
{"index": {"_index": "set_eod", "_type": "eod", "_id": "20060120_FOCUS"}}
{"symbol": "FOCUS", "eodDate": "2006-01-20T00:00:00", "open": 2.88, "high": 2.88, "low": 2.62, "close": 2.62, "volume": 27100, "id": "20060120_FOCUS" }
{"index": {"_index": "set_eod", "_type": "eod", "_id": "20060120_FSS"}}
{"symbol": "FSS", "eodDate": "2006-01-20T00:00:00", "open": 5.55, "high": 5.7, "low": 5.5, "close": 5.5, "volume": 277600, "id": "20060120_FSS" }
{"index": {"_index": "set_eod", "_type": "eod", "_id": "20060120_GBX"}}
{"symbol": "GBX", "eodDate": "2006-01-20T00:00:00", "open": 3.7, "high": 3.88, "low": 3.6, "close": 3.6, "volume": 318538304, "id": "20060120_GBX" }
{"index": {"_index": "set_eod", "_type": "eod", "_id": "20060120_GC"}}
{"symbol": "GC", "eodDate": "2006-01-20T00:00:00", "open": 2.3, "high": 2.36, "low": 2.3, "close": 2.36, "volume": 322600, "id": "20060120_GC" }
{"index": {"_index": "set_eod", "_type": "eod", "_id": "20060120_GEL"}}
{"symbol": "GEL", "eodDate": "2006-01-20T00:00:00", "open": 0.64, "high": 0.65, "low": 0.63, "close": 0.63, "volume": 2119123, "id": "20060120_GEL" }
{"index": {"_index": "set_eod", "_type": "eod", "_id": "20060120_GENCO"}}
{"symbol": "GENCO", "eodDate": "2006-01-20T00:00:00", "open": 0.76, "high": 0.78, "low": 0.74, "close": 0.74, "volume": 17706300, "id": "20060120_GENCO" }
{"index": {"_index": "set_eod", "_type": "eod", "_id": "20060120_GFPT"}}
{"symbol": "GFPT", "eodDate": "2006-01-20T00:00:00", "open": 1.55, "high": 1.56, "low": 1.55, "close": 1.56, "volume": 496010, "id": "20060120_GFPT" }
{"index": {"_index": "set_eod", "_type": "eod", "_id": "20060120_GJS"}}
{"symbol": "GJS", "eodDate": "2006-01-20T00:00:00", "open": 0.78, "high": 0.81, "low": 0.74, "close": 0.74, "volume": 610928576, "id": "20060120_GJS" }
{"index": {"_index": "set_eod", "_type": "eod", "_id": "20060120_GL"}}
{"symbol": "GL", "eodDate": "2006-01-20T00:00:00", "open": 8.219, "high": 8.219, "low": 8.219, "close": 8.219, "volume": 10500, "id": "20060120_GL" }
{"index": {"_index": "set_eod", "_type": "eod", "_id": "20060120_GLAND"}}
{"symbol": "GLAND", "eodDate": "2006-01-20T00:00:00", "open": 7.8, "high": 8.35, "low": 7.8, "close": 8, "volume": 978300, "id": "20060120_GLAND" }
{"index": {"_index": "set_eod", "_type": "eod", "_id": "20060120_GLOW"}}
{"symbol": "GLOW", "eodDate": "2006-01-20T00:00:00", "open": 24.9, "high": 25.25, "low": 24.8, "close": 25, "volume": 3689738, "id": "20060120_GLOW" }
{"index": {"_index": "set_eod", "_type": "eod", "_id": "20060120_GOLD"}}
{"symbol": "GOLD", "eodDate": "2006-01-20T00:00:00", "open": 8.9, "high": 10.5, "low": 8.9, "close": 9.9, "volume": 6858001, "id": "20060120_GOLD" }
{"index": {"_index": "set_eod", "_type": "eod", "_id": "20060120_GRAMMY"}}
{"symbol": "GRAMMY", "eodDate": "2006-01-20T00:00:00", "open": 13.1, "high": 13.6, "low": 13, "close": 13, "volume": 366300, "id": "20060120_GRAMMY" }
{"index": {"_index": "set_eod", "_type": "eod", "_id": "20060120_GRAND"}}
{"symbol": "GRAND", "eodDate": "2006-01-20T00:00:00", "open": 2.18, "high": 2.42, "low": 2.18, "close": 2.36, "volume": 9163218, "id": "20060120_GRAND" }
{"index": {"_index": "set_eod", "_type": "eod", "_id": "20060120_GREEN"}}
{"symbol": "GREEN", "eodDate": "2006-01-20T00:00:00", "open": 10.5, "high": 10.8, "low": 10.4, "close": 10.8, "volume": 26900, "id": "20060120_GREEN" }
{"index": {"_index": "set_eod", "_type": "eod", "_id": "20060120_HANA"}}
{"symbol": "HANA", "eodDate": "2006-01-20T00:00:00", "open": 28, "high": 28.5, "low": 27.5, "close": 27.5, "volume": 1388300, "id": "20060120_HANA" }
{"index": {"_index": "set_eod", "_type": "eod", "_id": "20060120_HFT"}}
{"symbol": "HFT", "eodDate": "2006-01-20T00:00:00", "open": 1.03, "high": 1.05, "low": 1.01, "close": 1.03, "volume": 6700, "id": "20060120_HFT" }
{"index": {"_index": "set_eod", "_type": "eod", "_id": "20060120_HMPRO"}}
{"symbol": "HMPRO", "eodDate": "2006-01-20T00:00:00", "open": 2.3465, "high": 2.3465, "low": 2.3174, "close": 2.3319, "volume": 1482213, "id": "20060120_HMPRO" }
{"index": {"_index": "set_eod", "_type": "eod", "_id": "20060120_HTC"}}
{"symbol": "HTC", "eodDate": "2006-01-20T00:00:00", "open": 3.78, "high": 3.8, "low": 3.78, "close": 3.8, "volume": 304000, "id": "20060120_HTC" }
{"index": {"_index": "set_eod", "_type": "eod", "_id": "20060120_IHL"}}
{"symbol": "IHL", "eodDate": "2006-01-20T00:00:00", "open": 3.46, "high": 3.48, "low": 3.42, "close": 3.42, "volume": 142200, "id": "20060120_IHL" }
{"index": {"_index": "set_eod", "_type": "eod", "_id": "20060120_ILINK"}}
{"symbol": "ILINK", "eodDate": "2006-01-20T00:00:00", "open": 3.7981, "high": 3.7981, "low": 3.7433, "close": 3.7433, "volume": 188938, "id": "20060120_ILINK" }
{"index": {"_index": "set_eod", "_type": "eod", "_id": "20060120_INET"}}
{"symbol": "INET", "eodDate": "2006-01-20T00:00:00", "open": 3.1, "high": 3.14, "low": 3.1, "close": 3.1, "volume": 129000, "id": "20060120_INET" }
{"index": {"_index": "set_eod", "_type": "eod", "_id": "20060120_INOX"}}
{"symbol": "INOX", "eodDate": "2006-01-20T00:00:00", "open": 1.17, "high": 1.18, "low": 1.16, "close": 1.16, "volume": 11124100, "id": "20060120_INOX" }
{"index": {"_index": "set_eod", "_type": "eod", "_id": "20060120_INTUCH"}}
{"symbol": "INTUCH", "eodDate": "2006-01-20T00:00:00", "open": 47.25, "high": 47.75, "low": 46.75, "close": 47.25, "volume": 23673180, "id": "20060120_INTUCH" }
{"index": {"_index": "set_eod", "_type": "eod", "_id": "20060120_IRC"}}
{"symbol": "IRC", "eodDate": "2006-01-20T00:00:00", "open": 8.2, "high": 8.2, "low": 8.1, "close": 8.2, "volume": 33500, "id": "20060120_IRC" }
{"index": {"_index": "set_eod", "_type": "eod", "_id": "20060120_IRCP"}}
{"symbol": "IRCP", "eodDate": "2006-01-20T00:00:00", "open": 11.2, "high": 11.2, "low": 11.2, "close": 11.2, "volume": 5000, "id": "20060120_IRCP" }
{"index": {"_index": "set_eod", "_type": "eod", "_id": "20060120_IRPC"}}
{"symbol": "IRPC", "eodDate": "2006-01-20T00:00:00", "open": 8.2, "high": 8.25, "low": 8.1, "close": 8.1, "volume": 108295432, "id": "20060120_IRPC" }
{"index": {"_index": "set_eod", "_type": "eod", "_id": "20060120_IT"}}
{"symbol": "IT", "eodDate": "2006-01-20T00:00:00", "open": 6.15, "high": 6.15, "low": 6.1, "close": 6.1, "volume": 191500, "id": "20060120_IT" }
{"index": {"_index": "set_eod", "_type": "eod", "_id": "20060120_ITD"}}
{"symbol": "ITD", "eodDate": "2006-01-20T00:00:00", "open": 8.85, "high": 9, "low": 8.8, "close": 8.85, "volume": 12066900, "id": "20060120_ITD" }
{"index": {"_index": "set_eod", "_type": "eod", "_id": "20060120_JAS"}}
{"symbol": "JAS", "eodDate": "2006-01-20T00:00:00", "open": 0.57, "high": 0.57, "low": 0.52, "close": 0.52, "volume": 272910592, "id": "20060120_JAS" }
{"index": {"_index": "set_eod", "_type": "eod", "_id": "20060120_JCT"}}
{"symbol": "JCT", "eodDate": "2006-01-20T00:00:00", "open": 27, "high": 27.5, "low": 27, "close": 27.5, "volume": 600, "id": "20060120_JCT" }
{"index": {"_index": "set_eod", "_type": "eod", "_id": "20060120_JUTHA"}}
{"symbol": "JUTHA", "eodDate": "2006-01-20T00:00:00", "open": 6.6, "high": 6.65, "low": 6.55, "close": 6.6, "volume": 82200, "id": "20060120_JUTHA" }
{"index": {"_index": "set_eod", "_type": "eod", "_id": "20060120_KAMART"}}
{"symbol": "KAMART", "eodDate": "2006-01-20T00:00:00", "open": 0.82, "high": 0.84, "low": 0.82, "close": 0.82, "volume": 361800, "id": "20060120_KAMART" }
{"index": {"_index": "set_eod", "_type": "eod", "_id": "20060120_KASET"}}
{"symbol": "KASET", "eodDate": "2006-01-20T00:00:00", "open": 1.15, "high": 1.15, "low": 1.14, "close": 1.15, "volume": 447500, "id": "20060120_KASET" }
{"index": {"_index": "set_eod", "_type": "eod", "_id": "20060120_KBANK"}}
{"symbol": "KBANK", "eodDate": "2006-01-20T00:00:00", "open": 70, "high": 70, "low": 68, "close": 68.5, "volume": 7807220, "id": "20060120_KBANK" }
{"index": {"_index": "set_eod", "_type": "eod", "_id": "20060120_KC"}}
{"symbol": "KC", "eodDate": "2006-01-20T00:00:00", "open": 1.31, "high": 1.35, "low": 1.3, "close": 1.3, "volume": 972300, "id": "20060120_KC" }
{"index": {"_index": "set_eod", "_type": "eod", "_id": "20060120_KCAR"}}
{"symbol": "KCAR", "eodDate": "2006-01-20T00:00:00", "open": 5.15, "high": 5.2, "low": 5.15, "close": 5.15, "volume": 420000, "id": "20060120_KCAR" }
{"index": {"_index": "set_eod", "_type": "eod", "_id": "20060120_KCE"}}
{"symbol": "KCE", "eodDate": "2006-01-20T00:00:00", "open": 4.6967, "high": 4.6967, "low": 4.6191, "close": 4.6191, "volume": 1308617, "id": "20060120_KCE" }
{"index": {"_index": "set_eod", "_type": "eod", "_id": "20060120_KGI"}}
{"symbol": "KGI", "eodDate": "2006-01-20T00:00:00", "open": 2.48, "high": 2.5, "low": 2.42, "close": 2.44, "volume": 9111711, "id": "20060120_KGI" }
{"index": {"_index": "set_eod", "_type": "eod", "_id": "20060120_KKC"}}
{"symbol": "KKC", "eodDate": "2006-01-20T00:00:00", "open": 7.7397, "high": 7.7397, "low": 7.7397, "close": 7.7397, "volume": 367, "id": "20060120_KKC" }
{"index": {"_index": "set_eod", "_type": "eod", "_id": "20060120_KKP"}}
{"symbol": "KKP", "eodDate": "2006-01-20T00:00:00", "open": 34.5, "high": 35.75, "low": 33.75, "close": 35, "volume": 3224026, "id": "20060120_KKP" }
{"index": {"_index": "set_eod", "_type": "eod", "_id": "20060120_KSL"}}
{"symbol": "KSL", "eodDate": "2006-01-20T00:00:00", "open": 9.25, "high": 9.75, "low": 9.25, "close": 9.7, "volume": 3170990, "id": "20060120_KSL" }
{"index": {"_index": "set_eod", "_type": "eod", "_id": "20060120_KTB"}}
{"symbol": "KTB", "eodDate": "2006-01-20T00:00:00", "open": 12, "high": 12, "low": 11.6, "close": 11.7, "volume": 41011144, "id": "20060120_KTB" }
{"index": {"_index": "set_eod", "_type": "eod", "_id": "20060120_KTC"}}
{"symbol": "KTC", "eodDate": "2006-01-20T00:00:00", "open": 22, "high": 22.7, "low": 22, "close": 22.5, "volume": 1036847, "id": "20060120_KTC" }
{"index": {"_index": "set_eod", "_type": "eod", "_id": "20060120_KWG"}}
{"symbol": "KWG", "eodDate": "2006-01-20T00:00:00", "open": 2.22, "high": 2.44, "low": 2.18, "close": 2.18, "volume": 782900, "id": "20060120_KWG" }
{"index": {"_index": "set_eod", "_type": "eod", "_id": "20060120_KYE"}}
{"symbol": "KYE", "eodDate": "2006-01-20T00:00:00", "open": 59.5, "high": 59.5, "low": 59.5, "close": 59.5, "volume": 14700, "id": "20060120_KYE" }
{"index": {"_index": "set_eod", "_type": "eod", "_id": "20060120_LALIN"}}
{"symbol": "LALIN", "eodDate": "2006-01-20T00:00:00", "open": 6.05, "high": 6.5, "low": 6.05, "close": 6.5, "volume": 3773647, "id": "20060120_LALIN" }
{"index": {"_index": "set_eod", "_type": "eod", "_id": "20060120_LANNA"}}
{"symbol": "LANNA", "eodDate": "2006-01-20T00:00:00", "open": 10.7, "high": 10.8, "low": 10.7, "close": 10.7, "volume": 488300, "id": "20060120_LANNA" }
{"index": {"_index": "set_eod", "_type": "eod", "_id": "20060120_LEE"}}
{"symbol": "LEE", "eodDate": "2006-01-20T00:00:00", "open": 2.92, "high": 2.96, "low": 2.9, "close": 2.9, "volume": 89400, "id": "20060120_LEE" }
{"index": {"_index": "set_eod", "_type": "eod", "_id": "20060120_LH"}}
{"symbol": "LH", "eodDate": "2006-01-20T00:00:00", "open": 9.35, "high": 9.65, "low": 9.35, "close": 9.55, "volume": 26036200, "id": "20060120_LH" }
{"index": {"_index": "set_eod", "_type": "eod", "_id": "20060120_LOXLEY"}}
{"symbol": "LOXLEY", "eodDate": "2006-01-20T00:00:00", "open": 3.56, "high": 3.62, "low": 3.26, "close": 3.28, "volume": 162355984, "id": "20060120_LOXLEY" }
{"index": {"_index": "set_eod", "_type": "eod", "_id": "20060120_LPN"}}
{"symbol": "LPN", "eodDate": "2006-01-20T00:00:00", "open": 4.02, "high": 4.14, "low": 4.02, "close": 4.02, "volume": 12598810, "id": "20060120_LPN" }
{"index": {"_index": "set_eod", "_type": "eod", "_id": "20060120_LRH"}}
{"symbol": "LRH", "eodDate": "2006-01-20T00:00:00", "open": 22.8131, "high": 22.8131, "low": 22.8131, "close": 22.8131, "volume": 8591, "id": "20060120_LRH" }
{"index": {"_index": "set_eod", "_type": "eod", "_id": "20060120_LST"}}
{"symbol": "LST", "eodDate": "2006-01-20T00:00:00", "open": 1.65, "high": 1.66, "low": 1.64, "close": 1.64, "volume": 1220000, "id": "20060120_LST" }
{"index": {"_index": "set_eod", "_type": "eod", "_id": "20060120_LTX"}}
{"symbol": "LTX", "eodDate": "2006-01-20T00:00:00", "open": 40, "high": 40, "low": 40, "close": 40, "volume": 100, "id": "20060120_LTX" }
{"index": {"_index": "set_eod", "_type": "eod", "_id": "20060120_LVT"}}
{"symbol": "LVT", "eodDate": "2006-01-20T00:00:00", "open": 2.42, "high": 2.5, "low": 2.4, "close": 2.4, "volume": 298600, "id": "20060120_LVT" }
{"index": {"_index": "set_eod", "_type": "eod", "_id": "20060120_M-CHAI"}}
{"symbol": "M-CHAI", "eodDate": "2006-01-20T00:00:00", "open": 24, "high": 24, "low": 24, "close": 24, "volume": 1600, "id": "20060120_M-CHAI" }
{"index": {"_index": "set_eod", "_type": "eod", "_id": "20060120_MACO"}}
{"symbol": "MACO", "eodDate": "2006-01-20T00:00:00", "open": 5.05, "high": 5.1, "low": 5.05, "close": 5.1, "volume": 14000, "id": "20060120_MACO" }
{"index": {"_index": "set_eod", "_type": "eod", "_id": "20060120_MAJOR"}}
{"symbol": "MAJOR", "eodDate": "2006-01-20T00:00:00", "open": 14.5, "high": 14.8, "low": 14.5, "close": 14.8, "volume": 4314789, "id": "20060120_MAJOR" }
{"index": {"_index": "set_eod", "_type": "eod", "_id": "20060120_MAKRO"}}
{"symbol": "MAKRO", "eodDate": "2006-01-20T00:00:00", "open": 70, "high": 71, "low": 70, "close": 71, "volume": 35300, "id": "20060120_MAKRO" }
{"index": {"_index": "set_eod", "_type": "eod", "_id": "20060120_MALEE"}}
{"symbol": "MALEE", "eodDate": "2006-01-20T00:00:00", "open": 4.1, "high": 4.2, "low": 4.1, "close": 4.1, "volume": 432000, "id": "20060120_MALEE" }
{"index": {"_index": "set_eod", "_type": "eod", "_id": "20060120_MATCH"}}
{"symbol": "MATCH", "eodDate": "2006-01-20T00:00:00", "open": 2, "high": 2.04, "low": 2, "close": 2, "volume": 66500, "id": "20060120_MATCH" }
{"index": {"_index": "set_eod", "_type": "eod", "_id": "20060120_MATI"}}
{"symbol": "MATI", "eodDate": "2006-01-20T00:00:00", "open": 11.2, "high": 11.2, "low": 11.2, "close": 11.2, "volume": 4500, "id": "20060120_MATI" }
{"index": {"_index": "set_eod", "_type": "eod", "_id": "20060120_MBK"}}
{"symbol": "MBK", "eodDate": "2006-01-20T00:00:00", "open": 45.5, "high": 47.5, "low": 45.5, "close": 47, "volume": 122400, "id": "20060120_MBK" }
{"index": {"_index": "set_eod", "_type": "eod", "_id": "20060120_MBKET"}}
{"symbol": "MBKET", "eodDate": "2006-01-20T00:00:00", "open": 29.25, "high": 29.25, "low": 27.75, "close": 28.5, "volume": 7831800, "id": "20060120_MBKET" }
{"index": {"_index": "set_eod", "_type": "eod", "_id": "20060120_MCOT"}}
{"symbol": "MCOT", "eodDate": "2006-01-20T00:00:00", "open": 29.75, "high": 31.5, "low": 29.75, "close": 31.25, "volume": 1578900, "id": "20060120_MCOT" }
{"index": {"_index": "set_eod", "_type": "eod", "_id": "20060120_MCS"}}
{"symbol": "MCS", "eodDate": "2006-01-20T00:00:00", "open": 2.74, "high": 2.76, "low": 2.72, "close": 2.72, "volume": 3007000, "id": "20060120_MCS" }
{"index": {"_index": "set_eod", "_type": "eod", "_id": "20060120_METCO"}}
{"symbol": "METCO", "eodDate": "2006-01-20T00:00:00", "open": 286, "high": 286, "low": 284, "close": 284, "volume": 2400, "id": "20060120_METCO" }
{"index": {"_index": "set_eod", "_type": "eod", "_id": "20060120_MFEC"}}
{"symbol": "MFEC", "eodDate": "2006-01-20T00:00:00", "open": 5.1, "high": 5.1, "low": 4.98, "close": 4.98, "volume": 242400, "id": "20060120_MFEC" }
{"index": {"_index": "set_eod", "_type": "eod", "_id": "20060120_MIDA"}}
{"symbol": "MIDA", "eodDate": "2006-01-20T00:00:00", "open": 2.76, "high": 2.78, "low": 2.68, "close": 2.74, "volume": 7660935, "id": "20060120_MIDA" }
{"index": {"_index": "set_eod", "_type": "eod", "_id": "20060120_MINT"}}
{"symbol": "MINT", "eodDate": "2006-01-20T00:00:00", "open": 5.9545, "high": 6, "low": 5.9091, "close": 5.9091, "volume": 747350, "id": "20060120_MINT" }
{"index": {"_index": "set_eod", "_type": "eod", "_id": "20060120_MK"}}
{"symbol": "MK", "eodDate": "2006-01-20T00:00:00", "open": 2.66, "high": 2.82, "low": 2.66, "close": 2.74, "volume": 23573500, "id": "20060120_MK" }
{"index": {"_index": "set_eod", "_type": "eod", "_id": "20060120_ML"}}
{"symbol": "ML", "eodDate": "2006-01-20T00:00:00", "open": 1.01, "high": 1.02, "low": 1.01, "close": 1.02, "volume": 8000, "id": "20060120_ML" }
{"index": {"_index": "set_eod", "_type": "eod", "_id": "20060120_MODERN"}}
{"symbol": "MODERN", "eodDate": "2006-01-20T00:00:00", "open": 37, "high": 37.25, "low": 37, "close": 37.25, "volume": 73800, "id": "20060120_MODERN" }
{"index": {"_index": "set_eod", "_type": "eod", "_id": "20060120_MPG"}}
{"symbol": "MPG", "eodDate": "2006-01-20T00:00:00", "open": 2.487, "high": 2.5443, "low": 2.4487, "close": 2.4487, "volume": 967800, "id": "20060120_MPG" }
{"index": {"_index": "set_eod", "_type": "eod", "_id": "20060120_MPIC"}}
{"symbol": "MPIC", "eodDate": "2006-01-20T00:00:00", "open": 0.4288, "high": 0.4368, "low": 0.4207, "close": 0.4207, "volume": 8924000, "id": "20060120_MPIC" }
{"index": {"_index": "set_eod", "_type": "eod", "_id": "20060120_MSC"}}
{"symbol": "MSC", "eodDate": "2006-01-20T00:00:00", "open": 2.8, "high": 2.8, "low": 2.8, "close": 2.8, "volume": 20000, "id": "20060120_MSC" }
{"index": {"_index": "set_eod", "_type": "eod", "_id": "20060120_NC"}}
{"symbol": "NC", "eodDate": "2006-01-20T00:00:00", "open": 6, "high": 6, "low": 6, "close": 6, "volume": 1000, "id": "20060120_NC" }
{"index": {"_index": "set_eod", "_type": "eod", "_id": "20060120_NCH"}}
{"symbol": "NCH", "eodDate": "2006-01-20T00:00:00", "open": 1.22, "high": 1.26, "low": 1.22, "close": 1.23, "volume": 423000, "id": "20060120_NCH" }
{"index": {"_index": "set_eod", "_type": "eod", "_id": "20060120_NEP"}}
{"symbol": "NEP", "eodDate": "2006-01-20T00:00:00", "open": 0.324, "high": 0.326, "low": 0.32, "close": 0.322, "volume": 369000, "id": "20060120_NEP" }
{"index": {"_index": "set_eod", "_type": "eod", "_id": "20060120_NEW"}}
{"symbol": "NEW", "eodDate": "2006-01-20T00:00:00", "open": 14, "high": 15.9, "low": 14, "close": 15.9, "volume": 700, "id": "20060120_NEW" }
{"index": {"_index": "set_eod", "_type": "eod", "_id": "20060120_NEWS"}}
{"symbol": "NEWS", "eodDate": "2006-01-20T00:00:00", "open": 0.312, "high": 0.316, "low": 0.312, "close": 0.316, "volume": 60000, "id": "20060120_NEWS" }
{"index": {"_index": "set_eod", "_type": "eod", "_id": "20060120_NKI"}}
{"symbol": "NKI", "eodDate": "2006-01-20T00:00:00", "open": 54.5, "high": 55, "low": 54.5, "close": 55, "volume": 4500, "id": "20060120_NKI" }
{"index": {"_index": "set_eod", "_type": "eod", "_id": "20060120_NMG"}}
{"symbol": "NMG", "eodDate": "2006-01-20T00:00:00", "open": 10.1, "high": 10.9, "low": 10.1, "close": 10.3, "volume": 225135, "id": "20060120_NMG" }
{"index": {"_index": "set_eod", "_type": "eod", "_id": "20060120_NNCL"}}
{"symbol": "NNCL", "eodDate": "2006-01-20T00:00:00", "open": 0.945, "high": 0.95, "low": 0.94, "close": 0.94, "volume": 624000, "id": "20060120_NNCL" }
{"index": {"_index": "set_eod", "_type": "eod", "_id": "20060120_NOBLE"}}
{"symbol": "NOBLE", "eodDate": "2006-01-20T00:00:00", "open": 4.04, "high": 4.2, "low": 4.04, "close": 4.08, "volume": 674000, "id": "20060120_NOBLE" }
{"index": {"_index": "set_eod", "_type": "eod", "_id": "20060120_NPP"}}
{"symbol": "NPP", "eodDate": "2006-01-20T00:00:00", "open": 14.5, "high": 14.7, "low": 14.1, "close": 14.1, "volume": 600, "id": "20060120_NPP" }
{"index": {"_index": "set_eod", "_type": "eod", "_id": "20060120_NTV"}}
{"symbol": "NTV", "eodDate": "2006-01-20T00:00:00", "open": 62, "high": 64.5, "low": 62, "close": 64.5, "volume": 2700, "id": "20060120_NTV" }
{"index": {"_index": "set_eod", "_type": "eod", "_id": "20060120_NWR"}}
{"symbol": "NWR", "eodDate": "2006-01-20T00:00:00", "open": 1.08, "high": 1.1, "low": 1.06, "close": 1.06, "volume": 31131596, "id": "20060120_NWR" }
{"index": {"_index": "set_eod", "_type": "eod", "_id": "20060120_OCC"}}
{"symbol": "OCC", "eodDate": "2006-01-20T00:00:00", "open": 11, "high": 11, "low": 11, "close": 11, "volume": 10000, "id": "20060120_OCC" }
{"index": {"_index": "set_eod", "_type": "eod", "_id": "20060120_OGC"}}
{"symbol": "OGC", "eodDate": "2006-01-20T00:00:00", "open": 67.5, "high": 67.5, "low": 67, "close": 67, "volume": 9400, "id": "20060120_OGC" }
{"index": {"_index": "set_eod", "_type": "eod", "_id": "20060120_OISHI"}}
{"symbol": "OISHI", "eodDate": "2006-01-20T00:00:00", "open": 31.5, "high": 31.5, "low": 31.25, "close": 31.5, "volume": 479700, "id": "20060120_OISHI" }
{"index": {"_index": "set_eod", "_type": "eod", "_id": "20060120_PAF"}}
{"symbol": "PAF", "eodDate": "2006-01-20T00:00:00", "open": 3.82, "high": 3.82, "low": 3.8, "close": 3.82, "volume": 23800, "id": "20060120_PAF" }
{"index": {"_index": "set_eod", "_type": "eod", "_id": "20060120_PAP"}}
{"symbol": "PAP", "eodDate": "2006-01-20T00:00:00", "open": 1.63, "high": 1.64, "low": 1.63, "close": 1.63, "volume": 308000, "id": "20060120_PAP" }
{"index": {"_index": "set_eod", "_type": "eod", "_id": "20060120_PB"}}
{"symbol": "PB", "eodDate": "2006-01-20T00:00:00", "open": 66.9055, "high": 66.9055, "low": 66.5025, "close": 66.9055, "volume": 6078, "id": "20060120_PB" }
{"index": {"_index": "set_eod", "_type": "eod", "_id": "20060120_PDI"}}
{"symbol": "PDI", "eodDate": "2006-01-20T00:00:00", "open": 19.3, "high": 19.4, "low": 19.1, "close": 19.2, "volume": 462100, "id": "20060120_PDI" }
{"index": {"_index": "set_eod", "_type": "eod", "_id": "20060120_PERM"}}
{"symbol": "PERM", "eodDate": "2006-01-20T00:00:00", "open": 3.56, "high": 4.56, "low": 3.52, "close": 4.56, "volume": 47801200, "id": "20060120_PERM" }
{"index": {"_index": "set_eod", "_type": "eod", "_id": "20060120_PF"}}
{"symbol": "PF", "eodDate": "2006-01-20T00:00:00", "open": 5.6, "high": 5.9, "low": 5.55, "close": 5.7, "volume": 23178492, "id": "20060120_PF" }
{"index": {"_index": "set_eod", "_type": "eod", "_id": "20060120_PICO"}}
{"symbol": "PICO", "eodDate": "2006-01-20T00:00:00", "open": 2.58, "high": 2.6, "low": 2.56, "close": 2.56, "volume": 314200, "id": "20060120_PICO" }
{"index": {"_index": "set_eod", "_type": "eod", "_id": "20060120_PK"}}
{"symbol": "PK", "eodDate": "2006-01-20T00:00:00", "open": 2.35, "high": 2.36, "low": 2.34, "close": 2.34, "volume": 85000, "id": "20060120_PK" }
{"index": {"_index": "set_eod", "_type": "eod", "_id": "20060120_PL"}}
{"symbol": "PL", "eodDate": "2006-01-20T00:00:00", "open": 2.76, "high": 2.76, "low": 2.72, "close": 2.76, "volume": 110600, "id": "20060120_PL" }
{"index": {"_index": "set_eod", "_type": "eod", "_id": "20060120_PLE"}}
{"symbol": "PLE", "eodDate": "2006-01-20T00:00:00", "open": 7.882, "high": 8.0156, "low": 7.5703, "close": 7.5703, "volume": 14041378, "id": "20060120_PLE" }
{"index": {"_index": "set_eod", "_type": "eod", "_id": "20060120_POST"}}
{"symbol": "POST", "eodDate": "2006-01-20T00:00:00", "open": 6.8, "high": 7, "low": 6.5, "close": 7, "volume": 38400, "id": "20060120_POST" }
{"index": {"_index": "set_eod", "_type": "eod", "_id": "20060120_PPM"}}
{"symbol": "PPM", "eodDate": "2006-01-20T00:00:00", "open": 2.68, "high": 2.76, "low": 2.68, "close": 2.68, "volume": 466400, "id": "20060120_PPM" }
{"index": {"_index": "set_eod", "_type": "eod", "_id": "20060120_PR"}}
{"symbol": "PR", "eodDate": "2006-01-20T00:00:00", "open": 93.5, "high": 93.5, "low": 93.5, "close": 93.5, "volume": 1000, "id": "20060120_PR" }
{"index": {"_index": "set_eod", "_type": "eod", "_id": "20060120_PRANDA"}}
{"symbol": "PRANDA", "eodDate": "2006-01-20T00:00:00", "open": 6.55, "high": 6.55, "low": 6.5, "close": 6.5, "volume": 26800, "id": "20060120_PRANDA" }
{"index": {"_index": "set_eod", "_type": "eod", "_id": "20060120_PREB"}}
{"symbol": "PREB", "eodDate": "2006-01-20T00:00:00", "open": 2.86, "high": 2.94, "low": 2.76, "close": 2.82, "volume": 30106300, "id": "20060120_PREB" }
{"index": {"_index": "set_eod", "_type": "eod", "_id": "20060120_PRG"}}
{"symbol": "PRG", "eodDate": "2006-01-20T00:00:00", "open": 25, "high": 25, "low": 25, "close": 25, "volume": 700, "id": "20060120_PRG" }
{"index": {"_index": "set_eod", "_type": "eod", "_id": "20060120_PRIN"}}
{"symbol": "PRIN", "eodDate": "2006-01-20T00:00:00", "open": 2.3268, "high": 2.3914, "low": 2.2945, "close": 2.3429, "volume": 22537670, "id": "20060120_PRIN" }
{"index": {"_index": "set_eod", "_type": "eod", "_id": "20060120_PRINC"}}
{"symbol": "PRINC", "eodDate": "2006-01-20T00:00:00", "open": 7.35, "high": 7.7, "low": 7.3, "close": 7.55, "volume": 10659400, "id": "20060120_PRINC" }
{"index": {"_index": "set_eod", "_type": "eod", "_id": "20060120_PRO"}}
{"symbol": "PRO", "eodDate": "2006-01-20T00:00:00", "open": 1.0725, "high": 1.0822, "low": 1.0725, "close": 1.0725, "volume": 389743, "id": "20060120_PRO" }
{"index": {"_index": "set_eod", "_type": "eod", "_id": "20060120_PSL"}}
{"symbol": "PSL", "eodDate": "2006-01-20T00:00:00", "open": 15.25, "high": 15.75, "low": 15.125, "close": 15.75, "volume": 1818208, "id": "20060120_PSL" }
{"index": {"_index": "set_eod", "_type": "eod", "_id": "20060120_PTL"}}
{"symbol": "PTL", "eodDate": "2006-01-20T00:00:00", "open": 5.65, "high": 5.8, "low": 5.6, "close": 5.6, "volume": 1281500, "id": "20060120_PTL" }
{"index": {"_index": "set_eod", "_type": "eod", "_id": "20060120_PTT"}}
{"symbol": "PTT", "eodDate": "2006-01-20T00:00:00", "open": 244, "high": 246, "low": 242, "close": 244, "volume": 5012255, "id": "20060120_PTT" }
{"index": {"_index": "set_eod", "_type": "eod", "_id": "20060120_PTTEP"}}
{"symbol": "PTTEP", "eodDate": "2006-01-20T00:00:00", "open": 103.2, "high": 104, "low": 103.2, "close": 103.2, "volume": 2812625, "id": "20060120_PTTEP" }
{"index": {"_index": "set_eod", "_type": "eod", "_id": "20060120_PYLON"}}
{"symbol": "PYLON", "eodDate": "2006-01-20T00:00:00", "open": 2.18, "high": 2.22, "low": 2.14, "close": 2.2, "volume": 898000, "id": "20060120_PYLON" }
{"index": {"_index": "set_eod", "_type": "eod", "_id": "20060120_Q-CON"}}
{"symbol": "Q-CON", "eodDate": "2006-01-20T00:00:00", "open": 3.04, "high": 3.1, "low": 2.96, "close": 2.96, "volume": 561600, "id": "20060120_Q-CON" }
{"index": {"_index": "set_eod", "_type": "eod", "_id": "20060120_QH"}}
{"symbol": "QH", "eodDate": "2006-01-20T00:00:00", "open": 1.23, "high": 1.26, "low": 1.23, "close": 1.25, "volume": 13628003, "id": "20060120_QH" }
{"index": {"_index": "set_eod", "_type": "eod", "_id": "20060120_RATCH"}}
{"symbol": "RATCH", "eodDate": "2006-01-20T00:00:00", "open": 41, "high": 42.75, "low": 41, "close": 42, "volume": 1592661, "id": "20060120_RATCH" }
{"index": {"_index": "set_eod", "_type": "eod", "_id": "20060120_RCI"}}
{"symbol": "RCI", "eodDate": "2006-01-20T00:00:00", "open": 2.1, "high": 2.12, "low": 2.1, "close": 2.11, "volume": 118000, "id": "20060120_RCI" }
{"index": {"_index": "set_eod", "_type": "eod", "_id": "20060120_RCL"}}
{"symbol": "RCL", "eodDate": "2006-01-20T00:00:00", "open": 26, "high": 26, "low": 25, "close": 25.5, "volume": 3330102, "id": "20060120_RCL" }
{"index": {"_index": "set_eod", "_type": "eod", "_id": "20060120_RML"}}
{"symbol": "RML", "eodDate": "2006-01-20T00:00:00", "open": 1.19, "high": 1.21, "low": 1.19, "close": 1.2, "volume": 5659700, "id": "20060120_RML" }
{"index": {"_index": "set_eod", "_type": "eod", "_id": "20060120_ROBINS"}}
{"symbol": "ROBINS", "eodDate": "2006-01-20T00:00:00", "open": 7.9, "high": 7.95, "low": 7.85, "close": 7.9, "volume": 832800, "id": "20060120_ROBINS" }
{"index": {"_index": "set_eod", "_type": "eod", "_id": "20060120_ROCK"}}
{"symbol": "ROCK", "eodDate": "2006-01-20T00:00:00", "open": 14.5, "high": 14.5, "low": 14.5, "close": 14.5, "volume": 100, "id": "20060120_ROCK" }
{"index": {"_index": "set_eod", "_type": "eod", "_id": "20060120_ROJNA"}}
{"symbol": "ROJNA", "eodDate": "2006-01-20T00:00:00", "open": 9.85, "high": 10, "low": 9.8, "close": 10, "volume": 344000, "id": "20060120_ROJNA" }
{"index": {"_index": "set_eod", "_type": "eod", "_id": "20060120_RPC"}}
{"symbol": "RPC", "eodDate": "2006-01-20T00:00:00", "open": 7.55, "high": 7.6, "low": 7.5, "close": 7.5, "volume": 150200, "id": "20060120_RPC" }
{"index": {"_index": "set_eod", "_type": "eod", "_id": "20060120_SALEE"}}
{"symbol": "SALEE", "eodDate": "2006-01-20T00:00:00", "open": 2.3478, "high": 2.3478, "low": 2.2821, "close": 2.2821, "volume": 1997209, "id": "20060120_SALEE" }
{"index": {"_index": "set_eod", "_type": "eod", "_id": "20060120_SAM"}}
{"symbol": "SAM", "eodDate": "2006-01-20T00:00:00", "open": 2.96, "high": 2.96, "low": 2.96, "close": 2.96, "volume": 5000, "id": "20060120_SAM" }
{"index": {"_index": "set_eod", "_type": "eod", "_id": "20060120_SAMART"}}
{"symbol": "SAMART", "eodDate": "2006-01-20T00:00:00", "open": 8.3, "high": 8.5, "low": 8.3, "close": 8.4, "volume": 26308300, "id": "20060120_SAMART" }
{"index": {"_index": "set_eod", "_type": "eod", "_id": "20060120_SAMCO"}}
{"symbol": "SAMCO", "eodDate": "2006-01-20T00:00:00", "open": 3.02, "high": 3.02, "low": 2.96, "close": 2.98, "volume": 685500, "id": "20060120_SAMCO" }
{"index": {"_index": "set_eod", "_type": "eod", "_id": "20060120_SAMTEL"}}
{"symbol": "SAMTEL", "eodDate": "2006-01-20T00:00:00", "open": 6.1, "high": 6.15, "low": 6.05, "close": 6.05, "volume": 10422500, "id": "20060120_SAMTEL" }
{"index": {"_index": "set_eod", "_type": "eod", "_id": "20060120_SAT"}}
{"symbol": "SAT", "eodDate": "2006-01-20T00:00:00", "open": 14.9, "high": 15.3, "low": 14.8, "close": 15.1, "volume": 936500, "id": "20060120_SAT" }
{"index": {"_index": "set_eod", "_type": "eod", "_id": "20060120_SAUCE"}}
{"symbol": "SAUCE", "eodDate": "2006-01-20T00:00:00", "open": 97, "high": 100, "low": 96.5, "close": 100, "volume": 1600, "id": "20060120_SAUCE" }
{"index": {"_index": "set_eod", "_type": "eod", "_id": "20060120_SAWANG"}}
{"symbol": "SAWANG", "eodDate": "2006-01-20T00:00:00", "open": 20, "high": 20, "low": 20, "close": 20, "volume": 100, "id": "20060120_SAWANG" }
{"index": {"_index": "set_eod", "_type": "eod", "_id": "20060120_SC"}}
{"symbol": "SC", "eodDate": "2006-01-20T00:00:00", "open": 16.5, "high": 16.6, "low": 15.5, "close": 16, "volume": 13121301, "id": "20060120_SC" }
{"index": {"_index": "set_eod", "_type": "eod", "_id": "20060120_SCB"}}
{"symbol": "SCB", "eodDate": "2006-01-20T00:00:00", "open": 57, "high": 57, "low": 56, "close": 57, "volume": 5958184, "id": "20060120_SCB" }
{"index": {"_index": "set_eod", "_type": "eod", "_id": "20060120_SCC"}}
{"symbol": "SCC", "eodDate": "2006-01-20T00:00:00", "open": 244, "high": 250, "low": 244, "close": 250, "volume": 1537880, "id": "20060120_SCC" }
{"index": {"_index": "set_eod", "_type": "eod", "_id": "20060120_SCCC"}}
{"symbol": "SCCC", "eodDate": "2006-01-20T00:00:00", "open": 374, "high": 382, "low": 366, "close": 372, "volume": 64001, "id": "20060120_SCCC" }
{"index": {"_index": "set_eod", "_type": "eod", "_id": "20060120_SCG"}}
{"symbol": "SCG", "eodDate": "2006-01-20T00:00:00", "open": 3.9, "high": 3.9, "low": 3.9, "close": 3.9, "volume": 500, "id": "20060120_SCG" }
{"index": {"_index": "set_eod", "_type": "eod", "_id": "20060120_SCP"}}
{"symbol": "SCP", "eodDate": "2006-01-20T00:00:00", "open": 10.9, "high": 11, "low": 10.7, "close": 10.7, "volume": 42600, "id": "20060120_SCP" }
{"index": {"_index": "set_eod", "_type": "eod", "_id": "20060120_SE-ED"}}
{"symbol": "SE-ED", "eodDate": "2006-01-20T00:00:00", "open": 6.1, "high": 6.15, "low": 6.1, "close": 6.15, "volume": 112600, "id": "20060120_SE-ED" }
{"index": {"_index": "set_eod", "_type": "eod", "_id": "20060120_SEAFCO"}}
{"symbol": "SEAFCO", "eodDate": "2006-01-20T00:00:00", "open": 3.74, "high": 3.96, "low": 3.72, "close": 3.88, "volume": 3390400, "id": "20060120_SEAFCO" }
{"index": {"_index": "set_eod", "_type": "eod", "_id": "20060120_SF"}}
{"symbol": "SF", "eodDate": "2006-01-20T00:00:00", "open": 4.223, "high": 4.223, "low": 4.1277, "close": 4.1277, "volume": 1487988, "id": "20060120_SF" }
{"index": {"_index": "set_eod", "_type": "eod", "_id": "20060120_SHANG"}}
{"symbol": "SHANG", "eodDate": "2006-01-20T00:00:00", "open": 31.75, "high": 31.75, "low": 31.75, "close": 31.75, "volume": 1000, "id": "20060120_SHANG" }
{"index": {"_index": "set_eod", "_type": "eod", "_id": "20060120_SIAM"}}
{"symbol": "SIAM", "eodDate": "2006-01-20T00:00:00", "open": 2.1, "high": 2.14, "low": 2.06, "close": 2.08, "volume": 3156500, "id": "20060120_SIAM" }
{"index": {"_index": "set_eod", "_type": "eod", "_id": "20060120_SIM"}}
{"symbol": "SIM", "eodDate": "2006-01-20T00:00:00", "open": 1.34, "high": 1.37, "low": 1.33, "close": 1.35, "volume": 6535200, "id": "20060120_SIM" }
{"index": {"_index": "set_eod", "_type": "eod", "_id": "20060120_SINGER"}}
{"symbol": "SINGER", "eodDate": "2006-01-20T00:00:00", "open": 4.02, "high": 4.06, "low": 4.02, "close": 4.06, "volume": 4500, "id": "20060120_SINGER" }
{"index": {"_index": "set_eod", "_type": "eod", "_id": "20060120_SIRI"}}
{"symbol": "SIRI", "eodDate": "2006-01-20T00:00:00", "open": 3.06, "high": 3.12, "low": 3, "close": 3.02, "volume": 8261692, "id": "20060120_SIRI" }
{"index": {"_index": "set_eod", "_type": "eod", "_id": "20060120_SIS"}}
{"symbol": "SIS", "eodDate": "2006-01-20T00:00:00", "open": 2.96, "high": 3, "low": 2.94, "close": 3, "volume": 144900, "id": "20060120_SIS" }
{"index": {"_index": "set_eod", "_type": "eod", "_id": "20060120_SITHAI"}}
{"symbol": "SITHAI", "eodDate": "2006-01-20T00:00:00", "open": 8.1, "high": 8.15, "low": 8.05, "close": 8.05, "volume": 27200, "id": "20060120_SITHAI" }
{"index": {"_index": "set_eod", "_type": "eod", "_id": "20060120_SKR"}}
{"symbol": "SKR", "eodDate": "2006-01-20T00:00:00", "open": 8.5, "high": 8.85, "low": 8.5, "close": 8.8, "volume": 1042900, "id": "20060120_SKR" }
{"index": {"_index": "set_eod", "_type": "eod", "_id": "20060120_SMIT"}}
{"symbol": "SMIT", "eodDate": "2006-01-20T00:00:00", "open": 2.06, "high": 2.12, "low": 2.06, "close": 2.08, "volume": 582900, "id": "20060120_SMIT" }
{"index": {"_index": "set_eod", "_type": "eod", "_id": "20060120_SMK"}}
{"symbol": "SMK", "eodDate": "2006-01-20T00:00:00", "open": 36, "high": 36.5, "low": 36, "close": 36.5, "volume": 36100, "id": "20060120_SMK" }
{"index": {"_index": "set_eod", "_type": "eod", "_id": "20060120_SMM"}}
{"symbol": "SMM", "eodDate": "2006-01-20T00:00:00", "open": 1.82, "high": 1.83, "low": 1.8, "close": 1.81, "volume": 1048700, "id": "20060120_SMM" }
{"index": {"_index": "set_eod", "_type": "eod", "_id": "20060120_SNC"}}
{"symbol": "SNC", "eodDate": "2006-01-20T00:00:00", "open": 4.96, "high": 4.96, "low": 4.96, "close": 4.96, "volume": 30000, "id": "20060120_SNC" }
{"index": {"_index": "set_eod", "_type": "eod", "_id": "20060120_SNP"}}
{"symbol": "SNP", "eodDate": "2006-01-20T00:00:00", "open": 23, "high": 23, "low": 23, "close": 23, "volume": 3900, "id": "20060120_SNP" }
{"index": {"_index": "set_eod", "_type": "eod", "_id": "20060120_SOLAR"}}
{"symbol": "SOLAR", "eodDate": "2006-01-20T00:00:00", "open": 8.05, "high": 8.05, "low": 7.7, "close": 7.7, "volume": 2286400, "id": "20060120_SOLAR" }
{"index": {"_index": "set_eod", "_type": "eod", "_id": "20060120_SORKON"}}
{"symbol": "SORKON", "eodDate": "2006-01-20T00:00:00", "open": 16.1905, "high": 16.4762, "low": 16.1905, "close": 16.4762, "volume": 19320, "id": "20060120_SORKON" }
{"index": {"_index": "set_eod", "_type": "eod", "_id": "20060120_SPACK"}}
{"symbol": "SPACK", "eodDate": "2006-01-20T00:00:00", "open": 2.2, "high": 2.22, "low": 2.2, "close": 2.22, "volume": 182000, "id": "20060120_SPACK" }
{"index": {"_index": "set_eod", "_type": "eod", "_id": "20060120_SPALI"}}
{"symbol": "SPALI", "eodDate": "2006-01-20T00:00:00", "open": 2.68, "high": 2.76, "low": 2.68, "close": 2.74, "volume": 18696868, "id": "20060120_SPALI" }
{"index": {"_index": "set_eod", "_type": "eod", "_id": "20060120_SPCG"}}
{"symbol": "SPCG", "eodDate": "2006-01-20T00:00:00", "open": 2.1, "high": 2.1, "low": 2.06, "close": 2.06, "volume": 106500, "id": "20060120_SPCG" }
{"index": {"_index": "set_eod", "_type": "eod", "_id": "20060120_SPG"}}
{"symbol": "SPG", "eodDate": "2006-01-20T00:00:00", "open": 37, "high": 37, "low": 36.25, "close": 36.25, "volume": 2000, "id": "20060120_SPG" }
{"index": {"_index": "set_eod", "_type": "eod", "_id": "20060120_SPI"}}
{"symbol": "SPI", "eodDate": "2006-01-20T00:00:00", "open": 16.5, "high": 17, "low": 16.5, "close": 16.5, "volume": 214607, "id": "20060120_SPI" }
{"index": {"_index": "set_eod", "_type": "eod", "_id": "20060120_SPORT"}}
{"symbol": "SPORT", "eodDate": "2006-01-20T00:00:00", "open": 2.52, "high": 2.52, "low": 2.5, "close": 2.5, "volume": 161400, "id": "20060120_SPORT" }
{"index": {"_index": "set_eod", "_type": "eod", "_id": "20060120_SPPT"}}
{"symbol": "SPPT", "eodDate": "2006-01-20T00:00:00", "open": 4.36, "high": 4.36, "low": 4.34, "close": 4.34, "volume": 87500, "id": "20060120_SPPT" }
{"index": {"_index": "set_eod", "_type": "eod", "_id": "20060120_SSC"}}
{"symbol": "SSC", "eodDate": "2006-01-20T00:00:00", "open": 20.5, "high": 20.5, "low": 20.4, "close": 20.5, "volume": 1795100, "id": "20060120_SSC" }
{"index": {"_index": "set_eod", "_type": "eod", "_id": "20060120_SSF"}}
{"symbol": "SSF", "eodDate": "2006-01-20T00:00:00", "open": 2.78, "high": 2.8, "low": 2.7, "close": 2.7, "volume": 221500, "id": "20060120_SSF" }
{"index": {"_index": "set_eod", "_type": "eod", "_id": "20060120_SSI"}}
{"symbol": "SSI", "eodDate": "2006-01-20T00:00:00", "open": 1.27, "high": 1.27, "low": 1.23, "close": 1.23, "volume": 56322900, "id": "20060120_SSI" }
{"index": {"_index": "set_eod", "_type": "eod", "_id": "20060120_SSSC"}}
{"symbol": "SSSC", "eodDate": "2006-01-20T00:00:00", "open": 30.8366, "high": 32.0034, "low": 30.8366, "close": 31.5034, "volume": 140695, "id": "20060120_SSSC" }
{"index": {"_index": "set_eod", "_type": "eod", "_id": "20060120_STA"}}
{"symbol": "STA", "eodDate": "2006-01-20T00:00:00", "open": 2.38, "high": 2.42, "low": 2.36, "close": 2.38, "volume": 2095140, "id": "20060120_STA" }
{"index": {"_index": "set_eod", "_type": "eod", "_id": "20060120_STANLY"}}
{"symbol": "STANLY", "eodDate": "2006-01-20T00:00:00", "open": 140, "high": 140, "low": 137, "close": 139, "volume": 70400, "id": "20060120_STANLY" }
{"index": {"_index": "set_eod", "_type": "eod", "_id": "20060120_STAR"}}
{"symbol": "STAR", "eodDate": "2006-01-20T00:00:00", "open": 1.87, "high": 1.87, "low": 1.85, "close": 1.85, "volume": 220100, "id": "20060120_STAR" }
{"index": {"_index": "set_eod", "_type": "eod", "_id": "20060120_STEC"}}
{"symbol": "STEC", "eodDate": "2006-01-20T00:00:00", "open": 12.4, "high": 12.5, "low": 11.9, "close": 12.2, "volume": 15271500, "id": "20060120_STEC" }
{"index": {"_index": "set_eod", "_type": "eod", "_id": "20060120_STHAI"}}
{"symbol": "STHAI", "eodDate": "2006-01-20T00:00:00", "open": 5.95, "high": 6, "low": 5.9, "close": 6, "volume": 71000, "id": "20060120_STHAI" }
{"index": {"_index": "set_eod", "_type": "eod", "_id": "20060120_STPI"}}
{"symbol": "STPI", "eodDate": "2006-01-20T00:00:00", "open": 2.44, "high": 2.56, "low": 2.42, "close": 2.48, "volume": 11621500, "id": "20060120_STPI" }
{"index": {"_index": "set_eod", "_type": "eod", "_id": "20060120_SUC"}}
{"symbol": "SUC", "eodDate": "2006-01-20T00:00:00", "open": 17.2, "high": 17.2, "low": 17, "close": 17.1, "volume": 127000, "id": "20060120_SUC" }
{"index": {"_index": "set_eod", "_type": "eod", "_id": "20060120_SUPER"}}
{"symbol": "SUPER", "eodDate": "2006-01-20T00:00:00", "open": 1.89, "high": 1.94, "low": 1.86, "close": 1.86, "volume": 1933500, "id": "20060120_SUPER" }
{"index": {"_index": "set_eod", "_type": "eod", "_id": "20060120_SUSCO"}}
{"symbol": "SUSCO", "eodDate": "2006-01-20T00:00:00", "open": 0.73, "high": 0.74, "low": 0.7, "close": 0.71, "volume": 13612140, "id": "20060120_SUSCO" }
{"index": {"_index": "set_eod", "_type": "eod", "_id": "20060120_SVI"}}
{"symbol": "SVI", "eodDate": "2006-01-20T00:00:00", "open": 0.945, "high": 0.95, "low": 0.945, "close": 0.945, "volume": 500000, "id": "20060120_SVI" }
{"index": {"_index": "set_eod", "_type": "eod", "_id": "20060120_SVOA"}}
{"symbol": "SVOA", "eodDate": "2006-01-20T00:00:00", "open": 1.04, "high": 1.04, "low": 1.02, "close": 1.02, "volume": 1136430, "id": "20060120_SVOA" }
{"index": {"_index": "set_eod", "_type": "eod", "_id": "20060120_SWC"}}
{"symbol": "SWC", "eodDate": "2006-01-20T00:00:00", "open": 3.4, "high": 3.5, "low": 3.4, "close": 3.4, "volume": 16100, "id": "20060120_SWC" }
{"index": {"_index": "set_eod", "_type": "eod", "_id": "20060120_SYNTEC"}}
{"symbol": "SYNTEC", "eodDate": "2006-01-20T00:00:00", "open": 0.87, "high": 0.9, "low": 0.78, "close": 0.79, "volume": 131403504, "id": "20060120_SYNTEC" }
{"index": {"_index": "set_eod", "_type": "eod", "_id": "20060120_TAPAC"}}
{"symbol": "TAPAC", "eodDate": "2006-01-20T00:00:00", "open": 2.18, "high": 2.18, "low": 2.18, "close": 2.18, "volume": 1000, "id": "20060120_TAPAC" }
{"index": {"_index": "set_eod", "_type": "eod", "_id": "20060120_TASCO"}}
{"symbol": "TASCO", "eodDate": "2006-01-20T00:00:00", "open": 19, "high": 19.2, "low": 19, "close": 19.2, "volume": 381700, "id": "20060120_TASCO" }
{"index": {"_index": "set_eod", "_type": "eod", "_id": "20060120_TC"}}
{"symbol": "TC", "eodDate": "2006-01-20T00:00:00", "open": 15.9, "high": 16.3, "low": 15.9, "close": 16.3, "volume": 500, "id": "20060120_TC" }
{"index": {"_index": "set_eod", "_type": "eod", "_id": "20060120_TCAP"}}
{"symbol": "TCAP", "eodDate": "2006-01-20T00:00:00", "open": 14.4, "high": 14.4, "low": 14.1, "close": 14.1, "volume": 2036351, "id": "20060120_TCAP" }
{"index": {"_index": "set_eod", "_type": "eod", "_id": "20060120_TCB"}}
{"symbol": "TCB", "eodDate": "2006-01-20T00:00:00", "open": 22, "high": 22, "low": 21.8, "close": 21.9, "volume": 23500, "id": "20060120_TCB" }
{"index": {"_index": "set_eod", "_type": "eod", "_id": "20060120_TCC"}}
{"symbol": "TCC", "eodDate": "2006-01-20T00:00:00", "open": 0.96, "high": 0.96, "low": 0.9, "close": 0.9, "volume": 3512800, "id": "20060120_TCC" }
{"index": {"_index": "set_eod", "_type": "eod", "_id": "20060120_TCCC"}}
{"symbol": "TCCC", "eodDate": "2006-01-20T00:00:00", "open": 5.85, "high": 5.85, "low": 5.7, "close": 5.7, "volume": 5800, "id": "20060120_TCCC" }
{"index": {"_index": "set_eod", "_type": "eod", "_id": "20060120_TCJ"}}
{"symbol": "TCJ", "eodDate": "2006-01-20T00:00:00", "open": 9.65, "high": 9.65, "low": 9.4, "close": 9.4, "volume": 490800, "id": "20060120_TCJ" }
{"index": {"_index": "set_eod", "_type": "eod", "_id": "20060120_TCMC"}}
{"symbol": "TCMC", "eodDate": "2006-01-20T00:00:00", "open": 4.8201, "high": 4.8201, "low": 4.8201, "close": 4.8201, "volume": 2406, "id": "20060120_TCMC" }
{"index": {"_index": "set_eod", "_type": "eod", "_id": "20060120_TEAM"}}
{"symbol": "TEAM", "eodDate": "2006-01-20T00:00:00", "open": 1.3918, "high": 1.4557, "low": 1.3918, "close": 1.4557, "volume": 2578127, "id": "20060120_TEAM" }
{"index": {"_index": "set_eod", "_type": "eod", "_id": "20060120_TFD"}}
{"symbol": "TFD", "eodDate": "2006-01-20T00:00:00", "open": 0.85, "high": 0.85, "low": 0.84, "close": 0.84, "volume": 2671400, "id": "20060120_TFD" }
{"index": {"_index": "set_eod", "_type": "eod", "_id": "20060120_TFI"}}
{"symbol": "TFI", "eodDate": "2006-01-20T00:00:00", "open": 0.3001, "high": 0.3001, "low": 0.2819, "close": 0.291, "volume": 8582478, "id": "20060120_TFI" }
{"index": {"_index": "set_eod", "_type": "eod", "_id": "20060120_TFUND"}}
{"symbol": "TFUND", "eodDate": "2006-01-20T00:00:00", "open": 10, "high": 10, "low": 10, "close": 10, "volume": 220000, "id": "20060120_TFUND" }
{"index": {"_index": "set_eod", "_type": "eod", "_id": "20060120_TGCI"}}
{"symbol": "TGCI", "eodDate": "2006-01-20T00:00:00", "open": 1.99, "high": 2, "low": 1.95, "close": 1.96, "volume": 394000, "id": "20060120_TGCI" }
{"index": {"_index": "set_eod", "_type": "eod", "_id": "20060120_THAI"}}
{"symbol": "THAI", "eodDate": "2006-01-20T00:00:00", "open": 41.75, "high": 43.5, "low": 41.75, "close": 42.75, "volume": 4829464, "id": "20060120_THAI" }
{"index": {"_index": "set_eod", "_type": "eod", "_id": "20060120_THANI"}}
{"symbol": "THANI", "eodDate": "2006-01-20T00:00:00", "open": 1.36, "high": 1.43, "low": 1.36, "close": 1.41, "volume": 269769, "id": "20060120_THANI" }
{"index": {"_index": "set_eod", "_type": "eod", "_id": "20060120_THCOM"}}
{"symbol": "THCOM", "eodDate": "2006-01-20T00:00:00", "open": 15.4, "high": 15.7, "low": 15.2, "close": 15.7, "volume": 32941800, "id": "20060120_THCOM" }
{"index": {"_index": "set_eod", "_type": "eod", "_id": "20060120_THIP"}}
{"symbol": "THIP", "eodDate": "2006-01-20T00:00:00", "open": 24.3, "high": 24.6, "low": 24.2, "close": 24.6, "volume": 3500, "id": "20060120_THIP" }
{"index": {"_index": "set_eod", "_type": "eod", "_id": "20060120_THRE"}}
{"symbol": "THRE", "eodDate": "2006-01-20T00:00:00", "open": 5.2, "high": 5.25, "low": 5.2, "close": 5.25, "volume": 588400, "id": "20060120_THRE" }
{"index": {"_index": "set_eod", "_type": "eod", "_id": "20060120_TICON"}}
{"symbol": "TICON", "eodDate": "2006-01-20T00:00:00", "open": 13.8, "high": 14.2, "low": 13.7, "close": 14.2, "volume": 1308300, "id": "20060120_TICON" }
{"index": {"_index": "set_eod", "_type": "eod", "_id": "20060120_TIP"}}
{"symbol": "TIP", "eodDate": "2006-01-20T00:00:00", "open": 13.7, "high": 13.8, "low": 13.6, "close": 13.6, "volume": 188700, "id": "20060120_TIP" }
{"index": {"_index": "set_eod", "_type": "eod", "_id": "20060120_TIPCO"}}
{"symbol": "TIPCO", "eodDate": "2006-01-20T00:00:00", "open": 4.3, "high": 4.34, "low": 4.28, "close": 4.3, "volume": 28600, "id": "20060120_TIPCO" }
{"index": {"_index": "set_eod", "_type": "eod", "_id": "20060120_TISCO"}}
{"symbol": "TISCO", "eodDate": "2006-01-20T00:00:00", "open": 27.75, "high": 28.25, "low": 27.75, "close": 28, "volume": 2923000, "id": "20060120_TISCO" }
{"index": {"_index": "set_eod", "_type": "eod", "_id": "20060120_TIW"}}
{"symbol": "TIW", "eodDate": "2006-01-20T00:00:00", "open": 70, "high": 70, "low": 70, "close": 70, "volume": 400, "id": "20060120_TIW" }
{"index": {"_index": "set_eod", "_type": "eod", "_id": "20060120_TK"}}
{"symbol": "TK", "eodDate": "2006-01-20T00:00:00", "open": 4.7, "high": 4.74, "low": 4.68, "close": 4.72, "volume": 115500, "id": "20060120_TK" }
{"index": {"_index": "set_eod", "_type": "eod", "_id": "20060120_TKS"}}
{"symbol": "TKS", "eodDate": "2006-01-20T00:00:00", "open": 2.64, "high": 2.66, "low": 2.6, "close": 2.62, "volume": 450090, "id": "20060120_TKS" }
{"index": {"_index": "set_eod", "_type": "eod", "_id": "20060120_TKT"}}
{"symbol": "TKT", "eodDate": "2006-01-20T00:00:00", "open": 1.91, "high": 1.91, "low": 1.8, "close": 1.86, "volume": 50400, "id": "20060120_TKT" }
{"index": {"_index": "set_eod", "_type": "eod", "_id": "20060120_TLUXE"}}
{"symbol": "TLUXE", "eodDate": "2006-01-20T00:00:00", "open": 2.08, "high": 2.08, "low": 2.04, "close": 2.08, "volume": 2252100, "id": "20060120_TLUXE" }
{"index": {"_index": "set_eod", "_type": "eod", "_id": "20060120_TMB"}}
{"symbol": "TMB", "eodDate": "2006-01-20T00:00:00", "open": 4.5482, "high": 4.5482, "low": 4.4341, "close": 4.4341, "volume": 105444112, "id": "20060120_TMB" }
{"index": {"_index": "set_eod", "_type": "eod", "_id": "20060120_TMD"}}
{"symbol": "TMD", "eodDate": "2006-01-20T00:00:00", "open": 50.5, "high": 50.5, "low": 50, "close": 50.5, "volume": 8500, "id": "20060120_TMD" }
{"index": {"_index": "set_eod", "_type": "eod", "_id": "20060120_TMT"}}
{"symbol": "TMT", "eodDate": "2006-01-20T00:00:00", "open": 3.32, "high": 3.32, "low": 3.26, "close": 3.28, "volume": 858000, "id": "20060120_TMT" }
{"index": {"_index": "set_eod", "_type": "eod", "_id": "20060120_TMW"}}
{"symbol": "TMW", "eodDate": "2006-01-20T00:00:00", "open": 20, "high": 20.9, "low": 19.8, "close": 20.8, "volume": 66600, "id": "20060120_TMW" }
{"index": {"_index": "set_eod", "_type": "eod", "_id": "20060120_TNH"}}
{"symbol": "TNH", "eodDate": "2006-01-20T00:00:00", "open": 1.84, "high": 1.85, "low": 1.84, "close": 1.84, "volume": 213000, "id": "20060120_TNH" }
{"index": {"_index": "set_eod", "_type": "eod", "_id": "20060120_TNITY"}}
{"symbol": "TNITY", "eodDate": "2006-01-20T00:00:00", "open": 11, "high": 11.1, "low": 10.6, "close": 10.7, "volume": 930200, "id": "20060120_TNITY" }
{"index": {"_index": "set_eod", "_type": "eod", "_id": "20060120_TOP"}}
{"symbol": "TOP", "eodDate": "2006-01-20T00:00:00", "open": 68, "high": 68, "low": 67, "close": 67, "volume": 3906502, "id": "20060120_TOP" }
{"index": {"_index": "set_eod", "_type": "eod", "_id": "20060120_TPA"}}
{"symbol": "TPA", "eodDate": "2006-01-20T00:00:00", "open": 50, "high": 50, "low": 50, "close": 50, "volume": 500, "id": "20060120_TPA" }
{"index": {"_index": "set_eod", "_type": "eod", "_id": "20060120_TPAC"}}
{"symbol": "TPAC", "eodDate": "2006-01-20T00:00:00", "open": 2.6, "high": 2.6, "low": 2.6, "close": 2.6, "volume": 6000, "id": "20060120_TPAC" }
{"index": {"_index": "set_eod", "_type": "eod", "_id": "20060120_TPC"}}
{"symbol": "TPC", "eodDate": "2006-01-20T00:00:00", "open": 15.8, "high": 15.9, "low": 15.7, "close": 15.9, "volume": 359500, "id": "20060120_TPC" }
{"index": {"_index": "set_eod", "_type": "eod", "_id": "20060120_TPCORP"}}
{"symbol": "TPCORP", "eodDate": "2006-01-20T00:00:00", "open": 20.5, "high": 22, "low": 20.5, "close": 22, "volume": 2000, "id": "20060120_TPCORP" }
{"index": {"_index": "set_eod", "_type": "eod", "_id": "20060120_TPIPL"}}
{"symbol": "TPIPL", "eodDate": "2006-01-20T00:00:00", "open": 24, "high": 24.1, "low": 23.8, "close": 23.8, "volume": 1609849, "id": "20060120_TPIPL" }
{"index": {"_index": "set_eod", "_type": "eod", "_id": "20060120_TPP"}}
{"symbol": "TPP", "eodDate": "2006-01-20T00:00:00", "open": 8.25, "high": 8.25, "low": 8.25, "close": 8.25, "volume": 2000, "id": "20060120_TPP" }
{"index": {"_index": "set_eod", "_type": "eod", "_id": "20060120_TRC"}}
{"symbol": "TRC", "eodDate": "2006-01-20T00:00:00", "open": 1.1273, "high": 1.1273, "low": 1.1273, "close": 1.1273, "volume": 10100, "id": "20060120_TRC" }
{"index": {"_index": "set_eod", "_type": "eod", "_id": "20060120_TRITN"}}
{"symbol": "TRITN", "eodDate": "2006-01-20T00:00:00", "open": 0.0501, "high": 0.054, "low": 0.0468, "close": 0.0481, "volume": 1299319552, "id": "20060120_TRITN" }
{"index": {"_index": "set_eod", "_type": "eod", "_id": "20060120_TRU"}}
{"symbol": "TRU", "eodDate": "2006-01-20T00:00:00", "open": 5.8, "high": 6, "low": 5.8, "close": 5.95, "volume": 149601, "id": "20060120_TRU" }
{"index": {"_index": "set_eod", "_type": "eod", "_id": "20060120_TRUBB"}}
{"symbol": "TRUBB", "eodDate": "2006-01-20T00:00:00", "open": 0.475, "high": 0.4781, "low": 0.475, "close": 0.4781, "volume": 49600, "id": "20060120_TRUBB" }
{"index": {"_index": "set_eod", "_type": "eod", "_id": "20060120_TRUE"}}
{"symbol": "TRUE", "eodDate": "2006-01-20T00:00:00", "open": 11, "high": 11.2, "low": 10.6, "close": 10.7, "volume": 16802892, "id": "20060120_TRUE" }
{"index": {"_index": "set_eod", "_type": "eod", "_id": "20060120_TSC"}}
{"symbol": "TSC", "eodDate": "2006-01-20T00:00:00", "open": 9.1, "high": 9.15, "low": 9.05, "close": 9.05, "volume": 465300, "id": "20060120_TSC" }
{"index": {"_index": "set_eod", "_type": "eod", "_id": "20060120_TSF"}}
{"symbol": "TSF", "eodDate": "2006-01-20T00:00:00", "open": 0.595, "high": 0.615, "low": 0.575, "close": 0.58, "volume": 99900, "id": "20060120_TSF" }
{"index": {"_index": "set_eod", "_type": "eod", "_id": "20060120_TSTE"}}
{"symbol": "TSTE", "eodDate": "2006-01-20T00:00:00", "open": 4.08, "high": 4.08, "low": 4.08, "close": 4.08, "volume": 3000, "id": "20060120_TSTE" }
{"index": {"_index": "set_eod", "_type": "eod", "_id": "20060120_TSTH"}}
{"symbol": "TSTH", "eodDate": "2006-01-20T00:00:00", "open": 1.1, "high": 1.11, "low": 1.09, "close": 1.1, "volume": 24203200, "id": "20060120_TSTH" }
{"index": {"_index": "set_eod", "_type": "eod", "_id": "20060120_TTA"}}
{"symbol": "TTA", "eodDate": "2006-01-20T00:00:00", "open": 23.6419, "high": 23.6419, "low": 23.1872, "close": 23.4145, "volume": 4126681, "id": "20060120_TTA" }
{"index": {"_index": "set_eod", "_type": "eod", "_id": "20060120_TTL"}}
{"symbol": "TTL", "eodDate": "2006-01-20T00:00:00", "open": 31.5, "high": 32.25, "low": 31.5, "close": 32.25, "volume": 22902, "id": "20060120_TTL" }
{"index": {"_index": "set_eod", "_type": "eod", "_id": "20060120_TTTM"}}
{"symbol": "TTTM", "eodDate": "2006-01-20T00:00:00", "open": 74.5, "high": 74.5, "low": 74.5, "close": 74.5, "volume": 200, "id": "20060120_TTTM" }
{"index": {"_index": "set_eod", "_type": "eod", "_id": "20060120_TU"}}
{"symbol": "TU", "eodDate": "2006-01-20T00:00:00", "open": 29.75, "high": 30, "low": 29.25, "close": 29.5, "volume": 323000, "id": "20060120_TU" }
{"index": {"_index": "set_eod", "_type": "eod", "_id": "20060120_TUCC"}}
{"symbol": "TUCC", "eodDate": "2006-01-20T00:00:00", "open": 3.2184, "high": 3.233, "low": 3.0582, "close": 3.0728, "volume": 1865200, "id": "20060120_TUCC" }
{"index": {"_index": "set_eod", "_type": "eod", "_id": "20060120_TVO"}}
{"symbol": "TVO", "eodDate": "2006-01-20T00:00:00", "open": 8.8, "high": 8.8, "low": 8.72, "close": 8.8, "volume": 404883, "id": "20060120_TVO" }
{"index": {"_index": "set_eod", "_type": "eod", "_id": "20060120_TWZ"}}
{"symbol": "TWZ", "eodDate": "2006-01-20T00:00:00", "open": 0.47, "high": 0.47, "low": 0.446, "close": 0.454, "volume": 16185500, "id": "20060120_TWZ" }
{"index": {"_index": "set_eod", "_type": "eod", "_id": "20060120_TYCN"}}
{"symbol": "TYCN", "eodDate": "2006-01-20T00:00:00", "open": 8.1, "high": 8.45, "low": 8.1, "close": 8.45, "volume": 426200, "id": "20060120_TYCN" }
{"index": {"_index": "set_eod", "_type": "eod", "_id": "20060120_U"}}
{"symbol": "U", "eodDate": "2006-01-20T00:00:00", "open": 0.4643, "high": 0.4714, "low": 0.4429, "close": 0.4429, "volume": 64592392, "id": "20060120_U" }
{"index": {"_index": "set_eod", "_type": "eod", "_id": "20060120_UEC"}}
{"symbol": "UEC", "eodDate": "2006-01-20T00:00:00", "open": 1.625, "high": 1.6375, "low": 1.6125, "close": 1.6125, "volume": 753300, "id": "20060120_UEC" }
{"index": {"_index": "set_eod", "_type": "eod", "_id": "20060120_UMI"}}
{"symbol": "UMI", "eodDate": "2006-01-20T00:00:00", "open": 1.89, "high": 2.02, "low": 1.85, "close": 1.9, "volume": 5931800, "id": "20060120_UMI" }
{"index": {"_index": "set_eod", "_type": "eod", "_id": "20060120_UMS"}}
{"symbol": "UMS", "eodDate": "2006-01-20T00:00:00", "open": 7.75, "high": 7.8, "low": 7.55, "close": 7.65, "volume": 206400, "id": "20060120_UMS" }
{"index": {"_index": "set_eod", "_type": "eod", "_id": "20060120_UOBKH"}}
{"symbol": "UOBKH", "eodDate": "2006-01-20T00:00:00", "open": 7.85, "high": 7.85, "low": 7.3, "close": 7.35, "volume": 14937301, "id": "20060120_UOBKH" }
{"index": {"_index": "set_eod", "_type": "eod", "_id": "20060120_UP"}}
{"symbol": "UP", "eodDate": "2006-01-20T00:00:00", "open": 14.5, "high": 14.5, "low": 14.5, "close": 14.5, "volume": 100, "id": "20060120_UP" }
{"index": {"_index": "set_eod", "_type": "eod", "_id": "20060120_UTP"}}
{"symbol": "UTP", "eodDate": "2006-01-20T00:00:00", "open": 5, "high": 5, "low": 4.78, "close": 4.8, "volume": 326000, "id": "20060120_UTP" }
{"index": {"_index": "set_eod", "_type": "eod", "_id": "20060120_UV"}}
{"symbol": "UV", "eodDate": "2006-01-20T00:00:00", "open": 1.75, "high": 1.81, "low": 1.74, "close": 1.77, "volume": 2681900, "id": "20060120_UV" }
{"index": {"_index": "set_eod", "_type": "eod", "_id": "20060120_UVAN"}}
{"symbol": "UVAN", "eodDate": "2006-01-20T00:00:00", "open": 29.25, "high": 29.25, "low": 29, "close": 29, "volume": 73000, "id": "20060120_UVAN" }
{"index": {"_index": "set_eod", "_type": "eod", "_id": "20060120_VARO"}}
{"symbol": "VARO", "eodDate": "2006-01-20T00:00:00", "open": 7.7235, "high": 7.7235, "low": 7.7235, "close": 7.7235, "volume": 11009, "id": "20060120_VARO" }
{"index": {"_index": "set_eod", "_type": "eod", "_id": "20060120_VIBHA"}}
{"symbol": "VIBHA", "eodDate": "2006-01-20T00:00:00", "open": 2.3, "high": 2.3, "low": 2.28, "close": 2.3, "volume": 71600, "id": "20060120_VIBHA" }
{"index": {"_index": "set_eod", "_type": "eod", "_id": "20060120_VNG"}}
{"symbol": "VNG", "eodDate": "2006-01-20T00:00:00", "open": 5.5, "high": 5.85, "low": 5.5, "close": 5.75, "volume": 12106800, "id": "20060120_VNG" }
{"index": {"_index": "set_eod", "_type": "eod", "_id": "20060120_VNT"}}
{"symbol": "VNT", "eodDate": "2006-01-20T00:00:00", "open": 9.85, "high": 9.9, "low": 9.75, "close": 9.8, "volume": 1052119, "id": "20060120_VNT" }
{"index": {"_index": "set_eod", "_type": "eod", "_id": "20060120_WACOAL"}}
{"symbol": "WACOAL", "eodDate": "2006-01-20T00:00:00", "open": 33.75, "high": 33.75, "low": 33.75, "close": 33.75, "volume": 200, "id": "20060120_WACOAL" }
{"index": {"_index": "set_eod", "_type": "eod", "_id": "20060120_WAVE"}}
{"symbol": "WAVE", "eodDate": "2006-01-20T00:00:00", "open": 22.7, "high": 24.1, "low": 22.7, "close": 23.8, "volume": 867520, "id": "20060120_WAVE" }
{"index": {"_index": "set_eod", "_type": "eod", "_id": "20060120_WG"}}
{"symbol": "WG", "eodDate": "2006-01-20T00:00:00", "open": 36, "high": 36, "low": 36, "close": 36, "volume": 5500, "id": "20060120_WG" }
{"index": {"_index": "set_eod", "_type": "eod", "_id": "20060120_WIIK"}}
{"symbol": "WIIK", "eodDate": "2006-01-20T00:00:00", "open": 1.65, "high": 1.7, "low": 1.63, "close": 1.65, "volume": 1416800, "id": "20060120_WIIK" }
{"index": {"_index": "set_eod", "_type": "eod", "_id": "20060120_WIN"}}
{"symbol": "WIN", "eodDate": "2006-01-20T00:00:00", "open": 2.6132, "high": 2.6132, "low": 2.5466, "close": 2.5633, "volume": 1177827, "id": "20060120_WIN" }
{"index": {"_index": "set_eod", "_type": "eod", "_id": "20060120_WORK"}}
{"symbol": "WORK", "eodDate": "2006-01-20T00:00:00", "open": 18.8, "high": 19.4, "low": 18.8, "close": 19.4, "volume": 1413400, "id": "20060120_WORK" }
{"index": {"_index": "set_eod", "_type": "eod", "_id": "20060120_YCI"}}
{"symbol": "YCI", "eodDate": "2006-01-20T00:00:00", "open": 8.7, "high": 8.7, "low": 8.5, "close": 8.5, "volume": 4700, "id": "20060120_YCI" }
{"index": {"_index": "set_eod", "_type": "eod", "_id": "20060120_YNP"}}
{"symbol": "YNP", "eodDate": "2006-01-20T00:00:00", "open": 2.54, "high": 2.56, "low": 2.48, "close": 2.48, "volume": 855100, "id": "20060120_YNP" }
{"index": {"_index": "set_eod", "_type": "eod", "_id": "20060120_YUASA"}}
{"symbol": "YUASA", "eodDate": "2006-01-20T00:00:00", "open": 3.2, "high": 3.2, "low": 2.98, "close": 3.14, "volume": 62100, "id": "20060120_YUASA" }
{"index": {"_index": "set_eod", "_type": "eod", "_id": "20060120_ZMICO"}}
{"symbol": "ZMICO", "eodDate": "2006-01-20T00:00:00", "open": 5.1, "high": 5.15, "low": 4.96, "close": 4.96, "volume": 7784369, "id": "20060120_ZMICO" }
{"index": {"_index": "set_eod", "_type": "eod", "_id": "20060120_BH-P"}}
{"symbol": "BH-P", "eodDate": "2006-01-20T00:00:00", "open": 30, "high": 30, "low": 29.75, "close": 29.75, "volume": 4000, "id": "20060120_BH-P" }
{"index": {"_index": "set_eod", "_type": "eod", "_id": "20060120_SCB-P"}}
{"symbol": "SCB-P", "eodDate": "2006-01-20T00:00:00", "open": 55.5, "high": 56.5, "low": 55.5, "close": 56.5, "volume": 6976, "id": "20060120_SCB-P" }
{"index": {"_index": "set_eod", "_type": "eod", "_id": "20060120_$AGRI"}}
{"symbol": "$AGRI", "eodDate": "2006-01-20T00:00:00", "open": 63.19, "high": 63.19, "low": 62.15, "close": 62.62, "volume": 1534500, "id": "20060120_$AGRI" }
{"index": {"_index": "set_eod", "_type": "eod", "_id": "20060120_$AUTO"}}
{"symbol": "$AUTO", "eodDate": "2006-01-20T00:00:00", "open": 351.04, "high": 351.82, "low": 348.44, "close": 350.02, "volume": 464100, "id": "20060120_$AUTO" }
{"index": {"_index": "set_eod", "_type": "eod", "_id": "20060120_$BANK"}}
{"symbol": "$BANK", "eodDate": "2006-01-20T00:00:00", "open": 280.98, "high": 281.19, "low": 275.96, "close": 276.81, "volume": 19694100, "id": "20060120_$BANK" }
{"index": {"_index": "set_eod", "_type": "eod", "_id": "20060120_$COMM"}}
{"symbol": "$COMM", "eodDate": "2006-01-20T00:00:00", "open": 3433.76, "high": 3436.33, "low": 3407.27, "close": 3421.93, "volume": 16523600, "id": "20060120_$COMM" }
{"index": {"_index": "set_eod", "_type": "eod", "_id": "20060120_$CONMAT"}}
{"symbol": "$CONMAT", "eodDate": "2006-01-20T00:00:00", "open": 6710.64, "high": 6810.94, "low": 6710.58, "close": 6806.74, "volume": 82459696, "id": "20060120_$CONMAT" }
{"index": {"_index": "set_eod", "_type": "eod", "_id": "20060120_$ENERG"}}
{"symbol": "$ENERG", "eodDate": "2006-01-20T00:00:00", "open": 15254.4, "high": 15358.3, "low": 15175.9, "close": 15248.5, "volume": 33376400, "id": "20060120_$ENERG" }
{"index": {"_index": "set_eod", "_type": "eod", "_id": "20060120_$ETRON"}}
{"symbol": "$ETRON", "eodDate": "2006-01-20T00:00:00", "open": 739.09, "high": 744.87, "low": 734.32, "close": 734.32, "volume": 3071700, "id": "20060120_$ETRON" }
{"index": {"_index": "set_eod", "_type": "eod", "_id": "20060120_$FASHION"}}
{"symbol": "$FASHION", "eodDate": "2006-01-20T00:00:00", "open": 542.91, "high": 543.55, "low": 539.25, "close": 540.98, "volume": 20700, "id": "20060120_$FASHION" }
{"index": {"_index": "set_eod", "_type": "eod", "_id": "20060120_$FIN"}}
{"symbol": "$FIN", "eodDate": "2006-01-20T00:00:00", "open": 1190.16, "high": 1193.03, "low": 1169.21, "close": 1169.21, "volume": 44934500, "id": "20060120_$FIN" }
{"index": {"_index": "set_eod", "_type": "eod", "_id": "20060120_$FOOD"}}
{"symbol": "$FOOD", "eodDate": "2006-01-20T00:00:00", "open": 3551.91, "high": 3569.52, "low": 3543.24, "close": 3562.21, "volume": 3339200, "id": "20060120_$FOOD" }
{"index": {"_index": "set_eod", "_type": "eod", "_id": "20060120_$HELTH"}}
{"symbol": "$HELTH", "eodDate": "2006-01-20T00:00:00", "open": 650.66, "high": 650.66, "low": 626.39, "close": 626.39, "volume": 340700, "id": "20060120_$HELTH" }
{"index": {"_index": "set_eod", "_type": "eod", "_id": "20060120_$INSUR"}}
{"symbol": "$INSUR", "eodDate": "2006-01-20T00:00:00", "open": 3555.45, "high": 3586.12, "low": 3555.45, "close": 3586.12, "volume": 95800, "id": "20060120_$INSUR" }
{"index": {"_index": "set_eod", "_type": "eod", "_id": "20060120_$MEDIA"}}
{"symbol": "$MEDIA", "eodDate": "2006-01-20T00:00:00", "open": 41.36, "high": 42.11, "low": 41.36, "close": 41.84, "volume": 94937696, "id": "20060120_$MEDIA" }
{"index": {"_index": "set_eod", "_type": "eod", "_id": "20060120_$MINE"}}
{"symbol": "$MINE", "eodDate": "2006-01-20T00:00:00", "open": 19.15, "high": 19.25, "low": 18.95, "close": 19.05, "volume": 46200, "id": "20060120_$MINE" }
{"index": {"_index": "set_eod", "_type": "eod", "_id": "20060120_$PAPER"}}
{"symbol": "$PAPER", "eodDate": "2006-01-20T00:00:00", "open": 388.59, "high": 388.85, "low": 384.98, "close": 388.34, "volume": 37600, "id": "20060120_$PAPER" }
{"index": {"_index": "set_eod", "_type": "eod", "_id": "20060120_$PERSON"}}
{"symbol": "$PERSON", "eodDate": "2006-01-20T00:00:00", "open": 307.17, "high": 307.4, "low": 304.78, "close": 307.4, "volume": 13000, "id": "20060120_$PERSON" }
{"index": {"_index": "set_eod", "_type": "eod", "_id": "20060120_$PETRO"}}
{"symbol": "$PETRO", "eodDate": "2006-01-20T00:00:00", "open": 457.47, "high": 464.52, "low": 455.3, "close": 462.08, "volume": 1796400, "id": "20060120_$PETRO" }
{"index": {"_index": "set_eod", "_type": "eod", "_id": "20060120_$PKG"}}
{"symbol": "$PKG", "eodDate": "2006-01-20T00:00:00", "open": 1528.07, "high": 1540.84, "low": 1512.85, "close": 1517.14, "volume": 945000, "id": "20060120_$PKG" }
{"index": {"_index": "set_eod", "_type": "eod", "_id": "20060120_$PROF"}}
{"symbol": "$PROF", "eodDate": "2006-01-20T00:00:00", "open": 258.67, "high": 262.12, "low": 254.07, "close": 254.07, "volume": 1808600, "id": "20060120_$PROF" }
{"index": {"_index": "set_eod", "_type": "eod", "_id": "20060120_$PROP"}}
{"symbol": "$PROP", "eodDate": "2006-01-20T00:00:00", "open": 122.43, "high": 124.17, "low": 122.4, "close": 123.41, "volume": 82956304, "id": "20060120_$PROP" }
{"index": {"_index": "set_eod", "_type": "eod", "_id": "20060120_$TRANS"}}
{"symbol": "$TRANS", "eodDate": "2006-01-20T00:00:00", "open": 125.28, "high": 126.94, "low": 124.97, "close": 125.83, "volume": 1851700, "id": "20060120_$TRANS" }
{"index": {"_index": "set_eod", "_type": "eod", "_id": "20060120_MAI"}}
{"symbol": "MAI", "eodDate": "2006-01-20T00:00:00", "open": 159.99, "high": 160.62, "low": 159.36, "close": 159.36, "volume": 8320100, "id": "20060120_MAI" }
{"index": {"_index": "set_eod", "_type": "eod", "_id": "20060120_SET"}}
{"symbol": "SET", "eodDate": "2006-01-20T00:00:00", "open": 749.77, "high": 752.61, "low": 747, "close": 747.7, "volume": 5444127744, "id": "20060120_SET" }
{"index": {"_index": "set_eod", "_type": "eod", "_id": "20060120_SET100"}}
{"symbol": "SET100", "eodDate": "2006-01-20T00:00:00", "open": 1150.61, "high": 1155.53, "low": 1145.86, "close": 1147.36, "volume": 2414951424, "id": "20060120_SET100" }
{"index": {"_index": "set_eod", "_type": "eod", "_id": "20060120_SET50"}}
{"symbol": "SET50", "eodDate": "2006-01-20T00:00:00", "open": 528.01, "high": 530.33, "low": 525.64, "close": 526.39, "volume": 612826496, "id": "20060120_SET50" }
{"index": {"_index": "set_eod", "_type": "eod", "_id": "20060120_AMATA-F"}}
{"symbol": "AMATA-F", "eodDate": "2006-01-20T00:00:00", "open": 16.1, "high": 16.9, "low": 16.1, "close": 16.9, "volume": 87000, "id": "20060120_AMATA-F" }
{"index": {"_index": "set_eod", "_type": "eod", "_id": "20060120_BAY-F"}}
{"symbol": "BAY-F", "eodDate": "2006-01-20T00:00:00", "open": 16.2, "high": 17.1, "low": 16.2, "close": 17.1, "volume": 1391200, "id": "20060120_BAY-F" }
{"index": {"_index": "set_eod", "_type": "eod", "_id": "20060120_BBL-F"}}
{"symbol": "BBL-F", "eodDate": "2006-01-20T00:00:00", "open": 124, "high": 124, "low": 122, "close": 123, "volume": 3296100, "id": "20060120_BBL-F" }
{"index": {"_index": "set_eod", "_type": "eod", "_id": "20060120_EGCO-F"}}
{"symbol": "EGCO-F", "eodDate": "2006-01-20T00:00:00", "open": 88, "high": 88, "low": 87.5, "close": 88, "volume": 98000, "id": "20060120_EGCO-F" }
{"index": {"_index": "set_eod", "_type": "eod", "_id": "20060120_ITD-F"}}
{"symbol": "ITD-F", "eodDate": "2006-01-20T00:00:00", "open": 8.95, "high": 8.95, "low": 8.95, "close": 8.95, "volume": 200000, "id": "20060120_ITD-F" }
{"index": {"_index": "set_eod", "_type": "eod", "_id": "20060120_KBANK-F"}}
{"symbol": "KBANK-F", "eodDate": "2006-01-20T00:00:00", "open": 73.5, "high": 73.5, "low": 71.5, "close": 72, "volume": 7916500, "id": "20060120_KBANK-F" }
{"index": {"_index": "set_eod", "_type": "eod", "_id": "20060120_LH-F"}}
{"symbol": "LH-F", "eodDate": "2006-01-20T00:00:00", "open": 9.8, "high": 10.3, "low": 9.8, "close": 10.2, "volume": 6453200, "id": "20060120_LH-F" }
{"index": {"_index": "set_eod", "_type": "eod", "_id": "20060120_MINT-F"}}
{"symbol": "MINT-F", "eodDate": "2006-01-20T00:00:00", "open": 5.9091, "high": 5.9091, "low": 5.9091, "close": 5.9091, "volume": 4300, "id": "20060120_MINT-F" }
{"index": {"_index": "set_eod", "_type": "eod", "_id": "20060120_SCC-F"}}
{"symbol": "SCC-F", "eodDate": "2006-01-20T00:00:00", "open": 272, "high": 276, "low": 272, "close": 276, "volume": 1370100, "id": "20060120_SCC-F" }
{"index": {"_index": "set_eod", "_type": "eod", "_id": "20060120_SPI-F"}}
{"symbol": "SPI-F", "eodDate": "2006-01-20T00:00:00", "open": 16, "high": 16, "low": 16, "close": 16, "volume": 200000, "id": "20060120_SPI-F" }
{"index": {"_index": "set_eod", "_type": "eod", "_id": "20060120_TCAP-F"}}
{"symbol": "TCAP-F", "eodDate": "2006-01-20T00:00:00", "open": 14.3, "high": 14.4, "low": 14.1, "close": 14.1, "volume": 1540200, "id": "20060120_TCAP-F" }
{"index": {"_index": "set_eod", "_type": "eod", "_id": "20060120_TMB-F"}}
{"symbol": "TMB-F", "eodDate": "2006-01-20T00:00:00", "open": 5.2, "high": 5.2, "low": 5.2, "close": 5.2, "volume": 1000, "id": "20060120_TMB-F" }
{"index": {"_index": "set_eod", "_type": "eod", "_id": "20060120_ASCON"}}
{"symbol": "ASCON", "eodDate": "2006-01-20T00:00:00", "open": 3.8197, "high": 3.8918, "low": 3.6035, "close": 3.6395, "volume": 13761638, "id": "20060120_ASCON" }
{"index": {"_index": "set_eod", "_type": "eod", "_id": "20060120_BCP-DR1"}}
{"symbol": "BCP-DR1", "eodDate": "2006-01-20T00:00:00", "open": 14.2, "high": 14.3, "low": 14.1, "close": 14.1, "volume": 356000, "id": "20060120_BCP-DR1" }
{"index": {"_index": "set_eod", "_type": "eod", "_id": "20060120_BECL"}}
{"symbol": "BECL", "eodDate": "2006-01-20T00:00:00", "open": 21.9, "high": 21.9, "low": 21.8, "close": 21.8, "volume": 1099900, "id": "20060120_BECL" }
{"index": {"_index": "set_eod", "_type": "eod", "_id": "20060120_BLISS-W1"}}
{"symbol": "BLISS-W1", "eodDate": "2006-01-20T00:00:00", "open": 0.378, "high": 0.378, "low": 0.36, "close": 0.36, "volume": 323000, "id": "20060120_BLISS-W1" }
{"index": {"_index": "set_eod", "_type": "eod", "_id": "20060120_BLS"}}
{"symbol": "BLS", "eodDate": "2006-01-20T00:00:00", "open": 14.6, "high": 14.6, "low": 14, "close": 14, "volume": 6493400, "id": "20060120_BLS" }
{"index": {"_index": "set_eod", "_type": "eod", "_id": "20060120_CAWOW"}}
{"symbol": "CAWOW", "eodDate": "2006-01-20T00:00:00", "open": 7.25, "high": 7.3, "low": 7.2, "close": 7.2, "volume": 409300, "id": "20060120_CAWOW" }
{"index": {"_index": "set_eod", "_type": "eod", "_id": "20060120_CGS"}}
{"symbol": "CGS", "eodDate": "2006-01-20T00:00:00", "open": 1.6637, "high": 1.676, "low": 1.5897, "close": 1.5897, "volume": 78486384, "id": "20060120_CGS" }
{"index": {"_index": "set_eod", "_type": "eod", "_id": "20060120_CWT-W1"}}
{"symbol": "CWT-W1", "eodDate": "2006-01-20T00:00:00", "open": 2.24, "high": 2.24, "low": 2.24, "close": 2.24, "volume": 3000, "id": "20060120_CWT-W1" }
{"index": {"_index": "set_eod", "_type": "eod", "_id": "20060120_ESTAR-W1"}}
{"symbol": "ESTAR-W1", "eodDate": "2006-01-20T00:00:00", "open": 0.21, "high": 0.23, "low": 0.21, "close": 0.21, "volume": 1268414, "id": "20060120_ESTAR-W1" }
{"index": {"_index": "set_eod", "_type": "eod", "_id": "20060120_ESTAR-W2"}}
{"symbol": "ESTAR-W2", "eodDate": "2006-01-20T00:00:00", "open": 0.14, "high": 0.14, "low": 0.13, "close": 0.13, "volume": 3015900, "id": "20060120_ESTAR-W2" }
{"index": {"_index": "set_eod", "_type": "eod", "_id": "20060120_GEN-W1"}}
{"symbol": "GEN-W1", "eodDate": "2006-01-20T00:00:00", "open": 0.34, "high": 0.34, "low": 0.33, "close": 0.33, "volume": 9611600, "id": "20060120_GEN-W1" }
{"index": {"_index": "set_eod", "_type": "eod", "_id": "20060120_GFM"}}
{"symbol": "GFM", "eodDate": "2006-01-20T00:00:00", "open": 7.95, "high": 8.05, "low": 7.95, "close": 8.05, "volume": 71000, "id": "20060120_GFM" }
{"index": {"_index": "set_eod", "_type": "eod", "_id": "20060120_GJS-W1"}}
{"symbol": "GJS-W1", "eodDate": "2006-01-20T00:00:00", "open": 0.24, "high": 0.25, "low": 0.23, "close": 0.23, "volume": 31752100, "id": "20060120_GJS-W1" }
{"index": {"_index": "set_eod", "_type": "eod", "_id": "20060120_HEMRAJ"}}
{"symbol": "HEMRAJ", "eodDate": "2006-01-20T00:00:00", "open": 0.95, "high": 0.96, "low": 0.94, "close": 0.94, "volume": 50359000, "id": "20060120_HEMRAJ" }
{"index": {"_index": "set_eod", "_type": "eod", "_id": "20060120_ICBCT"}}
{"symbol": "ICBCT", "eodDate": "2006-01-20T00:00:00", "open": 6, "high": 6, "low": 5.85, "close": 5.95, "volume": 1128000, "id": "20060120_ICBCT" }
{"index": {"_index": "set_eod", "_type": "eod", "_id": "20060120_ITV"}}
{"symbol": "ITV", "eodDate": "2006-01-20T00:00:00", "open": 12, "high": 12.5, "low": 11.7, "close": 12.1, "volume": 83997504, "id": "20060120_ITV" }
{"index": {"_index": "set_eod", "_type": "eod", "_id": "20060120_KK-F"}}
{"symbol": "KK-F", "eodDate": "2006-01-20T00:00:00", "open": 34.5, "high": 35, "low": 34.25, "close": 35, "volume": 698000, "id": "20060120_KK-F" }
{"index": {"_index": "set_eod", "_type": "eod", "_id": "20060120_KTECH"}}
{"symbol": "KTECH", "eodDate": "2006-01-20T00:00:00", "open": 2.32, "high": 2.34, "low": 2.18, "close": 2.2, "volume": 4401600, "id": "20060120_KTECH" }
{"index": {"_index": "set_eod", "_type": "eod", "_id": "20060120_LHS"}}
{"symbol": "LHS", "eodDate": "2006-01-20T00:00:00", "open": 1.78, "high": 1.78, "low": 1.75, "close": 1.77, "volume": 374049, "id": "20060120_LHS" }
{"index": {"_index": "set_eod", "_type": "eod", "_id": "20060120_NNCL-W1"}}
{"symbol": "NNCL-W1", "eodDate": "2006-01-20T00:00:00", "open": 0.224, "high": 0.232, "low": 0.224, "close": 0.226, "volume": 862000, "id": "20060120_NNCL-W1" }
{"index": {"_index": "set_eod", "_type": "eod", "_id": "20060120_PHATRA"}}
{"symbol": "PHATRA", "eodDate": "2006-01-20T00:00:00", "open": 47.75, "high": 47.75, "low": 46.5, "close": 46.5, "volume": 3853800, "id": "20060120_PHATRA" }
{"index": {"_index": "set_eod", "_type": "eod", "_id": "20060120_PICNI"}}
{"symbol": "PICNI", "eodDate": "2006-01-20T00:00:00", "open": 0.9, "high": 0.93, "low": 0.84, "close": 0.85, "volume": 298612032, "id": "20060120_PICNI" }
{"index": {"_index": "set_eod", "_type": "eod", "_id": "20060120_PS"}}
{"symbol": "PS", "eodDate": "2006-01-20T00:00:00", "open": 6.9, "high": 7.15, "low": 6.55, "close": 6.6, "volume": 5706302, "id": "20060120_PS" }
{"index": {"_index": "set_eod", "_type": "eod", "_id": "20060120_PTTCH"}}
{"symbol": "PTTCH", "eodDate": "2006-01-20T00:00:00", "open": 86, "high": 88, "low": 85.5, "close": 87.5, "volume": 3456152, "id": "20060120_PTTCH" }
{"index": {"_index": "set_eod", "_type": "eod", "_id": "20060120_SAFARI"}}
{"symbol": "SAFARI", "eodDate": "2006-01-20T00:00:00", "open": 3, "high": 3.24, "low": 3, "close": 3.24, "volume": 530733, "id": "20060120_SAFARI" }
{"index": {"_index": "set_eod", "_type": "eod", "_id": "20060120_SCBLIFE"}}
{"symbol": "SCBLIFE", "eodDate": "2006-01-20T00:00:00", "open": 70, "high": 72, "low": 70, "close": 72, "volume": 3000, "id": "20060120_SCBLIFE" }
{"index": {"_index": "set_eod", "_type": "eod", "_id": "20060120_SCIB"}}
{"symbol": "SCIB", "eodDate": "2006-01-20T00:00:00", "open": 26, "high": 26.25, "low": 25.5, "close": 25.5, "volume": 8646431, "id": "20060120_SCIB" }
{"index": {"_index": "set_eod", "_type": "eod", "_id": "20060120_SCIB-F"}}
{"symbol": "SCIB-F", "eodDate": "2006-01-20T00:00:00", "open": 26.25, "high": 26.25, "low": 26, "close": 26.25, "volume": 148800, "id": "20060120_SCIB-F" }
{"index": {"_index": "set_eod", "_type": "eod", "_id": "20060120_SGF"}}
{"symbol": "SGF", "eodDate": "2006-01-20T00:00:00", "open": 0.69, "high": 0.7, "low": 0.67, "close": 0.67, "volume": 2493600, "id": "20060120_SGF" }
{"index": {"_index": "set_eod", "_type": "eod", "_id": "20060120_SICCO"}}
{"symbol": "SICCO", "eodDate": "2006-01-20T00:00:00", "open": 5.2, "high": 5.2, "low": 5.15, "close": 5.15, "volume": 1346500, "id": "20060120_SICCO" }
{"index": {"_index": "set_eod", "_type": "eod", "_id": "20060120_SINGHA"}}
{"symbol": "SINGHA", "eodDate": "2006-01-20T00:00:00", "open": 7.4806, "high": 7.5268, "low": 7.3421, "close": 7.4806, "volume": 528299, "id": "20060120_SINGHA" }
{"index": {"_index": "set_eod", "_type": "eod", "_id": "20060120_SIRIPF"}}
{"symbol": "SIRIPF", "eodDate": "2006-01-20T00:00:00", "open": 10, "high": 10, "low": 10, "close": 10, "volume": 500, "id": "20060120_SIRIPF" }
{"index": {"_index": "set_eod", "_type": "eod", "_id": "20060120_SMC"}}
{"symbol": "SMC", "eodDate": "2006-01-20T00:00:00", "open": 1.8, "high": 1.81, "low": 1.77, "close": 1.77, "volume": 120000, "id": "20060120_SMC" }
{"index": {"_index": "set_eod", "_type": "eod", "_id": "20060120_SMG"}}
{"symbol": "SMG", "eodDate": "2006-01-20T00:00:00", "open": 34.75, "high": 34.75, "low": 34.5, "close": 34.5, "volume": 10539, "id": "20060120_SMG" }
{"index": {"_index": "set_eod", "_type": "eod", "_id": "20060120_TCP"}}
{"symbol": "TCP", "eodDate": "2006-01-20T00:00:00", "open": 14.3, "high": 14.3, "low": 14.2, "close": 14.3, "volume": 44100, "id": "20060120_TCP" }
{"index": {"_index": "set_eod", "_type": "eod", "_id": "20060120_TFD-W1"}}
{"symbol": "TFD-W1", "eodDate": "2006-01-20T00:00:00", "open": 0.55, "high": 0.56, "low": 0.54, "close": 0.54, "volume": 600800, "id": "20060120_TFD-W1" }
{"index": {"_index": "set_eod", "_type": "eod", "_id": "20060120_TKS-W1"}}
{"symbol": "TKS-W1", "eodDate": "2006-01-20T00:00:00", "open": 0.69, "high": 0.7, "low": 0.68, "close": 0.69, "volume": 76020, "id": "20060120_TKS-W1" }
{"index": {"_index": "set_eod", "_type": "eod", "_id": "20060120_TSTH-W1"}}
{"symbol": "TSTH-W1", "eodDate": "2006-01-20T00:00:00", "open": 0.39, "high": 0.39, "low": 0.37, "close": 0.37, "volume": 3793000, "id": "20060120_TSTH-W1" }
{"index": {"_index": "set_eod", "_type": "eod", "_id": "20060120_TSTH-W2"}}
{"symbol": "TSTH-W2", "eodDate": "2006-01-20T00:00:00", "open": 0.17, "high": 0.18, "low": 0.16, "close": 0.16, "volume": 5435000, "id": "20060120_TSTH-W2" }
{"index": {"_index": "set_eod", "_type": "eod", "_id": "20060120_TT&T"}}
{"symbol": "TT&T", "eodDate": "2006-01-20T00:00:00", "open": 3.76, "high": 3.78, "low": 3.62, "close": 3.64, "volume": 120841472, "id": "20060120_TT&T" }
{"index": {"_index": "set_eod", "_type": "eod", "_id": "20060120_TUF-F"}}
{"symbol": "TUF-F", "eodDate": "2006-01-20T00:00:00", "open": 30.75, "high": 30.75, "low": 30.5, "close": 30.5, "volume": 48800, "id": "20060120_TUF-F" }
{"index": {"_index": "set_eod", "_type": "eod", "_id": "20060120_TWFP"}}
{"symbol": "TWFP", "eodDate": "2006-01-20T00:00:00", "open": 104, "high": 104, "low": 104, "close": 104, "volume": 500, "id": "20060120_TWFP" }
{"index": {"_index": "set_eod", "_type": "eod", "_id": "20060120_VAYU1"}}
{"symbol": "VAYU1", "eodDate": "2006-01-20T00:00:00", "open": 9.08, "high": 9.08, "low": 9.07, "close": 9.07, "volume": 149000, "id": "20060120_VAYU1" }
{"index": {"_index": "set_eod", "_type": "eod", "_id": "20060120_VGM"}}
{"symbol": "VGM", "eodDate": "2006-01-20T00:00:00", "open": 0.5525, "high": 0.559, "low": 0.5232, "close": 0.5232, "volume": 116952312, "id": "20060120_VGM" }
